Workbook

Sheet SP_INVOICE_REPORT
A1: fulfilmentDate | B1: spBookingRefNumber | C1: bookingId | D1: customerName | E1: totalPax | F1: persons | G1: netPrice | H1: status | I1: beId | J1: paymentMethod | K1: reason | M1: count
A2: 25569 | C2: 27063716 | E2: 0 | F2: { } | G2: 102.38 | H2: SP_INVOICE_ENTRY_STATUS_ALREADY_AUTO_RECONCILED | I2: 507 | K2: Reconciliation ALREADY auto reconciled | M2: =COUNTIF(RECONCILIATION_REPORT!B:B,SP_INVOICE_REPORT!C2) -> 17
A3: 25569 | C3: 27070292 | E3: 0 | F3: { } | G3: 68.25 | H3: SP_INVOICE_ENTRY_STATUS_ALREADY_AUTO_RECONCILED | I3: 507 | K3: Reconciliation ALREADY auto reconciled | M3: =COUNTIF(RECONCILIATION_REPORT!B:B,SP_INVOICE_REPORT!C3) -> 5
A4: 25569 | C4: 27070478 | E4: 0 | F4: { } | G4: 97.5 | H4: SP_INVOICE_ENTRY_STATUS_DISCREPANCY | I4: 507 | K4: Net price discrepancy | M4: =COUNTIF(RECONCILIATION_REPORT!B:B,SP_INVOICE_REPORT!C4) -> 9
A5: 25569 | C5: 27075844 | E5: 0 | F5: { } | G5: 68.25 | H5: SP_INVOICE_ENTRY_STATUS_ALREADY_AUTO_RECONCILED | I5: 507 | K5: Reconciliation ALREADY auto reconciled | M5: =COUNTIF(RECONCILIATION_REPORT!B:B,SP_INVOICE_REPORT!C5) -> 4
A6: 25569 | C6: 27079427 | E6: 0 | F6: { } | G6: 68.25 | H6: SP_INVOICE_ENTRY_STATUS_ALREADY_AUTO_RECONCILED | I6: 507 | K6: Reconciliation ALREADY auto reconciled | M6: =COUNTIF(RECONCILIATION_REPORT!B:B,SP_INVOICE_REPORT!C6) -> 2
A7: 25569 | C7: 27081400 | E7: 0 | F7: { } | G7: 68.25 | H7: SP_INVOICE_ENTRY_STATUS_ALREADY_AUTO_RECONCILED | I7: 507 | K7: Reconciliation ALREADY auto reconciled | M7: =COUNTIF(RECONCILIATION_REPORT!B:B,SP_INVOICE_REPORT!C7) -> 2
A8: 25569 | C8: 27082263 | E8: 0 | F8: { } | G8: 68.25 | H8: SP_INVOICE_ENTRY_STATUS_DISCREPANCY | I8: 507 | K8: Net price discrepancy | M8: =COUNTIF(RECONCILIATION_REPORT!B:B,SP_INVOICE_REPORT!C8) -> 1
A9: 25569 | C9: 27082886 | E9: 0 | F9: { } | G9: 68.25 | H9: SP_INVOICE_ENTRY_STATUS_DISCREPANCY | I9: 507 | K9: Net price discrepancy | M9: =COUNTIF(RECONCILIATION_REPORT!B:B,SP_INVOICE_REPORT!C9) -> 1
A10: 25569 | C10: 27084375 | E10: 0 | F10: { } | G10: 68.25 | H10: SP_INVOICE_ENTRY_STATUS_ALREADY_AUTO_RECONCILED | I10: 507 | K10: Reconciliation ALREADY auto reconciled | M10: =COUNTIF(RECONCILIATION_REPORT!B:B,SP_INVOICE_REPORT!C10) -> 2
A11: 25569 | C11: 27085550 | E11: 0 | F11: { } | G11: 68.25 | H11: SP_INVOICE_ENTRY_STATUS_ALREADY_AUTO_RECONCILED | I11: 507 | K11: Reconciliation ALREADY auto reconciled | M11: =COUNTIF(RECONCILIATION_REPORT!B:B,SP_INVOICE_REPORT!C11) -> 3
A12: 25569 | C12: 27086473 | E12: 0 | F12: { } | G12: 34.12 | H12: SP_INVOICE_ENTRY_STATUS_DISCREPANCY | I12: 507 | K12: Net price discrepancy | M12: =COUNTIF(RECONCILIATION_REPORT!B:B,SP_INVOICE_REPORT!C12) -> 1
A13: 25569 | C13: 27087029 | E13: 0 | F13: { } | G13: 68.25 | H13: SP_INVOICE_ENTRY_STATUS_ALREADY_AUTO_RECONCILED | I13: 507 | K13: Reconciliation ALREADY auto reconciled | M13: =COUNTIF(RECONCILIATION_REPORT!B:B,SP_INVOICE_REPORT!C13) -> 3
... A2371: 25569 | C2371: 28755991 | E2371: 0 | F2371: { } | G2371: 472.5 | H2371: SP_INVOICE_ENTRY_STATUS_UNRESOLVED | I2371: 507 | K2371: No matching reconciliations found | M2371: =COUNTIF(RECONCILIATION_REPORT!B:B,SP_INVOICE_REPORT!C2371) -> 1

Sheet RECONCILIATION_REPORT
A1: id | B1: bookingId | C1: fulfilmentId | D1: bookingCreationDate | E1: experienceDate | F1: fulfilmentStatus | G1: tgid | H1: tid | I1: experienceName | J1: tourName | K1: billingEntityName | L1: beId | M1: vendorName | N1: vid | O1: fulfilmentMethod | P1: paymentMethod | Q1: primaryGuestName | R1: persons | S1: paymentBasis | T1: spBookingRefNumber | U1: internalPaymentRefNumber | V1: status | W1: actor | X1: version | Y1: createdAt | Z1: updatedAt | AA1: currency | AB1: headoutSellingPrice | AC1: netPrice | AD1: extraCharges | AE1: partiallyFulfilled | AF1: bookingStatus | AG1: finalVendorId | AH1: chargedLoss | AI1: errorTeamAttribution | AJ1: errorBucket | AK1: comments | AL1: reconcileManually | AM1: reason | AN1: bnpl | AO1: insurance | AP1: spNet | AQ1: invoiceId | AR1: totalAmountPayable | AS1: netPricePayable | AT1: totalAmountPaid | AU1: concatUtr | AV1: concatDateOfPayment | AW1: enteredAmountPaid | AX1: enteredUtr | AY1: enteredDateOfPayment | AZ1: disputeStatus | BA1: totalDisputeAmount | BB1: balanceDisputeAmount | BC1: totalDisputeAdjustmentAmount | BD1: concatDisputeAmountAdjustedInvoiceId | BE1: totalDiscrepancyAmount | BF1: enteredDisputeAdjustment | BG1: enteredDisputeAmountAdjustedInvoiceId | BH1: enteredDiscrepancyAmount | BI1: reconciledNetPrice | BJ1: adult_count | BK1: adult_unit_price | BL1: adult_price_net | BM1: child_count | BN1: child_unit_price | BO1: child_price_net | BP1: general_count | BQ1: general_unit_price | BR1: general_price_net
A2: reconciliation_1525919376221305 | B2: 27063716 | C2: 13792310 | D2: 45901.212 | E2: 45907 | F2: FAILED | G2: 16051 | H2: 27596 | I2: General Admission Open Dated | K2: Louvre Abu Dhabi | L2: 507 | M2: Louvre Mueseum_Abu Dhabi | N2: 1488 | O2: SELENIUM | P2: PORTAL_DEPOSIT | Q2: Akash Jay Krishnan | R2: { "totalCount": 3, "personList": [{ "count": 3, "type": "ADULT", "priceNet": 34.13 }] } | S2: DATE_OF_BOOKING | U2: TODO | V2: RECONCILIATION_STATUS_PENDING | W2: RECON | X2: 3 | Y2: 45901.212 | Z2: 45901.869 | AA2: AED | AB2: 135 | AC2: 102.39 | AD2: { } | AE2: FALSE | AF2: COMPLETED | AH2: FALSE | AL2: FALSE | AM2: Reconciliation ALREADY auto reconciled | AZ2: NONE | BJ2: 3 | BK2: 34.13 | BL2: 102.39
A3: reconciliation_16658292957344 | B3: 27063716 | C3: 13797312 | D3: 45901.504 | E3: 45907 | F3: FAILED | G3: 16051 | H3: 27596 | I3: General Admission Open Dated | K3: Louvre Abu Dhabi | L3: 507 | M3: Louvre Mueseum_Abu Dhabi | N3: 1488 | O3: SELENIUM | P3: PORTAL_DEPOSIT | Q3: Akash Jay Krishnan | R3: { "totalCount": 3, "personList": [{ "count": 3, "type": "ADULT", "priceNet": 34.13 }] } | S3: DATE_OF_BOOKING | U3: TODO | V3: RECONCILIATION_STATUS_PENDING | W3: RECON | X3: 3 | Y3: 45901.504 | Z3: 45901.869 | AA3: AED | AB3: 135 | AC3: 102.39 | AD3: { } | AE3: FALSE | AF3: COMPLETED | AH3: FALSE | AL3: FALSE | AM3: Reconciliation ALREADY auto reconciled | AZ3: NONE | BJ3: 3 | BK3: 34.13 | BL3: 102.39
A4: reconciliation_18266063789754 | B4: 27063716 | C4: 13802649 | D4: 45901.796 | E4: 45907 | F4: FAILED | G4: 16051 | H4: 27596 | I4: General Admission Open Dated | K4: Louvre Abu Dhabi | L4: 507 | M4: Louvre Mueseum_Abu Dhabi | N4: 1488 | O4: SELENIUM | P4: PORTAL_DEPOSIT | Q4: Akash Jay Krishnan | R4: { "totalCount": 3, "personList": [{ "count": 3, "type": "ADULT", "priceNet": 34.13 }] } | S4: DATE_OF_BOOKING | U4: TODO | V4: RECONCILIATION_STATUS_PENDING | W4: RECON | X4: 3 | Y4: 45901.796 | Z4: 45901.869 | AA4: AED | AB4: 135 | AC4: 102.39 | AD4: { } | AE4: FALSE | AF4: COMPLETED | AH4: FALSE | AL4: FALSE | AM4: Reconciliation ALREADY auto reconciled | AZ4: NONE | BJ4: 3 | BK4: 34.13 | BL4: 102.39
A5: reconciliation_20237438353024 | B5: 27063716 | C5: 13798076 | D5: 45901.546 | E5: 45907 | F5: FAILED | G5: 16051 | H5: 27596 | I5: General Admission Open Dated | K5: Louvre Abu Dhabi | L5: 507 | M5: Louvre Mueseum_Abu Dhabi | N5: 1488 | O5: SELENIUM | P5: PORTAL_DEPOSIT | Q5: Akash Jay Krishnan | R5: { "totalCount": 3, "personList": [{ "count": 3, "type": "ADULT", "priceNet": 34.13 }] } | S5: DATE_OF_BOOKING | U5: TODO | V5: RECONCILIATION_STATUS_PENDING | W5: RECON | X5: 3 | Y5: 45901.546 | Z5: 45901.869 | AA5: AED | AB5: 135 | AC5: 102.39 | AD5: { } | AE5: FALSE | AF5: COMPLETED | AH5: FALSE | AL5: FALSE | AM5: Reconciliation ALREADY auto reconciled | AZ5: NONE | BJ5: 3 | BK5: 34.13 | BL5: 102.39
A6: reconciliation_203569533027365 | B6: 27063716 | C6: 13798860 | D6: 45901.587 | E6: 45907 | F6: FAILED | G6: 16051 | H6: 27596 | I6: General Admission Open Dated | K6: Louvre Abu Dhabi | L6: 507 | M6: Louvre Mueseum_Abu Dhabi | N6: 1488 | O6: SELENIUM | P6: PORTAL_DEPOSIT | Q6: Akash Jay Krishnan | R6: { "totalCount": 3, "personList": [{ "count": 3, "type": "ADULT", "priceNet": 34.13 }] } | S6: DATE_OF_BOOKING | U6: TODO | V6: RECONCILIATION_STATUS_PENDING | W6: RECON | X6: 3 | Y6: 45901.587 | Z6: 45901.869 | AA6: AED | AB6: 135 | AC6: 102.39 | AD6: { } | AE6: FALSE | AF6: COMPLETED | AH6: FALSE | AL6: FALSE | AM6: Reconciliation ALREADY auto reconciled | AZ6: NONE | BJ6: 3 | BK6: 34.13 | BL6: 102.39
A7: reconciliation_207180278419249 | B7: 27063716 | C7: 13799622 | D7: 45901.629 | E7: 45907 | F7: FAILED | G7: 16051 | H7: 27596 | I7: General Admission Open Dated | K7: Louvre Abu Dhabi | L7: 507 | M7: Louvre Mueseum_Abu Dhabi | N7: 1488 | O7: SELENIUM | P7: PORTAL_DEPOSIT | Q7: Akash Jay Krishnan | R7: { "totalCount": 3, "personList": [{ "count": 3, "type": "ADULT", "priceNet": 34.13 }] } | S7: DATE_OF_BOOKING | U7: TODO | V7: RECONCILIATION_STATUS_PENDING | W7: RECON | X7: 3 | Y7: 45901.629 | Z7: 45901.869 | AA7: AED | AB7: 135 | AC7: 102.39 | AD7: { } | AE7: FALSE | AF7: COMPLETED | AH7: FALSE | AL7: FALSE | AM7: Reconciliation ALREADY auto reconciled | AZ7: NONE | BJ7: 3 | BK7: 34.13 | BL7: 102.39
A8: reconciliation_210812054231475 | B8: 27063716 | C8: 13800383 | D8: 45901.671 | E8: 45907 | F8: FAILED | G8: 16051 | H8: 27596 | I8: General Admission Open Dated | K8: Louvre Abu Dhabi | L8: 507 | M8: Louvre Mueseum_Abu Dhabi | N8: 1488 | O8: SELENIUM | P8: PORTAL_DEPOSIT | Q8: Akash Jay Krishnan | R8: { "totalCount": 3, "personList": [{ "count": 3, "type": "ADULT", "priceNet": 34.13 }] } | S8: DATE_OF_BOOKING | U8: TODO | V8: RECONCILIATION_STATUS_PENDING | W8: RECON | X8: 3 | Y8: 45901.671 | Z8: 45901.869 | AA8: AED | AB8: 135 | AC8: 102.39 | AD8: { } | AE8: FALSE | AF8: COMPLETED | AH8: FALSE | AL8: FALSE | AM8: Reconciliation ALREADY auto reconciled | AZ8: NONE | BJ8: 3 | BK8: 34.13 | BL8: 102.39
A9: reconciliation_214365181316922 | B9: 27063716 | C9: 13801147 | D9: 45901.712 | E9: 45907 | F9: FAILED | G9: 16051 | H9: 27596 | I9: General Admission Open Dated | K9: Louvre Abu Dhabi | L9: 507 | M9: Louvre Mueseum_Abu Dhabi | N9: 1488 | O9: SELENIUM | P9: PORTAL_DEPOSIT | Q9: Akash Jay Krishnan | R9: { "totalCount": 3, "personList": [{ "count": 3, "type": "ADULT", "priceNet": 34.13 }] } | S9: DATE_OF_BOOKING | U9: TODO | V9: RECONCILIATION_STATUS_PENDING | W9: RECON | X9: 3 | Y9: 45901.712 | Z9: 45901.869 | AA9: AED | AB9: 135 | AC9: 102.39 | AD9: { } | AE9: FALSE | AF9: COMPLETED | AH9: FALSE | AL9: FALSE | AM9: Reconciliation ALREADY auto reconciled | AZ9: NONE | BJ9: 3 | BK9: 34.13 | BL9: 102.39
A10: reconciliation_215680546474750 | B10: 27063716 | C10: 13791968 | D10: 45901.157 | E10: 45907 | F10: FAILED | G10: 16051 | H10: 27596 | I10: General Admission Open Dated | K10: Louvre Abu Dhabi | L10: 507 | M10: Louvre Mueseum_Abu Dhabi | N10: 1488 | O10: SELENIUM | P10: PORTAL_DEPOSIT | Q10: Akash Jay Krishnan | R10: { "totalCount": 3, "personList": [{ "count": 3, "type": "ADULT", "priceNet": 34.13 }] } | S10: DATE_OF_BOOKING | U10: TODO | V10: RECONCILIATION_STATUS_PENDING | W10: RECON | X10: 3 | Y10: 45901.157 | Z10: 45901.869 | AA10: AED | AB10: 135 | AC10: 102.39 | AD10: { } | AE10: FALSE | AF10: COMPLETED | AH10: FALSE | AL10: FALSE | AM10: Reconciliation ALREADY auto reconciled | AZ10: NONE | BJ10: 3 | BK10: 34.13 | BL10: 102.39
A11: reconciliation_21894286540508 | B11: 27063716 | C11: 13803466 | D11: 45901.838 | E11: 45907 | F11: FAILED | G11: 16051 | H11: 27596 | I11: General Admission Open Dated | K11: Louvre Abu Dhabi | L11: 507 | M11: Louvre Mueseum_Abu Dhabi | N11: 1488 | O11: SELENIUM | P11: PORTAL_DEPOSIT | Q11: Akash Jay Krishnan | R11: { "totalCount": 3, "personList": [{ "count": 3, "type": "ADULT", "priceNet": 34.13 }] } | S11: DATE_OF_BOOKING | U11: TODO | V11: RECONCILIATION_STATUS_PENDING | W11: RECON | X11: 3 | Y11: 45901.838 | Z11: 45901.869 | AA11: AED | AB11: 135 | AC11: 102.39 | AD11: { } | AE11: FALSE | AF11: COMPLETED | AH11: FALSE | AL11: FALSE | AM11: Reconciliation ALREADY auto reconciled | AZ11: NONE | BJ11: 3 | BK11: 34.13 | BL11: 102.39
A12: reconciliation_224111901198644 | B12: 27063716 | C12: 13792613 | D12: 45901.254 | E12: 45907 | F12: FAILED | G12: 16051 | H12: 27596 | I12: General Admission Open Dated | K12: Louvre Abu Dhabi | L12: 507 | M12: Louvre Mueseum_Abu Dhabi | N12: 1488 | O12: SELENIUM | P12: PORTAL_DEPOSIT | Q12: Akash Jay Krishnan | R12: { "totalCount": 3, "personList": [{ "count": 3, "type": "ADULT", "priceNet": 34.13 }] } | S12: DATE_OF_BOOKING | U12: TODO | V12: RECONCILIATION_STATUS_PENDING | W12: RECON | X12: 3 | Y12: 45901.254 | Z12: 45901.869 | AA12: AED | AB12: 135 | AC12: 102.39 | AD12: { } | AE12: FALSE | AF12: COMPLETED | AH12: FALSE | AL12: FALSE | AM12: Reconciliation ALREADY auto reconciled | AZ12: NONE | BJ12: 3 | BK12: 34.13 | BL12: 102.39
A13: reconciliation_227700100977044 | B13: 27063716 | C13: 13793066 | D13: 45901.296 | E13: 45907 | F13: FAILED | G13: 16051 | H13: 27596 | I13: General Admission Open Dated | K13: Louvre Abu Dhabi | L13: 507 | M13: Louvre Mueseum_Abu Dhabi | N13: 1488 | O13: SELENIUM | P13: PORTAL_DEPOSIT | Q13: Akash Jay Krishnan | R13: { "totalCount": 3, "personList": [{ "count": 3, "type": "ADULT", "priceNet": 34.13 }] } | S13: DATE_OF_BOOKING | U13: TODO | V13: RECONCILIATION_STATUS_PENDING | W13: RECON | X13: 3 | Y13: 45901.296 | Z13: 45901.869 | AA13: AED | AB13: 135 | AC13: 102.39 | AD13: { } | AE13: FALSE | AF13: COMPLETED | AH13: FALSE | AL13: FALSE | AM13: Reconciliation ALREADY auto reconciled | AZ13: NONE | BJ13: 3 | BK13: 34.13 | BL13: 102.39
... A15: reconciliation_242166492675003 | B15: 27063716 | C15: 13796543 | D15: 45901.463 | E15: 45907 | F15: FAILED | G15: 16051 | H15: 27596 | I15: General Admission Open Dated | K15: Louvre Abu Dhabi | L15: 507 | M15: Louvre Mueseum_Abu Dhabi | N15: 1488 | O15: SELENIUM | P15: PORTAL_DEPOSIT | Q15: Akash Jay Krishnan | R15: { "totalCount": 3, "personList": [{ "count": 3, "type": "ADULT", "priceNet": 34.13 }] } | S15: DATE_OF_BOOKING | U15: TODO | V15: RECONCILIATION_STATUS_PENDING | W15: RECON | X15: 3 | Y15: 45901.463 | Z15: 45901.869 | AA15: AED | AB15: 135 | AC15: 102.39 | AD15: { } | AE15: FALSE | AF15: COMPLETED | AH15: FALSE | AL15: FALSE | AM15: Reconciliation ALREADY auto reconciled | AZ15: NONE | BJ15: 3 | BK15: 34.13 | BL15: 102.39
A16: reconciliation_24600200396296 | B16: 27063716 | C16: 13804039 | D16: 45901.869 | E16: 45907 | F16: SUCCESS | G16: 16051 | H16: 27596 | I16: General Admission Open Dated | K16: Louvre Abu Dhabi | L16: 507 | M16: Louvre Mueseum_Abu Dhabi | N16: 1488 | O16: MANUAL | P16: PORTAL_DEPOSIT | Q16: Akash Jay Krishnan | R16: { "totalCount": 3, "personList": [{ "count": 3, "type": "ADULT", "priceNet": 34.13 }] } | S16: DATE_OF_BOOKING | T16: ORD-2546696-Z7V8M6 | U16: TODO | V16: RECONCILIATION_STATUS_AUTO_RECONCILED | W16: RECON | X16: 2 | Y16: 45901.869 | Z16: 45902.275 | AA16: AED | AB16: 135 | AC16: 102.39 | AD16: { } | AE16: FALSE | AF16: COMPLETED | AH16: FALSE | AL16: FALSE | AM16: Reconciliation ALREADY auto reconciled | AZ16: NONE | BJ16: 3 | BK16: 34.13 | BL16: 102.39
A17: reconciliation_5861759714950 | B17: 27063716 | C17: 13794795 | D17: 45901.379 | E17: 45907 | F17: FAILED | G17: 16051 | H17: 27596 | I17: General Admission Open Dated | K17: Louvre Abu Dhabi | L17: 507 | M17: Louvre Mueseum_Abu Dhabi | N17: 1488 | O17: SELENIUM | P17: PORTAL_DEPOSIT | Q17: Akash Jay Krishnan | R17: { "totalCount": 3, "personList": [{ "count": 3, "type": "ADULT", "priceNet": 34.13 }] } | S17: DATE_OF_BOOKING | U17: TODO | V17: RECONCILIATION_STATUS_PENDING | W17: RECON | X17: 3 | Y17: 45901.379 | Z17: 45901.869 | AA17: AED | AB17: 135 | AC17: 102.39 | AD17: { } | AE17: FALSE | AF17: COMPLETED | AH17: FALSE | AL17: FALSE | AM17: Reconciliation ALREADY auto reconciled | AZ17: NONE | BJ17: 3 | BK17: 34.13 | BL17: 102.39
A18: reconciliation_9463441904114 | B18: 27063716 | C18: 13795703 | D18: 45901.421 | E18: 45907 | F18: FAILED | G18: 16051 | H18: 27596 | I18: General Admission Open Dated | K18: Louvre Abu Dhabi | L18: 507 | M18: Louvre Mueseum_Abu Dhabi | N18: 1488 | O18: SELENIUM | P18: PORTAL_DEPOSIT | Q18: Akash Jay Krishnan | R18: { "totalCount": 3, "personList": [{ "count": 3, "type": "ADULT", "priceNet": 34.13 }] } | S18: DATE_OF_BOOKING | U18: TODO | V18: RECONCILIATION_STATUS_PENDING | W18: RECON | X18: 3 | Y18: 45901.421 | Z18: 45901.869 | AA18: AED | AB18: 135 | AC18: 102.39 | AD18: { } | AE18: FALSE | AF18: COMPLETED | AH18: FALSE | AL18: FALSE | AM18: Reconciliation ALREADY auto reconciled | AZ18: NONE | BJ18: 3 | BK18: 34.13 | BL18: 102.39
A19: reconciliation_20261488274821 | B19: 27070292 | C19: 13798089 | D19: 45901.546 | E19: 45902 | F19: FAILED | G19: 16051 | H19: 27596 | I19: General Admission Open Dated | K19: Louvre Abu Dhabi | L19: 507 | M19: Louvre Mueseum_Abu Dhabi | N19: 1488 | O19: SELENIUM | P19: PORTAL_DEPOSIT | Q19: Edward Theodor Danescu | R19: { "totalCount": 2, "personList": [{ "count": 2, "type": "ADULT", "priceNet": 34.13 }] } | S19: DATE_OF_BOOKING | U19: TODO | V19: RECONCILIATION_STATUS_PENDING | W19: RECON | X19: 3 | Y19: 45901.546 | Z19: 45901.639 | AA19: AED | AB19: 90 | AC19: 68.26 | AD19: { } | AE19: FALSE | AF19: COMPLETED | AH19: FALSE | AL19: FALSE | AM19: Reconciliation ALREADY auto reconciled | AZ19: NONE | BJ19: 2 | BK19: 34.13 | BL19: 68.26
A20: reconciliation_203592560424368 | B20: 27070292 | C20: 13798865 | D20: 45901.588 | E20: 45902 | F20: FAILED | G20: 16051 | H20: 27596 | I20: General Admission Open Dated | K20: Louvre Abu Dhabi | L20: 507 | M20: Louvre Mueseum_Abu Dhabi | N20: 1488 | O20: SELENIUM | P20: PORTAL_DEPOSIT | Q20: Edward Theodor Danescu | R20: { "totalCount": 2, "personList": [{ "count": 2, "type": "ADULT", "priceNet": 34.13 }] } | S20: DATE_OF_BOOKING | U20: TODO | V20: RECONCILIATION_STATUS_PENDING | W20: RECON | X20: 3 | Y20: 45901.588 | Z20: 45901.639 | AA20: AED | AB20: 90 | AC20: 68.26 | AD20: { } | AE20: FALSE | AF20: COMPLETED | AH20: FALSE | AL20: FALSE | AM20: Reconciliation ALREADY auto reconciled | AZ20: NONE | BJ20: 2 | BK20: 34.13 | BL20: 68.26
A21: reconciliation_208053534841590 | B21: 27070292 | C21: 13799814 | D21: 45901.639 | E21: 45902 | F21: SUCCESS | G21: 16051 | H21: 27596 | I21: General Admission Open Dated | K21: Louvre Abu Dhabi | L21: 507 | M21: Louvre Mueseum_Abu Dhabi | N21: 1488 | O21: MANUAL | P21: PORTAL_DEPOSIT | Q21: Edward Theodor Danescu | R21: { "totalCount": 2, "personList": [{ "count": 2, "type": "ADULT", "priceNet": 34.13 }] } | S21: DATE_OF_BOOKING | T21: ORD-2546623-L6P1Q5 | U21: TODO | V21: RECONCILIATION_STATUS_AUTO_RECONCILED | W21: RECON | X21: 2 | Y21: 45901.639 | Z21: 45902.275 | AA21: AED | AB21: 90 | AC21: 68.26 | AD21: { } | AE21: FALSE | AF21: COMPLETED | AH21: FALSE | AL21: FALSE | AM21: Reconciliation ALREADY auto reconciled | AZ21: NONE | BJ21: 2 | BK21: 34.13 | BL21: 68.26
A22: reconciliation_245289225839154 | B22: 27070292 | C22: 13797228 | D22: 45901.499 | E22: 45902 | F22: FAILED | G22: 16051 | H22: 27596 | I22: General Admission Open Dated | K22: Louvre Abu Dhabi | L22: 507 | M22: Louvre Mueseum_Abu Dhabi | N22: 1488 | O22: SELENIUM | P22: PORTAL_DEPOSIT | Q22: Edward Theodor Danescu | R22: { "totalCount": 2, "personList": [{ "count": 2, "type": "ADULT", "priceNet": 34.13 }] } | S22: DATE_OF_BOOKING | U22: TODO | V22: RECONCILIATION_STATUS_PENDING | W22: RECON | X22: 3 | Y22: 45901.499 | Z22: 45901.639 | AA22: AED | AB22: 90 | AC22: 68.26 | AD22: { } | AE22: FALSE | AF22: COMPLETED | AH22: FALSE | AL22: FALSE | AM22: Reconciliation ALREADY auto reconciled | AZ22: NONE | BJ22: 2 | BK22: 34.13 | BL22: 68.26
A23: reconciliation_3905271371704 | B23: 27070292 | C23: 13799627 | D23: 45901.629 | E23: 45902 | F23: FAILED | G23: 16051 | H23: 27596 | I23: General Admission Open Dated | K23: Louvre Abu Dhabi | L23: 507 | M23: Louvre Mueseum_Abu Dhabi | N23: 1488 | O23: SELENIUM | P23: PORTAL_DEPOSIT | Q23: Edward Theodor Danescu | R23: { "totalCount": 2, "personList": [{ "count": 2, "type": "ADULT", "priceNet": 34.13 }] } | S23: DATE_OF_BOOKING | U23: TODO | V23: RECONCILIATION_STATUS_PENDING | W23: RECON | X23: 3 | Y23: 45901.629 | Z23: 45901.639 | AA23: AED | AB23: 90 | AC23: 68.26 | AD23: { } | AE23: FALSE | AF23: COMPLETED | AH23: FALSE | AL23: FALSE | AM23: Reconciliation ALREADY auto reconciled | AZ23: NONE | BJ23: 2 | BK23: 34.13 | BL23: 68.26
A24: reconciliation_11090198195300 | B24: 27070478 | C24: 13801153 | D24: 45901.713 | E24: 45907 | F24: FAILED | G24: 14619 | H24: 27596 | I24: General Admission Open Dated | K24: Louvre Abu Dhabi | L24: 507 | M24: Louvre Mueseum_Abu Dhabi | N24: 1488 | O24: SELENIUM | P24: PORTAL_DEPOSIT | Q24: Inesa Alikhanyan | R24: { "totalCount": 2, "personList": [{ "count": 2, "type": "ADULT", "priceNet": 34.13 }] } | S24: DATE_OF_BOOKING | U24: TODO | V24: RECONCILIATION_STATUS_PENDING | W24: RECON | X24: 3 | Y24: 45901.713 | Z24: 45901.824 | AA24: AED | AB24: 90 | AC24: 68.26 | AD24: { } | AE24: FALSE | AF24: COMPLETED | AH24: FALSE | AL24: FALSE | AM24: Net price discrepancy | AZ24: NONE | BJ24: 2 | BK24: 34.13 | BL24: 68.26
A25: reconciliation_17028536426481 | B25: 27070478 | C25: 13797405 | D25: 45901.508 | E25: 45907 | F25: FAILED | G25: 14619 | H25: 27596 | I25: General Admission Open Dated | K25: Louvre Abu Dhabi | L25: 507 | M25: Louvre Mueseum_Abu Dhabi | N25: 1488 | O25: SELENIUM | P25: PORTAL_DEPOSIT | Q25: Inesa Alikhanyan | R25: { "totalCount": 2, "personList": [{ "count": 2, "type": "ADULT", "priceNet": 34.13 }] } | S25: DATE_OF_BOOKING | U25: TODO | V25: RECONCILIATION_STATUS_PENDING | W25: RECON | X25: 3 | Y25: 45901.508 | Z25: 45901.824 | AA25: AED | AB25: 90 | AC25: 68.26 | AD25: { } | AE25: FALSE | AF25: COMPLETED | AH25: FALSE | AL25: FALSE | AM25: Net price discrepancy | AZ25: NONE | BJ25: 2 | BK25: 34.13 | BL25: 68.26
A26: reconciliation_203592579461615 | B26: 27070478 | C26: 13798866 | D26: 45901.588 | E26: 45907 | F26: FAILED | G26: 14619 | H26: 27596 | I26: General Admission Open Dated | K26: Louvre Abu Dhabi | L26: 507 | M26: Louvre Mueseum_Abu Dhabi | N26: 1488 | O26: SELENIUM | P26: PORTAL_DEPOSIT | Q26: Inesa Alikhanyan | R26: { "totalCount": 2, "personList": [{ "count": 2, "type": "ADULT", "priceNet": 34.13 }] } | S26: DATE_OF_BOOKING | U26: TODO | V26: RECONCILIATION_STATUS_PENDING | W26: RECON | X26: 3 | Y26: 45901.588 | Z26: 45901.824 | AA26: AED | AB26: 90 | AC26: 68.26 | AD26: { } | AE26: FALSE | AF26: COMPLETED | AH26: FALSE | AL26: FALSE | AM26: Net price discrepancy | AZ26: NONE | BJ26: 2 | BK26: 34.13 | BL26: 68.26
A27: reconciliation_210834598683758 | B27: 27070478 | C27: 13800387 | D27: 45901.671 | E27: 45907 | F27: FAILED | G27: 14619 | H27: 27596 | I27: General Admission Open Dated | K27: Louvre Abu Dhabi | L27: 507 | M27: Louvre Mueseum_Abu Dhabi | N27: 1488 | O27: SELENIUM | P27: PORTAL_DEPOSIT | Q27: Inesa Alikhanyan | R27: { "totalCount": 2, "personList": [{ "count": 2, "type": "ADULT", "priceNet": 34.13 }] } | S27: DATE_OF_BOOKING | U27: TODO | V27: RECONCILIATION_STATUS_PENDING | W27: RECON | X27: 3 | Y27: 45901.671 | Z27: 45901.824 | AA27: AED | AB27: 90 | AC27: 68.26 | AD27: { } | AE27: FALSE | AF27: COMPLETED | AH27: FALSE | AL27: FALSE | AM27: Net price discrepancy | AZ27: NONE | BJ27: 2 | BK27: 34.13 | BL27: 68.26
A28: reconciliation_218101659143509 | B28: 27070478 | C28: 13801905 | D28: 45901.756 | E28: 45907 | F28: FAILED | G28: 14619 | H28: 27596 | I28: General Admission Open Dated | K28: Louvre Abu Dhabi | L28: 507 | M28: Louvre Mueseum_Abu Dhabi | N28: 1488 | O28: SELENIUM | P28: PORTAL_DEPOSIT | Q28: Inesa Alikhanyan | R28: { "totalCount": 2, "personList": [{ "count": 2, "type": "ADULT", "priceNet": 34.13 }] } | S28: DATE_OF_BOOKING | U28: TODO | V28: RECONCILIATION_STATUS_PENDING | W28: RECON | X28: 3 | Y28: 45901.755 | Z28: 45901.824 | AA28: AED | AB28: 90 | AC28: 68.26 | AD28: { } | AE28: FALSE | AF28: COMPLETED | AH28: FALSE | AL28: FALSE | AM28: Net price discrepancy | AZ28: NONE | BJ28: 2 | BK28: 34.13 | BL28: 68.26
A29: reconciliation_221584146498982 | B29: 27070478 | C29: 13802658 | D29: 45901.796 | E29: 45907 | F29: FAILED | G29: 14619 | H29: 27596 | I29: General Admission Open Dated | K29: Louvre Abu Dhabi | L29: 507 | M29: Louvre Mueseum_Abu Dhabi | N29: 1488 | O29: SELENIUM | P29: PORTAL_DEPOSIT | Q29: Inesa Alikhanyan | R29: { "totalCount": 2, "personList": [{ "count": 2, "type": "ADULT", "priceNet": 34.13 }] } | S29: DATE_OF_BOOKING | U29: TODO | V29: RECONCILIATION_STATUS_PENDING | W29: RECON | X29: 3 | Y29: 45901.796 | Z29: 45901.824 | AA29: AED | AB29: 90 | AC29: 68.26 | AD29: { } | AE29: FALSE | AF29: COMPLETED | AH29: FALSE | AL29: FALSE | AM29: Net price discrepancy | AZ29: NONE | BJ29: 2 | BK29: 34.13 | BL29: 68.26
A30: reconciliation_223984442949738 | B30: 27070478 | C30: 13803170 | D30: 45901.824 | E30: 45907 | F30: SUCCESS | G30: 14619 | H30: 27596 | I30: General Admission Open Dated | K30: Louvre Abu Dhabi | L30: 507 | M30: Louvre Mueseum_Abu Dhabi | N30: 1488 | O30: MANUAL | P30: PORTAL_DEPOSIT | Q30: Inesa Alikhanyan | R30: { "totalCount": 2, "personList": [{ "count": 2, "type": "ADULT", "priceNet": 34.13 }] } | S30: DATE_OF_BOOKING | T30: ORD-2546649-R3Y6F2 | U30: TODO | V30: RECONCILIATION_STATUS_DISCREPANCY | W30: RECON | X30: 2 | Y30: 45901.824 | Z30: 45902.275 | AA30: AED | AB30: 90 | AC30: 68.26 | AD30: { } | AE30: FALSE | AF30: COMPLETED | AH30: FALSE | AL30: FALSE | AM30: Net price discrepancy | AZ30: NONE | BJ30: 2 | BK30: 34.13 | BL30: 68.26
A31: reconciliation_249314257888654 | B31: 27070478 | C31: 13798090 | D31: 45901.546 | E31: 45907 | F31: FAILED | G31: 14619 | H31: 27596 | I31: General Admission Open Dated | K31: Louvre Abu Dhabi | L31: 507 | M31: Louvre Mueseum_Abu Dhabi | N31: 1488 | O31: SELENIUM | P31: PORTAL_DEPOSIT | Q31: Inesa Alikhanyan | R31: { "totalCount": 2, "personList": [{ "count": 2, "type": "ADULT", "priceNet": 34.13 }] } | S31: DATE_OF_BOOKING | U31: TODO | V31: RECONCILIATION_STATUS_PENDING | W31: RECON | X31: 3 | Y31: 45901.546 | Z31: 45901.824 | AA31: AED | AB31: 90 | AC31: 68.26 | AD31: { } | AE31: FALSE | AF31: COMPLETED | AH31: FALSE | AL31: FALSE | AM31: Net price discrepancy | AZ31: NONE | BJ31: 2 | BK31: 34.13 | BL31: 68.26
A32: reconciliation_3905769190387 | B32: 27070478 | C32: 13799630 | D32: 45901.629 | E32: 45907 | F32: FAILED | G32: 14619 | H32: 27596 | I32: General Admission Open Dated | K32: Louvre Abu Dhabi | L32: 507 | M32: Louvre Mueseum_Abu Dhabi | N32: 1488 | O32: SELENIUM | P32: PORTAL_DEPOSIT | Q32: Inesa Alikhanyan | R32: { "totalCount": 2, "personList": [{ "count": 2, "type": "ADULT", "priceNet": 34.13 }] } | S32: DATE_OF_BOOKING | U32: TODO | V32: RECONCILIATION_STATUS_PENDING | W32: RECON | X32: 3 | Y32: 45901.629 | Z32: 45901.824 | AA32: AED | AB32: 90 | AC32: 68.26 | AD32: { } | AE32: FALSE | AF32: COMPLETED | AH32: FALSE | AL32: FALSE | AM32: Net price discrepancy | AZ32: NONE | BJ32: 2 | BK32: 34.13 | BL32: 68.26
A33: reconciliation_18293591235479 | B33: 27075844 | C33: 13802664 | D33: 45901.796 | E33: 45902 | F33: FAILED | G33: 14619 | H33: 27596 | I33: General Admission Open Dated | K33: Louvre Abu Dhabi | L33: 507 | M33: Louvre Mueseum_Abu Dhabi | N33: 1488 | O33: SELENIUM | P33: PORTAL_DEPOSIT | Q33: Ioanna stamouli | R33: { "totalCount": 2, "personList": [{ "count": 2, "type": "ADULT", "priceNet": 34.13 }] } | S33: DATE_OF_BOOKING | U33: TODO | V33: RECONCILIATION_STATUS_PENDING | W33: RECON | X33: 3 | Y33: 45901.796 | Z33: 45901.879 | AA33: AED | AB33: 90 | AC33: 68.26 | AD33: { } | AE33: FALSE | AF33: COMPLETED | AH33: FALSE | AL33: FALSE | AM33: Reconciliation ALREADY auto reconciled | AZ33: NONE | BJ33: 2 | BK33: 34.13 | BL33: 68.26
A34: reconciliation_217364686273216 | B34: 27075844 | C34: 13801764 | D34: 45901.747 | E34: 45902 | F34: FAILED | G34: 14619 | H34: 27596 | I34: General Admission Open Dated | K34: Louvre Abu Dhabi | L34: 507 | M34: Louvre Mueseum_Abu Dhabi | N34: 1488 | O34: SELENIUM | P34: PORTAL_DEPOSIT | Q34: Ioanna stamouli | R34: { "totalCount": 2, "personList": [{ "count": 2, "type": "ADULT", "priceNet": 34.13 }] } | S34: DATE_OF_BOOKING | U34: TODO | V34: RECONCILIATION_STATUS_PENDING | W34: RECON | X34: 3 | Y34: 45901.747 | Z34: 45901.879 | AA34: AED | AB34: 90 | AC34: 68.26 | AD34: { } | AE34: FALSE | AF34: COMPLETED | AH34: FALSE | AL34: FALSE | AM34: Reconciliation ALREADY auto reconciled | AZ34: NONE | BJ34: 2 | BK34: 34.13 | BL34: 68.26
A35: reconciliation_225216389714667 | B35: 27075844 | C35: 13803478 | D35: 45901.838 | E35: 45902 | F35: FAILED | G35: 14619 | H35: 27596 | I35: General Admission Open Dated | K35: Louvre Abu Dhabi | L35: 507 | M35: Louvre Mueseum_Abu Dhabi | N35: 1488 | O35: SELENIUM | P35: PORTAL_DEPOSIT | Q35: Ioanna stamouli | R35: { "totalCount": 2, "personList": [{ "count": 2, "type": "ADULT", "priceNet": 34.13 }] } | S35: DATE_OF_BOOKING | U35: TODO | V35: RECONCILIATION_STATUS_PENDING | W35: RECON | X35: 3 | Y35: 45901.838 | Z35: 45901.879 | AA35: AED | AB35: 90 | AC35: 68.26 | AD35: { } | AE35: FALSE | AF35: COMPLETED | AH35: FALSE | AL35: FALSE | AM35: Reconciliation ALREADY auto reconciled | AZ35: NONE | BJ35: 2 | BK35: 34.13 | BL35: 68.26
A36: reconciliation_25478958673280 | B36: 27075844 | C36: 13804228 | D36: 45901.879 | E36: 45902 | F36: SUCCESS | G36: 14619 | H36: 27596 | I36: General Admission Open Dated | K36: Louvre Abu Dhabi | L36: 507 | M36: Louvre Mueseum_Abu Dhabi | N36: 1488 | O36: MANUAL | P36: PORTAL_DEPOSIT | Q36: Ioanna stamouli | R36: { "totalCount": 2, "personList": [{ "count": 2, "type": "ADULT", "priceNet": 34.13 }] } | S36: DATE_OF_BOOKING | T36: ORD-2546710-B0F7D3 | U36: TODO | V36: RECONCILIATION_STATUS_AUTO_RECONCILED | W36: RECON | X36: 2 | Y36: 45901.879 | Z36: 45903.345 | AA36: AED | AB36: 90 | AC36: 68.26 | AD36: { } | AE36: FALSE | AF36: COMPLETED | AH36: FALSE | AL36: FALSE | AM36: Reconciliation ALREADY auto reconciled | AZ36: NONE | BJ36: 2 | BK36: 34.13 | BL36: 68.26
A37: reconciliation_235364756125429 | B37: 27079427 | C37: 13805198 | D37: 45901.955 | E37: 45912 | F37: SUCCESS | G37: 16051 | H37: 27596 | I37: General Admission Open Dated | K37: Louvre Abu Dhabi | L37: 507 | M37: Louvre Mueseum_Abu Dhabi | N37: 1488 | O37: MANUAL | P37: PORTAL_DEPOSIT | Q37: Andrei Ivankou | R37: { "totalCount": 2, "personList": [{ "count": 2, "type": "ADULT", "priceNet": 34.13 }] } | S37: DATE_OF_BOOKING | T37: ORD-2546715-H8M7B5 | U37: TODO | V37: RECONCILIATION_STATUS_AUTO_RECONCILED | W37: RECON | X37: 2 | Y37: 45901.955 | Z37: 45903.345 | AA37: AED | AB37: 90 | AC37: 68.26 | AD37: { } | AE37: FALSE | AF37: COMPLETED | AH37: FALSE | AL37: FALSE | AM37: Reconciliation ALREADY auto reconciled | AZ37: NONE | BJ37: 2 | BK37: 34.13 | BL37: 68.26
A38: reconciliation_28603219558905 | B38: 27079427 | C38: 13804759 | D38: 45901.915 | E38: 45912 | F38: FAILED | G38: 16051 | H38: 27596 | I38: General Admission Open Dated | K38: Louvre Abu Dhabi | L38: 507 | M38: Louvre Mueseum_Abu Dhabi | N38: 1488 | O38: SELENIUM | P38: PORTAL_DEPOSIT | Q38: Andrei Ivankou | R38: { "totalCount": 2, "personList": [{ "count": 2, "type": "ADULT", "priceNet": 34.13 }] } | S38: DATE_OF_BOOKING | U38: TODO | V38: RECONCILIATION_STATUS_PENDING | W38: RECON | X38: 3 | Y38: 45901.915 | Z38: 45901.955 | AA38: AED | AB38: 90 | AC38: 68.26 | AD38: { } | AE38: FALSE | AF38: COMPLETED | AH38: FALSE | AL38: FALSE | AM38: Reconciliation ALREADY auto reconciled | AZ38: NONE | BJ38: 2 | BK38: 34.13 | BL38: 68.26
A39: reconciliation_252054199085924 | B39: 27081400 | C39: 13806569 | D39: 45902.148 | E39: 45902 | F39: SUCCESS | G39: 14619 | H39: 27596 | I39: General Admission Open Dated | K39: Louvre Abu Dhabi | L39: 507 | M39: Louvre Mueseum_Abu Dhabi | N39: 1488 | O39: MANUAL | P39: PORTAL_DEPOSIT | Q39: josep seuma lavilla | R39: { "totalCount": 2, "personList": [{ "count": 2, "type": "ADULT", "priceNet": 34.13 }] } | S39: DATE_OF_BOOKING | T39: ORD-2546735-C2Z4W4 | U39: TODO | V39: RECONCILIATION_STATUS_AUTO_RECONCILED | W39: RECON | X39: 2 | Y39: 45902.148 | Z39: 45903.345 | AA39: AED | AB39: 90 | AC39: 68.26 | AD39: { } | AE39: FALSE | AF39: COMPLETED | AH39: FALSE | AL39: FALSE | AM39: Reconciliation ALREADY auto reconciled | AZ39: NONE | BJ39: 2 | BK39: 34.13 | BL39: 68.26
A40: reconciliation_45850829660552 | B40: 27081400 | C40: 13806367 | D40: 45902.115 | E40: 45902 | F40: FAILED | G40: 14619 | H40: 27596 | I40: General Admission Open Dated | K40: Louvre Abu Dhabi | L40: 507 | M40: Louvre Mueseum_Abu Dhabi | N40: 1488 | O40: SELENIUM | P40: PORTAL_DEPOSIT | Q40: josep seuma lavilla | R40: { "totalCount": 2, "personList": [{ "count": 2, "type": "ADULT", "priceNet": 34.13 }] } | S40: DATE_OF_BOOKING | U40: TODO | V40: RECONCILIATION_STATUS_PENDING | W40: RECON | X40: 3 | Y40: 45902.115 | Z40: 45902.148 | AA40: AED | AB40: 90 | AC40: 68.26 | AD40: { } | AE40: FALSE | AF40: COMPLETED | AH40: FALSE | AL40: FALSE | AM40: Reconciliation ALREADY auto reconciled | AZ40: NONE | BJ40: 2 | BK40: 34.13 | BL40: 68.26
A41: reconciliation_259679542622479 | B41: 27082263 | C41: 13807059 | D41: 45902.237 | E41: 45902 | F41: SUCCESS | G41: 33803 | H41: 15344 | I41: LOUVRE ABU DHABI - General Admission | K41: Louvre Abu Dhabi | L41: 507 | M41: Louvre Mueseum_Abu Dhabi | N41: 1488 | O41: MANUAL | P41: PORTAL_DEPOSIT | Q41: Nina Reichenberger | R41: { "totalCount": 4, "personList": [{ "count": 2, "type": "ADULT", "priceNet": 48.75 }, { "count": 2, "type": "CHILD" }] } | S41: DATE_OF_BOOKING | T41: ORD-2546767-W3R9P3 | U41: TODO | V41: RECONCILIATION_STATUS_DISCREPANCY | W41: RECON | X41: 4 | Y41: 45902.237 | Z41: 45903.345 | AA41: AED | AB41: 104 | AC41: 97.5 | AD41: { } | AE41: FALSE | AF41: COMPLETED | AH41: FALSE | AL41: FALSE | AM41: Net price discrepancy | AZ41: NONE | BJ41: 2 | BK41: 48.75 | BL41: 97.5 | BM41: 2 | BN41: 0 | BO41: 0
A42: reconciliation_60350424060792 | B42: 27082886 | C42: 13807555 | D42: 45902.283 | E42: 45903 | F42: SUCCESS | G42: 33803 | H42: 15344 | I42: LOUVRE ABU DHABI - General Admission | K42: Louvre Abu Dhabi | L42: 507 | M42: Louvre Mueseum_Abu Dhabi | N42: 1488 | O42: MANUAL | P42: PORTAL_DEPOSIT | Q42: lakin fish | R42: { "totalCount": 2, "personList": [{ "count": 2, "type": "ADULT", "priceNet": 48.75 }] } | S42: DATE_OF_BOOKING | T42: ORD-2546831-G6J6T5 | U42: TODO | V42: RECONCILIATION_STATUS_DISCREPANCY | W42: RECON | X42: 4 | Y42: 45902.283 | Z42: 45903.345 | AA42: AED | AB42: 104 | AC42: 97.5 | AD42: { } | AE42: FALSE | AF42: COMPLETED | AH42: FALSE | AL42: FALSE | AM42: Net price discrepancy | AZ42: NONE | BJ42: 2 | BK42: 48.75 | BL42: 97.5
A43: reconciliation_269739675712024 | B43: 27084375 | C43: 13808966 | D43: 45902.353 | E43: 45902 | F43: FAILED | G43: 14619 | H43: 27596 | I43: General Admission Open Dated | K43: Louvre Abu Dhabi | L43: 507 | M43: Louvre Mueseum_Abu Dhabi | N43: 1488 | O43: SELENIUM | P43: PORTAL_DEPOSIT | Q43: FengShu Chang | R43: { "totalCount": 2, "personList": [{ "count": 2, "type": "ADULT", "priceNet": 34.13 }] } | S43: DATE_OF_BOOKING | U43: TODO | V43: RECONCILIATION_STATUS_PENDING | W43: RECON | X43: 3 | Y43: 45902.353 | Z43: 45902.388 | AA43: AED | AB43: 90 | AC43: 68.26 | AD43: { } | AE43: FALSE | AF43: COMPLETED | AH43: FALSE | AL43: FALSE | AM43: Reconciliation ALREADY auto reconciled | AZ43: NONE | BJ43: 2 | BK43: 34.13 | BL43: 68.26
A44: reconciliation_69100442447487 | B44: 27084375 | C44: 13809703 | D44: 45902.384 | E44: 45902 | F44: SUCCESS | G44: 14619 | H44: 27596 | I44: General Admission Open Dated | K44: Louvre Abu Dhabi | L44: 507 | M44: Louvre Mueseum_Abu Dhabi | N44: 1488 | O44: MANUAL | P44: PORTAL_DEPOSIT | Q44: FengShu Chang | R44: { "totalCount": 2, "personList": [{ "count": 2, "type": "ADULT", "priceNet": 34.13 }] } | S44: DATE_OF_BOOKING | T44: ORD-2546983-N6Q8F8 | U44: TODO | V44: RECONCILIATION_STATUS_AUTO_RECONCILED | W44: RECON | X44: 2 | Y44: 45902.384 | Z44: 45903.345 | AA44: AED | AB44: 90 | AC44: 68.26 | AD44: { } | AE44: FALSE | AF44: COMPLETED | AH44: FALSE | AL44: FALSE | AM44: Reconciliation ALREADY auto reconciled | AZ44: NONE | BJ44: 2 | BK44: 34.13 | BL44: 68.26
A45: reconciliation_1116011625073 | B45: 27085550 | C45: 13810710 | D45: 45902.428 | E45: 45902 | F45: FAILED | G45: 16051 | H45: 27596 | I45: General Admission Open Dated | K45: Louvre Abu Dhabi | L45: 507 | M45: Louvre Mueseum_Abu Dhabi | N45: 1488 | O45: SELENIUM | P45: PORTAL_DEPOSIT | Q45: Pedro Daniel Lages de Almeida | R45: { "totalCount": 2, "personList": [{ "count": 2, "type": "ADULT", "priceNet": 34.13 }] } | S45: DATE_OF_BOOKING | U45: TODO | V45: RECONCILIATION_STATUS_PENDING | W45: RECON | X45: 3 | Y45: 45902.428 | Z45: 45902.437 | AA45: AED | AB45: 90 | AC45: 68.26 | AD45: { } | AE45: FALSE | AF45: COMPLETED | AH45: FALSE | AL45: FALSE | AM45: Reconciliation ALREADY auto reconciled | AZ45: NONE | BJ45: 2 | BK45: 34.13 | BL45: 68.26
A46: reconciliation_1870065975123 | B46: 27085550 | C46: 13810910 | D46: 45902.437 | E46: 45902 | F46: SUCCESS | G46: 16051 | H46: 27596 | I46: General Admission Open Dated | K46: Louvre Abu Dhabi | L46: 507 | M46: Louvre Mueseum_Abu Dhabi | N46: 1488 | O46: MANUAL | P46: PORTAL_DEPOSIT | Q46: Pedro Daniel Lages de Almeida | R46: { "totalCount": 2, "personList": [{ "count": 2, "type": "ADULT", "priceNet": 34.13 }] } | S46: DATE_OF_BOOKING | T46: ORD-2547096-D8S6T6 | U46: TODO | V46: RECONCILIATION_STATUS_AUTO_RECONCILED | W46: RECON | X46: 2 | Y46: 45902.437 | Z46: 45903.345 | AA46: AED | AB46: 90 | AC46: 68.26 | AD46: { } | AE46: FALSE | AF46: COMPLETED | AH46: FALSE | AL46: FALSE | AM46: Reconciliation ALREADY auto reconciled | AZ46: NONE | BJ46: 2 | BK46: 34.13 | BL46: 68.26
A47: reconciliation_272717133121131 | B47: 27085550 | C47: 13809801 | D47: 45902.388 | E47: 45902 | F47: FAILED | G47: 16051 | H47: 27596 | I47: General Admission Open Dated | K47: Louvre Abu Dhabi | L47: 507 | M47: Louvre Mueseum_Abu Dhabi | N47: 1488 | O47: SELENIUM | P47: PORTAL_DEPOSIT | Q47: Pedro Daniel Lages de Almeida | R47: { "totalCount": 2, "personList": [{ "count": 2, "type": "ADULT", "priceNet": 34.13 }] } | S47: DATE_OF_BOOKING | U47: TODO | V47: RECONCILIATION_STATUS_PENDING | W47: RECON | X47: 3 | Y47: 45902.388 | Z47: 45902.437 | AA47: AED | AB47: 90 | AC47: 68.26 | AD47: { } | AE47: FALSE | AF47: COMPLETED | AH47: FALSE | AL47: FALSE | AM47: Reconciliation ALREADY auto reconciled | AZ47: NONE | BJ47: 2 | BK47: 34.13 | BL47: 68.26
A48: reconciliation_275703318336606 | B48: 27086473 | C48: 13810499 | D48: 45902.419 | E48: 45902 | F48: SUCCESS | G48: 33803 | H48: 15344 | I48: LOUVRE ABU DHABI - General Admission | K48: Louvre Abu Dhabi | L48: 507 | M48: Louvre Mueseum_Abu Dhabi | N48: 1488 | O48: MANUAL | P48: PORTAL_DEPOSIT | Q48: Melanie Langbein | R48: { "totalCount": 4, "personList": [{ "count": 1, "type": "ADULT", "priceNet": 48.75 }, { "count": 3, "type": "CHILD" }] } | S48: DATE_OF_BOOKING | T48: ORD-2547034-V6Y7M0 | U48: TODO | V48: RECONCILIATION_STATUS_DISCREPANCY | W48: RECON | X48: 4 | Y48: 45902.422 | Z48: 45903.345 | AA48: AED | AB48: 52 | AC48: 48.75 | AD48: { } | AE48: FALSE | AF48: COMPLETED | AH48: FALSE | AL48: FALSE | AM48: Net price discrepancy | AZ48: NONE | BJ48: 1 | BK48: 48.75 | BL48: 48.75 | BM48: 3 | BN48: 0 | BO48: 0
A49: reconciliation_2595647088504 | B49: 27087029 | C49: 13811560 | D49: 45902.471 | E49: 45902 | F49: FAILED | G49: 14619 | H49: 27596 | I49: General Admission Open Dated | K49: Louvre Abu Dhabi | L49: 507 | M49: Louvre Mueseum_Abu Dhabi | N49: 1488 | O49: SELENIUM | P49: PORTAL_DEPOSIT | Q49: Tanishqa Modi | R49: { "totalCount": 2, "personList": [{ "count": 2, "type": "ADULT", "priceNet": 34.13 }] } | S49: DATE_OF_BOOKING | U49: TODO | V49: RECONCILIATION_STATUS_PENDING | W49: RECON | X49: 3 | Y49: 45902.471 | Z49: 45902.489 | AA49: AED | AB49: 90 | AC49: 68.26 | AD49: { } | AE49: FALSE | AF49: COMPLETED | AH49: FALSE | AL49: FALSE | AM49: Reconciliation ALREADY auto reconciled | AZ49: NONE | BJ49: 2 | BK49: 34.13 | BL49: 68.26
A50: reconciliation_277007258583607 | B50: 27087029 | C50: 13810931 | D50: 45902.437 | E50: 45902 | F50: FAILED | G50: 14619 | H50: 27596 | I50: General Admission Open Dated | K50: Louvre Abu Dhabi | L50: 507 | M50: Louvre Mueseum_Abu Dhabi | N50: 1488 | O50: SELENIUM | P50: PORTAL_DEPOSIT | Q50: Tanishqa Modi | R50: { "totalCount": 2, "personList": [{ "count": 2, "type": "ADULT", "priceNet": 34.13 }] } | S50: DATE_OF_BOOKING | U50: TODO | V50: RECONCILIATION_STATUS_PENDING | W50: RECON | X50: 3 | Y50: 45902.437 | Z50: 45902.489 | AA50: AED | AB50: 90 | AC50: 68.26 | AD50: { } | AE50: FALSE | AF50: COMPLETED | AH50: FALSE | AL50: FALSE | AM50: Reconciliation ALREADY auto reconciled | AZ50: NONE | BJ50: 2 | BK50: 34.13 | BL50: 68.26
A51: reconciliation_4092643903250 | B51: 27087029 | C51: 13812012 | D51: 45902.489 | E51: 45902 | F51: SUCCESS | G51: 14619 | H51: 27596 | I51: General Admission Open Dated | K51: Louvre Abu Dhabi | L51: 507 | M51: Louvre Mueseum_Abu Dhabi | N51: 1488 | O51: MANUAL | P51: PORTAL_DEPOSIT | Q51: Tanishqa Modi | R51: { "totalCount": 2, "personList": [{ "count": 2, "type": "ADULT", "priceNet": 34.13 }] } | S51: DATE_OF_BOOKING | T51: ORD-2547165-N4K9Q8 | U51: TODO | V51: RECONCILIATION_STATUS_AUTO_RECONCILED | W51: RECON | X51: 2 | Y51: 45902.489 | Z51: 45903.345 | AA51: AED | AB51: 90 | AC51: 68.26 | AD51: { } | AE51: FALSE | AF51: COMPLETED | AH51: FALSE | AL51: FALSE | AM51: Reconciliation ALREADY auto reconciled | AZ51: NONE | BJ51: 2 | BK51: 34.13 | BL51: 68.26
A52: reconciliation_277169083392242 | B52: 27087076 | C52: 13810973 | D52: 45902.439 | E52: 45902 | F52: FAILED | G52: 14619 | H52: 27596 | I52: General Admission Open Dated | K52: Louvre Abu Dhabi | L52: 507 | M52: Louvre Mueseum_Abu Dhabi | N52: 1488 | O52: SELENIUM | P52: PORTAL_DEPOSIT | Q52: Sajan Shrestha | R52: { "totalCount": 2, "personList": [{ "count": 2, "type": "ADULT", "priceNet": 34.13 }] } | S52: DATE_OF_BOOKING | U52: TODO | V52: RECONCILIATION_STATUS_PENDING | W52: RECON | X52: 3 | Y52: 45902.439 | Z52: 45902.467 | AA52: AED | AB52: 74.2 | AC52: 68.26 | AD52: { } | AE52: FALSE | AF52: COMPLETED | AH52: FALSE | AL52: FALSE | AM52: Net price discrepancy | AZ52: NONE | BJ52: 2 | BK52: 34.13 | BL52: 68.26
A53: reconciliation_4512158864761 | B53: 27087076 | C53: 13811501 | D53: 45902.466 | E53: 45902 | F53: SUCCESS | G53: 14619 | H53: 27596 | I53: General Admission Open Dated | K53: Louvre Abu Dhabi | L53: 507 | M53: Louvre Mueseum_Abu Dhabi | N53: 1488 | O53: MANUAL | P53: PORTAL_DEPOSIT | Q53: Sajan Shrestha | R53: { "totalCount": 2, "personList": [{ "count": 2, "type": "ADULT", "priceNet": 34.13 }] } | S53: DATE_OF_BOOKING | T53: ORD-2547114-K4G4D6 | U53: TODO | V53: RECONCILIATION_STATUS_MANUALLY_RECONCILED | W53: RECON | X53: 4 | Y53: 45902.466 | Z53: 45921.503 | AA53: AED | AB53: 74.2 | AC53: 68.89 | AD53: { } | AE53: FALSE | AF53: COMPLETED | AH53: FALSE | AK53: ok | AL53: FALSE | AM53: Net price discrepancy | AZ53: NONE | BJ53: 2 | BK53: 34.13 | BL53: 68.26
A54: reconciliation_6772034209447 | B54: 27088909 | C54: 13812515 | D54: 45902.52 | E54: 45907 | F54: SUCCESS | G54: 33803 | H54: 15344 | I54: LOUVRE ABU DHABI - General Admission | K54: Louvre Abu Dhabi | L54: 507 | M54: Louvre Mueseum_Abu Dhabi | N54: 1488 | O54: MANUAL | P54: PORTAL_DEPOSIT | Q54: Volodymyr Mukhin | R54: { "totalCount": 1, "personList": [{ "count": 1, "type": "ADULT", "priceNet": 48.75 }] } | S54: DATE_OF_BOOKING | T54: ORD-2547206-D2P3Y6 | U54: TODO | V54: RECONCILIATION_STATUS_DISCREPANCY | W54: RECON | X54: 2 | Y54: 45902.52 | Z54: 45903.345 | AA54: AED | AB54: 52 | AC54: 48.75 | AD54: { } | AE54: FALSE | AF54: COMPLETED | AH54: FALSE | AL54: FALSE | AM54: Net price discrepancy | AZ54: NONE | BJ54: 1 | BK54: 48.75 | BL54: 48.75
A55: reconciliation_6784053178670 | B55: 27088909 | C55: 13812530 | D55: 45902.52 | E55: 45907 | F55: PENDING | G55: 33803 | H55: 15344 | I55: LOUVRE ABU DHABI - General Admission | K55: Louvre Abu Dhabi | L55: 507 | M55: Louvre Mueseum_Abu Dhabi | N55: 1488 | O55: MANUAL | P55: PORTAL_DEPOSIT | Q55: Volodymyr Mukhin | R55: { "totalCount": 1, "personList": [{ "count": 1, "type": "ADULT", "priceNet": 48.75 }] } | S55: DATE_OF_BOOKING | U55: TODO | V55: RECONCILIATION_STATUS_PENDING | W55: RECON | X55: 1 | Y55: 45902.52 | Z55: 45902.52 | AA55: AED | AB55: 52 | AC55: 48.75 | AD55: { } | AE55: FALSE | AF55: COMPLETED | AH55: FALSE | AL55: FALSE | AM55: Net price discrepancy | AZ55: NONE | BJ55: 1 | BK55: 48.75 | BL55: 48.75
A56: reconciliation_1534855591783 | B56: 27089111 | C56: 13812681 | D56: 45902.525 | E56: 45903 | F56: SUCCESS | G56: 33803 | H56: 15344 | I56: LOUVRE ABU DHABI - General Admission | K56: Louvre Abu Dhabi | L56: 507 | M56: Louvre Mueseum_Abu Dhabi | N56: 1488 | O56: MANUAL | P56: PORTAL_DEPOSIT | Q56: Nene Ojima | R56: { "totalCount": 2, "personList": [{ "count": 2, "type": "ADULT", "priceNet": 48.75 }] } | S56: DATE_OF_BOOKING | T56: ORD-2547237-R2T0S1 | U56: TODO | V56: RECONCILIATION_STATUS_DISCREPANCY | W56: RECON | X56: 4 | Y56: 45902.525 | Z56: 45903.345 | AA56: AED | AB56: 104 | AC56: 97.5 | AD56: { } | AE56: FALSE | AF56: COMPLETED | AH56: FALSE | AL56: FALSE | AM56: Net price discrepancy | AZ56: NONE | BJ56: 2 | BK56: 48.75 | BL56: 97.5
A57: reconciliation_7801074722956 | B57: 27089240 | C57: 13812746 | D57: 45902.532 | E57: 45903 | F57: SUCCESS | G57: 33803 | H57: 15344 | I57: LOUVRE ABU DHABI - General Admission | K57: Louvre Abu Dhabi | L57: 507 | M57: Louvre Mueseum_Abu Dhabi | N57: 1488 | O57: MANUAL | P57: PORTAL_DEPOSIT | Q57: Jessica Crespo Fernández | R57: { "totalCount": 1, "personList": [{ "count": 1, "type": "ADULT", "priceNet": 48.75 }] } | S57: DATE_OF_BOOKING | T57: ORD-2547277-B4V0L1 | U57: TODO | V57: RECONCILIATION_STATUS_DISCREPANCY | W57: RECON | X57: 4 | Y57: 45902.532 | Z57: 45903.345 | AA57: AED | AB57: 52 | AC57: 48.75 | AD57: { } | AE57: FALSE | AF57: COMPLETED | AH57: FALSE | AL57: FALSE | AM57: Net price discrepancy | AZ57: NONE | BJ57: 1 | BK57: 48.75 | BL57: 48.75
A58: reconciliation_6101989617121 | B58: 27089392 | C58: 13813595 | D58: 45902.578 | E58: 45902 | F58: SUCCESS | G58: 14619 | H58: 27596 | I58: General Admission Open Dated | K58: Louvre Abu Dhabi | L58: 507 | M58: Louvre Mueseum_Abu Dhabi | N58: 1488 | O58: MANUAL | P58: PORTAL_DEPOSIT | Q58: Zara Ahmed | R58: { "totalCount": 1, "personList": [{ "count": 1, "type": "ADULT", "priceNet": 34.13 }] } | S58: DATE_OF_BOOKING | T58: ORD-2547279-Q9L2D4 | U58: TODO | V58: RECONCILIATION_STATUS_AUTO_RECONCILED | W58: RECON | X58: 2 | Y58: 45902.578 | Z58: 45903.345 | AA58: AED | AB58: 45 | AC58: 34.13 | AD58: { } | AE58: FALSE | AF58: COMPLETED | AH58: FALSE | AL58: FALSE | AM58: Reconciliation ALREADY auto reconciled | AZ58: NONE | BJ58: 1 | BK58: 34.13 | BL58: 34.13
A59: reconciliation_8412301011227 | B59: 27089392 | C59: 13812916 | D59: 45902.539 | E59: 45902 | F59: FAILED | G59: 14619 | H59: 27596 | I59: General Admission Open Dated | K59: Louvre Abu Dhabi | L59: 507 | M59: Louvre Mueseum_Abu Dhabi | N59: 1488 | O59: SELENIUM | P59: PORTAL_DEPOSIT | Q59: Zara Ahmed | R59: { "totalCount": 1, "personList": [{ "count": 1, "type": "ADULT", "priceNet": 34.13 }] } | S59: DATE_OF_BOOKING | U59: TODO | V59: RECONCILIATION_STATUS_PENDING | W59: RECON | X59: 3 | Y59: 45902.539 | Z59: 45902.578 | AA59: AED | AB59: 45 | AC59: 34.13 | AD59: { } | AE59: FALSE | AF59: COMPLETED | AH59: FALSE | AL59: FALSE | AM59: Reconciliation ALREADY auto reconciled | AZ59: NONE | BJ59: 1 | BK59: 34.13 | BL59: 34.13
A60: reconciliation_12182341513604 | B60: 27090280 | C60: 13813708 | D60: 45902.582 | E60: 45903 | F60: FAILED | G60: 14619 | H60: 27596 | I60: General Admission Open Dated | K60: Louvre Abu Dhabi | L60: 507 | M60: Louvre Mueseum_Abu Dhabi | N60: 1488 | O60: SELENIUM | P60: PORTAL_DEPOSIT | Q60: wonseok lee | R60: { "totalCount": 2, "personList": [{ "count": 2, "type": "ADULT", "priceNet": 34.13 }] } | S60: DATE_OF_BOOKING | U60: TODO | V60: RECONCILIATION_STATUS_PENDING | W60: RECON | X60: 3 | Y60: 45902.582 | Z60: 45902.704 | AA60: AED | AB60: 90 | AC60: 68.26 | AD60: { } | AE60: FALSE | AF60: COMPLETED | AH60: FALSE | AL60: FALSE | AM60: Reconciliation ALREADY auto reconciled | AZ60: NONE | BJ60: 2 | BK60: 34.13 | BL60: 68.26
A61: reconciliation_16293559074821 | B61: 27090280 | C61: 13814558 | D61: 45902.63 | E61: 45903 | F61: FAILED | G61: 14619 | H61: 27596 | I61: General Admission Open Dated | K61: Louvre Abu Dhabi | L61: 507 | M61: Louvre Mueseum_Abu Dhabi | N61: 1488 | O61: SELENIUM | P61: PORTAL_DEPOSIT | Q61: wonseok lee | R61: { "totalCount": 2, "personList": [{ "count": 2, "type": "ADULT", "priceNet": 34.13 }] } | S61: DATE_OF_BOOKING | U61: TODO | V61: RECONCILIATION_STATUS_PENDING | W61: RECON | X61: 3 | Y61: 45902.63 | Z61: 45902.704 | AA61: AED | AB61: 90 | AC61: 68.26 | AD61: { } | AE61: FALSE | AF61: COMPLETED | AH61: FALSE | AL61: FALSE | AM61: Reconciliation ALREADY auto reconciled | AZ61: NONE | BJ61: 2 | BK61: 34.13 | BL61: 68.26
A62: reconciliation_19920309372473 | B62: 27090280 | C62: 13815252 | D62: 45902.672 | E62: 45903 | F62: FAILED | G62: 14619 | H62: 27596 | I62: General Admission Open Dated | K62: Louvre Abu Dhabi | L62: 507 | M62: Louvre Mueseum_Abu Dhabi | N62: 1488 | O62: SELENIUM | P62: PORTAL_DEPOSIT | Q62: wonseok lee | R62: { "totalCount": 2, "personList": [{ "count": 2, "type": "ADULT", "priceNet": 34.13 }] } | S62: DATE_OF_BOOKING | U62: TODO | V62: RECONCILIATION_STATUS_PENDING | W62: RECON | X62: 3 | Y62: 45902.672 | Z62: 45902.704 | AA62: AED | AB62: 90 | AC62: 68.26 | AD62: { } | AE62: FALSE | AF62: COMPLETED | AH62: FALSE | AL62: FALSE | AM62: Reconciliation ALREADY auto reconciled | AZ62: NONE | BJ62: 2 | BK62: 34.13 | BL62: 68.26
A63: reconciliation_22687351585881 | B63: 27090280 | C63: 13815833 | D63: 45902.704 | E63: 45903 | F63: SUCCESS | G63: 14619 | H63: 27596 | I63: General Admission Open Dated | K63: Louvre Abu Dhabi | L63: 507 | M63: Louvre Mueseum_Abu Dhabi | N63: 1488 | O63: MANUAL | P63: PORTAL_DEPOSIT | Q63: wonseok lee | R63: { "totalCount": 2, "personList": [{ "count": 2, "type": "ADULT", "priceNet": 34.13 }] } | S63: DATE_OF_BOOKING | T63: ORD-2547296-F5D3C9 | U63: TODO | V63: RECONCILIATION_STATUS_AUTO_RECONCILED | W63: RECON | X63: 2 | Y63: 45902.704 | Z63: 45903.345 | AA63: AED | AB63: 90 | AC63: 68.26 | AD63: { } | AE63: FALSE | AF63: COMPLETED | AH63: FALSE | AL63: FALSE | AM63: Reconciliation ALREADY auto reconciled | AZ63: NONE | BJ63: 2 | BK63: 34.13 | BL63: 68.26
A64: reconciliation_17393585869873 | B64: 27092919 | C64: 13815929 | D64: 45902.709 | E64: 45926 | F64: SUCCESS | G64: 33803 | H64: 15344 | I64: LOUVRE ABU DHABI - General Admission | K64: Louvre Abu Dhabi | L64: 507 | M64: Louvre Mueseum_Abu Dhabi | N64: 1488 | O64: MANUAL | P64: PORTAL_DEPOSIT | Q64: Manfron Antonio | R64: { "totalCount": 2, "personList": [{ "count": 2, "type": "ADULT", "priceNet": 48.75 }] } | S64: DATE_OF_BOOKING | T64: ORD-2547366-Z2H9Q7 | U64: TODO | V64: RECONCILIATION_STATUS_AUTO_RECONCILED | W64: RECON | X64: 4 | Y64: 45902.709 | Z64: 45904.391 | AA64: AED | AB64: 104 | AC64: 97.5 | AD64: { } | AE64: FALSE | AF64: COMPLETED | AH64: FALSE | AL64: FALSE | AM64: Reconciliation ALREADY auto reconciled | AZ64: NONE | BJ64: 2 | BK64: 48.75 | BL64: 97.5
A65: reconciliation_28366040838502 | B65: 27095676 | C65: 13818235 | D65: 45902.836 | E65: 45903 | F65: FAILED | G65: 14619 | H65: 27596 | I65: General Admission Open Dated | K65: Louvre Abu Dhabi | L65: 507 | M65: Louvre Mueseum_Abu Dhabi | N65: 1488 | O65: SELENIUM | P65: PORTAL_DEPOSIT | Q65: Sudev Sivadasan Nair | R65: { "totalCount": 7, "personList": [{ "count": 7, "type": "ADULT", "priceNet": 34.13 }] } | S65: DATE_OF_BOOKING | U65: TODO | V65: RECONCILIATION_STATUS_PENDING | W65: RECON | X65: 3 | Y65: 45902.836 | Z65: 45902.992 | AA65: AED | AB65: 315 | AC65: 238.91 | AD65: { } | AE65: FALSE | AF65: COMPLETED | AH65: FALSE | AL65: FALSE | AM65: Reconciliation ALREADY auto reconciled | AZ65: NONE | BJ65: 7 | BK65: 34.13 | BL65: 238.91
A66: reconciliation_35776352867056 | B66: 27095676 | C66: 13819546 | D66: 45902.921 | E66: 45903 | F66: FAILED | G66: 14619 | H66: 27596 | I66: General Admission Open Dated | K66: Louvre Abu Dhabi | L66: 507 | M66: Louvre Mueseum_Abu Dhabi | N66: 1488 | O66: SELENIUM | P66: PORTAL_DEPOSIT | Q66: Sudev Sivadasan Nair | R66: { "totalCount": 7, "personList": [{ "count": 7, "type": "ADULT", "priceNet": 34.13 }] } | S66: DATE_OF_BOOKING | U66: TODO | V66: RECONCILIATION_STATUS_PENDING | W66: RECON | X66: 3 | Y66: 45902.921 | Z66: 45902.992 | AA66: AED | AB66: 315 | AC66: 238.91 | AD66: { } | AE66: FALSE | AF66: COMPLETED | AH66: FALSE | AL66: FALSE | AM66: Reconciliation ALREADY auto reconciled | AZ66: NONE | BJ66: 7 | BK66: 34.13 | BL66: 238.91
A67: reconciliation_37862707313212 | B67: 27095676 | C67: 13818964 | D67: 45902.879 | E67: 45903 | F67: FAILED | G67: 14619 | H67: 27596 | I67: General Admission Open Dated | K67: Louvre Abu Dhabi | L67: 507 | M67: Louvre Mueseum_Abu Dhabi | N67: 1488 | O67: SELENIUM | P67: PORTAL_DEPOSIT | Q67: Sudev Sivadasan Nair | R67: { "totalCount": 7, "personList": [{ "count": 7, "type": "ADULT", "priceNet": 34.13 }] } | S67: DATE_OF_BOOKING | U67: TODO | V67: RECONCILIATION_STATUS_PENDING | W67: RECON | X67: 3 | Y67: 45902.879 | Z67: 45902.992 | AA67: AED | AB67: 315 | AC67: 238.91 | AD67: { } | AE67: FALSE | AF67: COMPLETED | AH67: FALSE | AL67: FALSE | AM67: Reconciliation ALREADY auto reconciled | AZ67: NONE | BJ67: 7 | BK67: 34.13 | BL67: 238.91
A68: reconciliation_39356516227271 | B68: 27095676 | C68: 13819964 | D68: 45902.963 | E68: 45903 | F68: FAILED | G68: 14619 | H68: 27596 | I68: General Admission Open Dated | K68: Louvre Abu Dhabi | L68: 507 | M68: Louvre Mueseum_Abu Dhabi | N68: 1488 | O68: SELENIUM | P68: PORTAL_DEPOSIT | Q68: Sudev Sivadasan Nair | R68: { "totalCount": 7, "personList": [{ "count": 7, "type": "ADULT", "priceNet": 34.13 }] } | S68: DATE_OF_BOOKING | U68: TODO | V68: RECONCILIATION_STATUS_PENDING | W68: RECON | X68: 3 | Y68: 45902.963 | Z68: 45902.992 | AA68: AED | AB68: 315 | AC68: 238.91 | AD68: { } | AE68: FALSE | AF68: COMPLETED | AH68: FALSE | AL68: FALSE | AM68: Reconciliation ALREADY auto reconciled | AZ68: NONE | BJ68: 7 | BK68: 34.13 | BL68: 238.91
A69: reconciliation_41874061378585 | B69: 27095676 | C69: 13820172 | D69: 45902.992 | E69: 45903 | F69: SUCCESS | G69: 14619 | H69: 27596 | I69: General Admission Open Dated | K69: Louvre Abu Dhabi | L69: 507 | M69: Louvre Mueseum_Abu Dhabi | N69: 1488 | O69: MANUAL | P69: PORTAL_DEPOSIT | Q69: Sudev Sivadasan Nair | R69: { "totalCount": 7, "personList": [{ "count": 7, "type": "ADULT", "priceNet": 34.13 }] } | S69: DATE_OF_BOOKING | T69: ORD-2547375-Y9K3C0 | U69: TODO | V69: RECONCILIATION_STATUS_AUTO_RECONCILED | W69: RECON | X69: 2 | Y69: 45902.992 | Z69: 45904.391 | AA69: AED | AB69: 315 | AC69: 238.91 | AD69: { } | AE69: FALSE | AF69: COMPLETED | AH69: FALSE | AL69: FALSE | AM69: Reconciliation ALREADY auto reconciled | AZ69: NONE | BJ69: 7 | BK69: 34.13 | BL69: 238.91
A70: reconciliation_66308179592672 | B70: 27100019 | C70: 13821690 | D70: 45903.215 | E70: 45903 | F70: FAILED | G70: 14619 | H70: 27596 | I70: General Admission Open Dated | K70: Louvre Abu Dhabi | L70: 507 | M70: Louvre Mueseum_Abu Dhabi | N70: 1488 | O70: SELENIUM | P70: PORTAL_DEPOSIT | Q70: Constantin Heldman | R70: { "totalCount": 1, "personList": [{ "count": 1, "type": "ADULT", "priceNet": 34.13 }] } | S70: DATE_OF_BOOKING | U70: TODO | V70: RECONCILIATION_STATUS_PENDING | W70: RECON | X70: 3 | Y70: 45903.215 | Z70: 45903.249 | AA70: AED | AB70: 45 | AC70: 34.13 | AD70: { } | AE70: FALSE | AF70: COMPLETED | AH70: FALSE | AL70: FALSE | AM70: Reconciliation ALREADY auto reconciled | AZ70: NONE | BJ70: 1 | BK70: 34.13 | BL70: 34.13
A71: reconciliation_69823389110963 | B71: 27100019 | C71: 13821950 | D71: 45903.249 | E71: 45903 | F71: SUCCESS | G71: 14619 | H71: 27596 | I71: General Admission Open Dated | K71: Louvre Abu Dhabi | L71: 507 | M71: Louvre Mueseum_Abu Dhabi | N71: 1488 | O71: MANUAL | P71: PORTAL_DEPOSIT | Q71: Constantin Heldman | R71: { "totalCount": 1, "personList": [{ "count": 1, "type": "ADULT", "priceNet": 34.13 }] } | S71: DATE_OF_BOOKING | T71: ORD-2547397-X7Y7J8 | U71: TODO | V71: RECONCILIATION_STATUS_AUTO_RECONCILED | W71: RECON | X71: 2 | Y71: 45903.249 | Z71: 45904.391 | AA71: AED | AB71: 45 | AC71: 34.13 | AD71: { } | AE71: FALSE | AF71: COMPLETED | AH71: FALSE | AL71: FALSE | AM71: Reconciliation ALREADY auto reconciled | AZ71: NONE | BJ71: 1 | BK71: 34.13 | BL71: 34.13
A72: reconciliation_70691140736273 | B72: 27100473 | C72: 13822040 | D72: 45903.259 | E72: 45903 | F72: SUCCESS | G72: 33803 | H72: 15344 | I72: LOUVRE ABU DHABI - General Admission | K72: Louvre Abu Dhabi | L72: 507 | M72: Louvre Mueseum_Abu Dhabi | N72: 1488 | O72: MANUAL | P72: PORTAL_DEPOSIT | Q72: Ali Ashoor Ali | R72: { "totalCount": 4, "personList": [{ "count": 2, "type": "ADULT", "priceNet": 48.75 }, { "count": 2, "type": "CHILD" }] } | S72: DATE_OF_BOOKING | T72: ORD-2547440-V5Z6F4 | U72: TODO | V72: RECONCILIATION_STATUS_DISCREPANCY | W72: RECON | X72: 4 | Y72: 45903.259 | Z72: 45904.391 | AA72: AED | AB72: 104 | AC72: 97.5 | AD72: { } | AE72: FALSE | AF72: COMPLETED | AH72: FALSE | AL72: FALSE | AM72: Net price discrepancy | AZ72: NONE | BJ72: 2 | BK72: 48.75 | BL72: 97.5 | BM72: 2 | BN72: 0 | BO72: 0
A73: reconciliation_1625168607299 | B73: 27101167 | C73: 13822665 | D73: 45903.3 | E73: 45903 | F73: FAILED | G73: 14619 | H73: 27596 | I73: General Admission Open Dated | K73: Louvre Abu Dhabi | L73: 507 | M73: Louvre Mueseum_Abu Dhabi | N73: 1488 | O73: SELENIUM | P73: PORTAL_DEPOSIT | Q73: Vahan Avagyan | R73: { "totalCount": 2, "personList": [{ "count": 2, "type": "ADULT", "priceNet": 34.13 }] } | S73: DATE_OF_BOOKING | U73: TODO | V73: RECONCILIATION_STATUS_PENDING | W73: RECON | X73: 3 | Y73: 45903.3 | Z73: 45903.365 | AA73: AED | AB73: 90 | AC73: 68.26 | AD73: { } | AE73: FALSE | AF73: COMPLETED | AH73: FALSE | AL73: FALSE | AM73: Reconciliation ALREADY auto reconciled | AZ73: NONE | BJ73: 2 | BK73: 34.13 | BL73: 68.26
A74: reconciliation_7197303376518 | B74: 27101167 | C74: 13824065 | D74: 45903.365 | E74: 45903 | F74: SUCCESS | G74: 14619 | H74: 27596 | I74: General Admission Open Dated | K74: Louvre Abu Dhabi | L74: 507 | M74: Louvre Mueseum_Abu Dhabi | N74: 1488 | O74: MANUAL | P74: PORTAL_DEPOSIT | Q74: Vahan Avagyan | R74: { "totalCount": 2, "personList": [{ "count": 2, "type": "ADULT", "priceNet": 34.13 }] } | S74: DATE_OF_BOOKING | T74: ORD-2547488-Q7G4G1 | U74: TODO | V74: RECONCILIATION_STATUS_AUTO_RECONCILED | W74: RECON | X74: 2 | Y74: 45903.365 | Z74: 45904.391 | AA74: AED | AB74: 90 | AC74: 68.26 | AD74: { } | AE74: FALSE | AF74: COMPLETED | AH74: FALSE | AL74: FALSE | AM74: Reconciliation ALREADY auto reconciled | AZ74: NONE | BJ74: 2 | BK74: 34.13 | BL74: 68.26
A75: reconciliation_77493760484943 | B75: 27101167 | C75: 13823397 | D75: 45903.338 | E75: 45903 | F75: FAILED | G75: 14619 | H75: 27596 | I75: General Admission Open Dated | K75: Louvre Abu Dhabi | L75: 507 | M75: Louvre Mueseum_Abu Dhabi | N75: 1488 | O75: SELENIUM | P75: PORTAL_DEPOSIT | Q75: Vahan Avagyan | R75: { "totalCount": 2, "personList": [{ "count": 2, "type": "ADULT", "priceNet": 34.13 }] } | S75: DATE_OF_BOOKING | U75: TODO | V75: RECONCILIATION_STATUS_PENDING | W75: RECON | X75: 3 | Y75: 45903.338 | Z75: 45903.365 | AA75: AED | AB75: 90 | AC75: 68.26 | AD75: { } | AE75: FALSE | AF75: COMPLETED | AH75: FALSE | AL75: FALSE | AM75: Reconciliation ALREADY auto reconciled | AZ75: NONE | BJ75: 2 | BK75: 34.13 | BL75: 68.26
A76: reconciliation_12000422423962 | B76: 27103040 | C76: 13825367 | D76: 45903.42 | E76: 45903 | F76: FAILED | G76: 14619 | H76: 27596 | I76: General Admission Open Dated | K76: Louvre Abu Dhabi | L76: 507 | M76: Louvre Mueseum_Abu Dhabi | N76: 1488 | O76: SELENIUM | P76: PORTAL_DEPOSIT | Q76: Maiza Siwar | R76: { "totalCount": 3, "personList": [{ "count": 3, "type": "ADULT", "priceNet": 34.13 }] } | S76: DATE_OF_BOOKING | U76: TODO | V76: RECONCILIATION_STATUS_PENDING | W76: RECON | X76: 3 | Y76: 45903.42 | Z76: 45903.429 | AA76: AED | AB76: 111.3 | AC76: 102.39 | AD76: { } | AE76: FALSE | AF76: COMPLETED | AH76: FALSE | AL76: FALSE | AM76: Reconciliation ALREADY auto reconciled | AZ76: NONE | BJ76: 3 | BK76: 34.13 | BL76: 102.39
A77: reconciliation_12774954332349 | B77: 27103040 | C77: 13825557 | D77: 45903.429 | E77: 45903 | F77: SUCCESS | G77: 14619 | H77: 27596 | I77: General Admission Open Dated | K77: Louvre Abu Dhabi | L77: 507 | M77: Louvre Mueseum_Abu Dhabi | N77: 1488 | O77: MANUAL | P77: PORTAL_DEPOSIT | Q77: Maiza Siwar | R77: { "totalCount": 3, "personList": [{ "count": 3, "type": "ADULT", "priceNet": 34.13 }] } | S77: DATE_OF_BOOKING | T77: INV-2547547-Y8Q1X7 | U77: TODO | V77: RECONCILIATION_STATUS_AUTO_RECONCILED | W77: RECON | X77: 2 | Y77: 45903.429 | Z77: 45904.391 | AA77: AED | AB77: 111.3 | AC77: 102.39 | AD77: { } | AE77: FALSE | AF77: COMPLETED | AH77: FALSE | AL77: FALSE | AM77: Reconciliation ALREADY auto reconciled | AZ77: NONE | BJ77: 3 | BK77: 34.13 | BL77: 102.39
A78: reconciliation_7853143412326 | B78: 27103040 | C78: 13824210 | D78: 45903.372 | E78: 45903 | F78: FAILED | G78: 14619 | H78: 27596 | I78: General Admission Open Dated | K78: Louvre Abu Dhabi | L78: 507 | M78: Louvre Mueseum_Abu Dhabi | N78: 1488 | O78: SELENIUM | P78: PORTAL_DEPOSIT | Q78: Maiza Siwar | R78: { "totalCount": 3, "personList": [{ "count": 3, "type": "ADULT", "priceNet": 34.13 }] } | S78: DATE_OF_BOOKING | U78: TODO | V78: RECONCILIATION_STATUS_PENDING | W78: RECON | X78: 3 | Y78: 45903.372 | Z78: 45903.429 | AA78: AED | AB78: 111.3 | AC78: 102.39 | AD78: { } | AE78: FALSE | AF78: COMPLETED | AH78: FALSE | AL78: FALSE | AM78: Reconciliation ALREADY auto reconciled | AZ78: NONE | BJ78: 3 | BK78: 34.13 | BL78: 102.39
A79: reconciliation_84599940399061 | B79: 27104444 | C79: 13825359 | D79: 45903.42 | E79: 45903 | F79: SUCCESS | G79: 14619 | H79: 27596 | I79: General Admission Open Dated | K79: Louvre Abu Dhabi | L79: 507 | M79: Louvre Mueseum_Abu Dhabi | N79: 1488 | O79: SELENIUM | P79: PORTAL_DEPOSIT | Q79: Khuong Viet Hang | R79: { "totalCount": 5, "personList": [{ "count": 5, "type": "ADULT", "priceNet": 34.13 }] } | S79: DATE_OF_BOOKING | T79: ORD-2547663-J3C1L4 | U79: TODO | V79: RECONCILIATION_STATUS_AUTO_RECONCILED | W79: RECON | X79: 4 | Y79: 45903.42 | Z79: 45904.391 | AA79: AED | AB79: 225 | AC79: 170.62 | AD79: { } | AE79: FALSE | AF79: COMPLETED | AH79: FALSE | AL79: FALSE | AM79: Reconciliation ALREADY auto reconciled | AZ79: NONE | BJ79: 5 | BK79: 34.13 | BL79: 170.65
A80: reconciliation_95287307154559 | B80: 27107395 | C80: 13827878 | D80: 45903.544 | E80: 45907 | F80: SUCCESS | G80: 14619 | H80: 27596 | I80: General Admission Open Dated | K80: Louvre Abu Dhabi | L80: 507 | M80: Louvre Mueseum_Abu Dhabi | N80: 1488 | O80: SELENIUM | P80: PORTAL_DEPOSIT | Q80: Diana Sargsyan | R80: { "totalCount": 1, "personList": [{ "count": 1, "type": "ADULT", "priceNet": 34.13 }] } | S80: DATE_OF_BOOKING | T80: ORD-2547847-J0K4F2 | U80: TODO | V80: RECONCILIATION_STATUS_AUTO_RECONCILED | W80: RECON | X80: 4 | Y80: 45903.544 | Z80: 45904.391 | AA80: AED | AB80: 45 | AC80: 34.12 | AD80: { } | AE80: FALSE | AF80: COMPLETED | AH80: FALSE | AL80: FALSE | AM80: Reconciliation ALREADY auto reconciled | AZ80: NONE | BJ80: 1 | BK80: 34.13 | BL80: 34.13
A81: reconciliation_95386002455972 | B81: 27107424 | C81: 13827900 | D81: 45903.545 | E81: 45907 | F81: SUCCESS | G81: 14619 | H81: 27596 | I81: General Admission Open Dated | K81: Louvre Abu Dhabi | L81: 507 | M81: Louvre Mueseum_Abu Dhabi | N81: 1488 | O81: SELENIUM | P81: PORTAL_DEPOSIT | Q81: Noyemi Mailyan | R81: { "totalCount": 1, "personList": [{ "count": 1, "type": "ADULT", "priceNet": 34.13 }] } | S81: DATE_OF_BOOKING | T81: ORD-2547656-R1L0N6 | U81: TODO | V81: RECONCILIATION_STATUS_AUTO_RECONCILED | W81: RECON | X81: 4 | Y81: 45903.545 | Z81: 45904.391 | AA81: AED | AB81: 45 | AC81: 34.12 | AD81: { } | AE81: FALSE | AF81: COMPLETED | AH81: FALSE | AL81: FALSE | AM81: Reconciliation ALREADY auto reconciled | AZ81: NONE | BJ81: 1 | BK81: 34.13 | BL81: 34.13
A82: reconciliation_23940802883103 | B82: 27107709 | C82: 13828173 | D82: 45903.559 | E82: 45905 | F82: SUCCESS | G82: 33803 | H82: 15344 | I82: LOUVRE ABU DHABI - General Admission | K82: Louvre Abu Dhabi | L82: 507 | M82: Louvre Mueseum_Abu Dhabi | N82: 1488 | O82: MANUAL | P82: PORTAL_DEPOSIT | Q82: Aleksandr Panaetov | R82: { "totalCount": 2, "personList": [{ "count": 2, "type": "ADULT", "priceNet": 48.75 }] } | S82: DATE_OF_BOOKING | T82: ORD-2547865-H7N1H6 | U82: TODO | V82: RECONCILIATION_STATUS_DISCREPANCY | W82: RECON | X82: 4 | Y82: 45903.559 | Z82: 45904.391 | AA82: AED | AB82: 104 | AC82: 97.5 | AD82: { } | AE82: FALSE | AF82: COMPLETED | AH82: FALSE | AL82: FALSE | AM82: Net price discrepancy | AZ82: NONE | BJ82: 2 | BK82: 48.75 | BL82: 97.5
A83: reconciliation_97968168323808 | B83: 27108065 | C83: 13828467 | D83: 45903.575 | E83: 45907 | F83: SUCCESS | G83: 14619 | H83: 27596 | I83: General Admission Open Dated | K83: Louvre Abu Dhabi | L83: 507 | M83: Louvre Mueseum_Abu Dhabi | N83: 1488 | O83: SELENIUM | P83: PORTAL_DEPOSIT | Q83: Volodymyr Mukhin | R83: { "totalCount": 1, "personList": [{ "count": 1, "type": "ADULT", "priceNet": 34.13 }] } | S83: DATE_OF_BOOKING | T83: ORD-2547876-Y0F9N9 | U83: TODO | V83: RECONCILIATION_STATUS_AUTO_RECONCILED | W83: RECON | X83: 4 | Y83: 45903.575 | Z83: 45904.391 | AA83: AED | AB83: 45 | AC83: 34.12 | AD83: { } | AE83: FALSE | AF83: COMPLETED | AH83: FALSE | AL83: FALSE | AM83: Reconciliation ALREADY auto reconciled | AZ83: NONE | BJ83: 1 | BK83: 34.13 | BL83: 34.13
A84: reconciliation_27914730849673 | B84: 27108677 | C84: 13828976 | D84: 45903.605 | E84: 45912 | F84: SUCCESS | G84: 14619 | H84: 27596 | I84: General Admission Open Dated | K84: Louvre Abu Dhabi | L84: 507 | M84: Louvre Mueseum_Abu Dhabi | N84: 1488 | O84: SELENIUM | P84: PORTAL_DEPOSIT | Q84: letal buchbinder | R84: { "totalCount": 3, "personList": [{ "count": 3, "type": "ADULT", "priceNet": 34.13 }] } | S84: DATE_OF_BOOKING | T84: ORD-2547889-S8X8Y2 | U84: TODO | V84: RECONCILIATION_STATUS_AUTO_RECONCILED | W84: RECON | X84: 4 | Y84: 45903.605 | Z84: 45904.391 | AA84: AED | AB84: 135 | AC84: 102.38 | AD84: { } | AE84: FALSE | AF84: COMPLETED | AH84: FALSE | AL84: FALSE | AM84: Reconciliation ALREADY auto reconciled | AZ84: NONE | BJ84: 3 | BK84: 34.13 | BL84: 102.39
A85: reconciliation_33197268912005 | B85: 27109978 | C85: 13830024 | D85: 45903.666 | E85: 45910 | F85: SUCCESS | G85: 14619 | H85: 27596 | I85: General Admission Open Dated | K85: Louvre Abu Dhabi | L85: 507 | M85: Louvre Mueseum_Abu Dhabi | N85: 1488 | O85: SELENIUM | P85: PORTAL_DEPOSIT | Q85: Sabrine Laidouci | R85: { "totalCount": 2, "personList": [{ "count": 2, "type": "ADULT", "priceNet": 34.13 }] } | S85: DATE_OF_BOOKING | T85: ORD-2547906-K2W1L4 | U85: TODO | V85: RECONCILIATION_STATUS_AUTO_RECONCILED | W85: RECON | X85: 4 | Y85: 45903.666 | Z85: 45904.391 | AA85: AED | AB85: 90 | AC85: 68.25 | AD85: { } | AE85: FALSE | AF85: COMPLETED | AH85: FALSE | AL85: FALSE | AM85: Reconciliation ALREADY auto reconciled | AZ85: NONE | BJ85: 2 | BK85: 34.13 | BL85: 68.26
A86: reconciliation_50007340785046 | B86: 27113867 | C86: 13833360 | D86: 45903.86 | E86: 45907 | F86: SUCCESS | G86: 14619 | H86: 27596 | I86: General Admission Open Dated | K86: Louvre Abu Dhabi | L86: 507 | M86: Louvre Mueseum_Abu Dhabi | N86: 1488 | O86: SELENIUM | P86: PORTAL_DEPOSIT | Q86: Sona Turabyan | R86: { "totalCount": 1, "personList": [{ "count": 1, "type": "ADULT", "priceNet": 34.13 }] } | S86: DATE_OF_BOOKING | T86: ORD-2547951-Q4K4D1 | U86: TODO | V86: RECONCILIATION_STATUS_AUTO_RECONCILED | W86: RECON | X86: 4 | Y86: 45903.86 | Z86: 45905.394 | AA86: AED | AB86: 45 | AC86: 34.12 | AD86: { } | AE86: FALSE | AF86: COMPLETED | AH86: FALSE | AL86: FALSE | AM86: Reconciliation ALREADY auto reconciled | AZ86: NONE | BJ86: 1 | BK86: 34.13 | BL86: 34.13
A87: reconciliation_156267720635241 | B87: 27117880 | C87: 13836631 | D87: 45904.25 | E87: 45916 | F87: SUCCESS | G87: 14619 | H87: 27596 | I87: General Admission Open Dated | K87: Louvre Abu Dhabi | L87: 507 | M87: Louvre Mueseum_Abu Dhabi | N87: 1488 | O87: SELENIUM | P87: PORTAL_DEPOSIT | Q87: Sanket Sakhale | R87: { "totalCount": 2, "personList": [{ "count": 2, "type": "ADULT", "priceNet": 34.13 }] } | S87: DATE_OF_BOOKING | T87: ORD-2547986-S3G8C0 | U87: TODO | V87: RECONCILIATION_STATUS_AUTO_RECONCILED | W87: RECON | X87: 4 | Y87: 45904.25 | Z87: 45905.394 | AA87: AED | AB87: 90 | AC87: 68.25 | AD87: { } | AE87: FALSE | AF87: COMPLETED | AH87: FALSE | AL87: FALSE | AM87: Reconciliation ALREADY auto reconciled | AZ87: NONE | BJ87: 2 | BK87: 34.13 | BL87: 68.26
A88: reconciliation_84287930639223 | B88: 27117978 | C88: 13836705 | D88: 45904.257 | E88: 45906 | F88: SUCCESS | G88: 14619 | H88: 27596 | I88: General Admission Open Dated | K88: Louvre Abu Dhabi | L88: 507 | M88: Louvre Mueseum_Abu Dhabi | N88: 1488 | O88: SELENIUM | P88: PORTAL_DEPOSIT | Q88: Basharah Binti Abd Rashid | R88: { "totalCount": 2, "personList": [{ "count": 2, "type": "ADULT", "priceNet": 34.13 }] } | S88: DATE_OF_BOOKING | T88: ORD-2548031-Y4Y2T4 | U88: TODO | V88: RECONCILIATION_STATUS_AUTO_RECONCILED | W88: RECON | X88: 4 | Y88: 45904.257 | Z88: 45905.394 | AA88: AED | AB88: 90 | AC88: 68.25 | AD88: { } | AE88: FALSE | AF88: COMPLETED | AH88: FALSE | AL88: FALSE | AM88: Reconciliation ALREADY auto reconciled | AZ88: NONE | BJ88: 2 | BK88: 34.13 | BL88: 68.26
A89: reconciliation_158679057498384 | B89: 27118296 | C89: 13836996 | D89: 45904.278 | E89: 45905 | F89: SUCCESS | G89: 33803 | H89: 15344 | I89: LOUVRE ABU DHABI - General Admission | K89: Louvre Abu Dhabi | L89: 507 | M89: Louvre Mueseum_Abu Dhabi | N89: 1488 | O89: MANUAL | P89: PORTAL_DEPOSIT | Q89: Faisal Alhamad | R89: { "totalCount": 2, "personList": [{ "count": 2, "type": "ADULT", "priceNet": 48.75 }] } | S89: DATE_OF_BOOKING | T89: ORD-2548070-X8C8N7 | U89: TODO | V89: RECONCILIATION_STATUS_DISCREPANCY | W89: RECON | X89: 4 | Y89: 45904.278 | Z89: 45905.394 | AA89: AED | AB89: 104 | AC89: 97.5 | AD89: { } | AE89: FALSE | AF89: COMPLETED | AH89: FALSE | AL89: FALSE | AM89: Net price discrepancy | AZ89: NONE | BJ89: 2 | BK89: 48.75 | BL89: 97.5
A90: reconciliation_162225126465135 | B90: 27119086 | C90: 13837692 | D90: 45904.319 | E90: 45905 | F90: SUCCESS | G90: 33803 | H90: 15344 | I90: LOUVRE ABU DHABI - General Admission | K90: Louvre Abu Dhabi | L90: 507 | M90: Louvre Mueseum_Abu Dhabi | N90: 1488 | O90: MANUAL | P90: PORTAL_DEPOSIT | Q90: Jose Jean Ricardo Bautista Mora | R90: { "totalCount": 2, "personList": [{ "count": 2, "type": "ADULT", "priceNet": 48.75 }] } | S90: DATE_OF_BOOKING | T90: ORD-2548142-K3L7Y1 | U90: TODO | V90: RECONCILIATION_STATUS_DISCREPANCY | W90: RECON | X90: 4 | Y90: 45904.319 | Z90: 45905.394 | AA90: AED | AB90: 104 | AC90: 97.5 | AD90: { } | AE90: FALSE | AF90: COMPLETED | AH90: FALSE | AL90: FALSE | AM90: Net price discrepancy | AZ90: NONE | BJ90: 2 | BK90: 48.75 | BL90: 97.5
... A96: reconciliation_213176837886927 | B96: 27132271 | C96: 13848559 | D96: 45904.909 | E96: 45907 | F96: SUCCESS | G96: 14619 | H96: 27596 | I96: General Admission Open Dated | K96: Louvre Abu Dhabi | L96: 507 | M96: Louvre Mueseum_Abu Dhabi | N96: 1488 | O96: SELENIUM | P96: PORTAL_DEPOSIT | Q96: Narek Grigoryan | R96: { "totalCount": 4, "personList": [{ "count": 4, "type": "ADULT", "priceNet": 34.13 }] } | S96: DATE_OF_BOOKING | T96: ORD-2548641-Z2R2N8 | U96: TODO | V96: RECONCILIATION_STATUS_AUTO_RECONCILED | W96: RECON | X96: 4 | Y96: 45904.909 | Z96: 45908.215 | AA96: AED | AB96: 180 | AC96: 136.5 | AD96: { } | AE96: FALSE | AF96: COMPLETED | AH96: FALSE | AL96: FALSE | AM96: Reconciliation ALREADY auto reconciled | AZ96: NONE | BJ96: 4 | BK96: 34.13 | BL96: 136.52
A97: reconciliation_242906818181640 | B97: 27135549 | C97: 13851088 | D97: 45905.253 | E97: 45905 | F97: FAILED | G97: 8583 | H97: 49803 | I97: Join us Express Tour | K97: Louvre Abu Dhabi | L97: 507 | M97: Louvre Mueseum_Abu Dhabi | N97: 1488 | O97: SELENIUM | P97: PORTAL_DEPOSIT | Q97: Matthew Sen | R97: { "totalCount": 4, "personList": [{ "count": 4, "type": "GENERAL", "priceNet": 91.25 }] } | S97: DATE_OF_BOOKING | U97: TODO | V97: RECONCILIATION_STATUS_PENDING | W97: RECON | X97: 3 | Y97: 45905.253 | Z97: 45905.267 | AA97: AED | AB97: 396 | AC97: 365 | AD97: { } | AE97: FALSE | AF97: COMPLETED | AH97: FALSE | AL97: FALSE | AM97: Reconciliation ALREADY auto reconciled | AZ97: NONE | BP97: 4 | BQ97: 91.25 | BR97: 365
A98: reconciliation_244163330196418 | B98: 27135549 | C98: 13851253 | D98: 45905.267 | E98: 45905 | F98: SUCCESS | G98: 8583 | H98: 49803 | I98: Join us Express Tour | K98: Louvre Abu Dhabi | L98: 507 | M98: Louvre Mueseum_Abu Dhabi | N98: 1488 | O98: MANUAL | P98: PORTAL_DEPOSIT | Q98: Matthew Sen | R98: { "totalCount": 4, "personList": [{ "count": 4, "type": "GENERAL", "priceNet": 91.25 }] } | S98: DATE_OF_BOOKING | T98: ORD-2548669-Q7B4M2 | U98: TODO | V98: RECONCILIATION_STATUS_AUTO_RECONCILED | W98: RECON | X98: 2 | Y98: 45905.267 | Z98: 45908.215 | AA98: AED | AB98: 396 | AC98: 365 | AD98: { } | AE98: FALSE | AF98: COMPLETED | AH98: FALSE | AL98: FALSE | AM98: Reconciliation ALREADY auto reconciled | AZ98: NONE | BP98: 4 | BQ98: 91.25 | BR98: 365
A99: reconciliation_71947027405643 | B99: 27136165 | C99: 13851628 | D99: 45905.291 | E99: 45906 | F99: CANCELLED | G99: 14619 | H99: 27596 | I99: General Admission Open Dated | K99: Louvre Abu Dhabi | L99: 507 | M99: Louvre Mueseum_Abu Dhabi | N99: 1488 | O99: SELENIUM | P99: PORTAL_DEPOSIT | Q99: Rajasekar Dhanasekar | R99: { "totalCount": 2, "personList": [{ "count": 2, "type": "ADULT", "priceNet": 34.13 }] } | S99: DATE_OF_BOOKING | T99: ORD-2548779-C0T1B9 | U99: TODO | V99: RECONCILIATION_STATUS_DISCREPANCY | W99: RECON | X99: 6 | Y99: 45905.291 | Z99: 45908.215 | AA99: AED | AB99: 90 | AC99: 0 | AD99: { } | AE99: FALSE | AF99: CANCELLED | AH99: FALSE | AL99: FALSE | AM99: No successful reconciliation found against booking id | AZ99: NONE | BJ99: 2 | BK99: 34.13 | BL99: 68.26
A100: reconciliation_93284999324852 | B100: 27143021 | C100: 13857363 | D100: 45905.538 | E100: 45906 | F100: SUCCESS | G100: 14619 | H100: 27596 | I100: General Admission Open Dated | K100: Louvre Abu Dhabi | L100: 507 | M100: Louvre Mueseum_Abu Dhabi | N100: 1488 | O100: SELENIUM | P100: PORTAL_DEPOSIT | Q100: Muhammad Ahsan | R100: { "totalCount": 2, "personList": [{ "count": 2, "type": "ADULT", "priceNet": 34.13 }] } | S100: DATE_OF_BOOKING | T100: ORD-2549549-Z7Y3M9 | U100: TODO | V100: RECONCILIATION_STATUS_AUTO_RECONCILED | W100: RECON | X100: 4 | Y100: 45905.538 | Z100: 45908.215 | AA100: AED | AB100: 90 | AC100: 68.25 | AD100: { } | AE100: FALSE | AF100: COMPLETED | AH100: FALSE | AL100: FALSE | AM100: Reconciliation ALREADY auto reconciled | AZ100: NONE | BJ100: 2 | BK100: 34.13 | BL100: 68.26
A101: reconciliation_7777750083866 | B101: 27144451 | C101: 13858665 | D101: 45905.603 | E101: 45906 | F101: SUCCESS | G101: 16051 | H101: 27596 | I101: General Admission Open Dated | K101: Louvre Abu Dhabi | L101: 507 | M101: Louvre Mueseum_Abu Dhabi | N101: 1488 | O101: MANUAL | P101: PORTAL_DEPOSIT | Q101: Sandeep singh johal | R101: { "totalCount": 3, "personList": [{ "count": 3, "type": "ADULT", "priceNet": 34.13 }] } | S101: DATE_OF_BOOKING | T101: INV-2549115-Z5D5Q3 | U101: TODO | V101: RECONCILIATION_STATUS_AUTO_RECONCILED | W101: RECON | X101: 2 | Y101: 45905.603 | Z101: 45908.215 | AA101: AED | AB101: 129.27 | AC101: 102.39 | AD101: { } | AE101: FALSE | AF101: COMPLETED | AH101: FALSE | AL101: FALSE | AM101: Reconciliation ALREADY auto reconciled | AZ101: NONE | BJ101: 3 | BK101: 34.13 | BL101: 102.39
A102: reconciliation_97901208827138 | B102: 27144451 | C102: 13858425 | D102: 45905.591 | E102: 45906 | F102: FAILED | G102: 16051 | H102: 27596 | I102: General Admission Open Dated | K102: Louvre Abu Dhabi | L102: 507 | M102: Louvre Mueseum_Abu Dhabi | N102: 1488 | O102: SELENIUM | P102: PORTAL_DEPOSIT | Q102: Sandeep singh johal | R102: { "totalCount": 3, "personList": [{ "count": 3, "type": "ADULT", "priceNet": 34.13 }] } | S102: DATE_OF_BOOKING | U102: TODO | V102: RECONCILIATION_STATUS_PENDING | W102: RECON | X102: 3 | Y102: 45905.591 | Z102: 45905.603 | AA102: AED | AB102: 129.27 | AC102: 102.39 | AD102: { } | AE102: FALSE | AF102: COMPLETED | AH102: FALSE | AL102: FALSE | AM102: Reconciliation ALREADY auto reconciled | AZ102: NONE | BJ102: 3 | BK102: 34.13 | BL102: 102.39
A103: reconciliation_101242888918598 | B103: 27145344 | C103: 13859172 | D103: 45905.63 | E103: 45923 | F103: SUCCESS | G103: 14619 | H103: 27596 | I103: General Admission Open Dated | K103: Louvre Abu Dhabi | L103: 507 | M103: Louvre Mueseum_Abu Dhabi | N103: 1488 | O103: SELENIUM | P103: PORTAL_DEPOSIT | Q103: Lirika Dvoeglazova | R103: { "totalCount": 4, "personList": [{ "count": 4, "type": "ADULT", "priceNet": 34.13 }] } | S103: DATE_OF_BOOKING | T103: ORD-2549715-S1N9C3 | U103: TODO | V103: RECONCILIATION_STATUS_AUTO_RECONCILED | W103: RECON | X103: 4 | Y103: 45905.63 | Z103: 45908.215 | AA103: AED | AB103: 180 | AC103: 136.5 | AD103: { } | AE103: FALSE | AF103: COMPLETED | AH103: FALSE | AL103: FALSE | AM103: Reconciliation ALREADY auto reconciled | AZ103: NONE | BJ103: 4 | BK103: 34.13 | BL103: 136.52
A104: reconciliation_102389679617880 | B104: 27145420 | C104: 13859418 | D104: 45905.643 | E104: 45906 | F104: SUCCESS | G104: 14619 | H104: 27596 | I104: General Admission Open Dated | K104: Louvre Abu Dhabi | L104: 507 | M104: Louvre Mueseum_Abu Dhabi | N104: 1488 | O104: MANUAL | P104: PORTAL_DEPOSIT | Q104: Delailah Inohiaban | R104: { "totalCount": 3, "personList": [{ "count": 3, "type": "ADULT", "priceNet": 34.13 }] } | S104: DATE_OF_BOOKING | T104: ORD-2549720-K4F9P6 | U104: TODO | V104: RECONCILIATION_STATUS_DISCREPANCY | W104: RECON | X104: 2 | Y104: 45905.643 | Z104: 45908.215 | AA104: AED | AB104: 135 | AC104: 102.38 | AD104: { } | AE104: FALSE | AF104: COMPLETED | AH104: FALSE | AL104: FALSE | AM104: Net price discrepancy | AZ104: NONE | BJ104: 3 | BK104: 34.13 | BL104: 102.39
A105: reconciliation_10376442538552 | B105: 27145420 | C105: 13859241 | D105: 45905.633 | E105: 45906 | F105: SUCCESS | G105: 14619 | H105: 27596 | I105: General Admission Open Dated | K105: Louvre Abu Dhabi | L105: 507 | M105: Louvre Mueseum_Abu Dhabi | N105: 1488 | O105: SELENIUM | P105: PORTAL_DEPOSIT | Q105: Delailah Inohiaban | R105: { "totalCount": 3, "personList": [{ "count": 3, "type": "ADULT", "priceNet": 34.13 }] } | S105: DATE_OF_BOOKING | T105: ORD-2549720-K4F9P6 | U105: TODO | V105: RECONCILIATION_STATUS_DISCREPANCY | W105: RECON | X105: 4 | Y105: 45905.633 | Z105: 45908.215 | AA105: AED | AB105: 135 | AC105: 102.38 | AD105: { } | AE105: FALSE | AF105: COMPLETED | AH105: FALSE | AL105: FALSE | AM105: Net price discrepancy | AZ105: NONE | BJ105: 3 | BK105: 34.13 | BL105: 102.39
A106: reconciliation_11830892656825 | B106: 27146001 | C106: 13859700 | D106: 45905.659 | E106: 45907 | F106: SUCCESS | G106: 14619 | H106: 27596 | I106: General Admission Open Dated | K106: Louvre Abu Dhabi | L106: 507 | M106: Louvre Mueseum_Abu Dhabi | N106: 1488 | O106: SELENIUM | P106: PORTAL_DEPOSIT | Q106: Pedro Victor Claros Escalada | R106: { "totalCount": 2, "personList": [{ "count": 2, "type": "ADULT", "priceNet": 34.13 }] } | S106: DATE_OF_BOOKING | T106: ORD-2549751-Q7Q8Y2 | U106: TODO | V106: RECONCILIATION_STATUS_AUTO_RECONCILED | W106: RECON | X106: 4 | Y106: 45905.659 | Z106: 45908.215 | AA106: AED | AB106: 90 | AC106: 68.25 | AD106: { } | AE106: FALSE | AF106: COMPLETED | AH106: FALSE | AL106: FALSE | AM106: Reconciliation ALREADY auto reconciled | AZ106: NONE | BJ106: 2 | BK106: 34.13 | BL106: 68.26
...
