Workbook

Sheet SP Invoice Report
A1: fulfilmentDate | B1: spBookingRefNumber | C1: bookingId | D1: customerName | E1: totalPax | F1: persons | G1: netPrice | H1: status | I1: beId | J1: paymentMethod | K1: reason | L1: Ticket id | M1: Currency | N1: count
A2: 25569 | C2: 27697547 | E2: 0 | F2: { } | G2: 1973.16 | H2: SP_INVOICE_ENTRY_STATUS_DISCREPANCY | I2: 111 | K2: Net price discrepancy | M2: SGD | N2: =COUNTIF('HO data'!B:B,'SP Invoice Report'!C2) -> 1
A3: 25569 | C3: 28028088 | E3: 0 | F3: { } | G3: 565 | H3: SP_INVOICE_ENTRY_STATUS_ALREADY_MANUALLY_RECONCILED | I3: 111 | K3: Reconciliation ALREADY manually reconciled | M3: SGD | N3: =COUNTIF('HO data'!B:B,'SP Invoice Report'!C3) -> 1
A4: 25569 | C4: 28045518 | E4: 0 | F4: { } | G4: 320.28 | H4: SP_INVOICE_ENTRY_STATUS_DISCREPANCY | I4: 111 | K4: Net price discrepancy | M4: SGD | N4: =COUNTIF('HO data'!B:B,'SP Invoice Report'!C4) -> 1
A5: 25569 | C5: 28584208 | E5: 0 | F5: { } | G5: -144.27 | H5: SP_INVOICE_ENTRY_STATUS_DISCREPANCY | I5: 111 | K5: No successful reconciliation found against booking id | M5: SGD | N5: =COUNTIF('HO data'!B:B,'SP Invoice Report'!C5) -> 1
A6: 25569 | C6: 28731825 | E6: 0 | F6: { } | G6: -81.72 | H6: SP_INVOICE_ENTRY_STATUS_DISCREPANCY | I6: 111 | K6: No successful reconciliation found against booking id | M6: SGD | N6: =COUNTIF('HO data'!B:B,'SP Invoice Report'!C6) -> 1
A7: 25569 | C7: 28994240 | E7: 0 | F7: { } | G7: -74.4 | H7: SP_INVOICE_ENTRY_STATUS_DISCREPANCY | I7: 111 | K7: No successful reconciliation found against booking id | M7: SGD | N7: =COUNTIF('HO data'!B:B,'SP Invoice Report'!C7) -> 1
A8: 25569 | C8: 29003064 | E8: 0 | F8: { } | G8: 287 | H8: SP_INVOICE_ENTRY_STATUS_DISCREPANCY | I8: 111 | K8: Net price discrepancy | M8: SGD | N8: =COUNTIF('HO data'!B:B,'SP Invoice Report'!C8) -> 1
A9: 25569 | C9: 29036584 | E9: 0 | F9: { } | G9: -57.72 | H9: SP_INVOICE_ENTRY_STATUS_DISCREPANCY | I9: 111 | K9: Net price discrepancy | M9: SGD | N9: =COUNTIF('HO data'!B:B,'SP Invoice Report'!C9) -> 1
A10: 25569 | C10: 29170286 | E10: 0 | F10: { } | G10: -163.08 | H10: SP_INVOICE_ENTRY_STATUS_DISCREPANCY | I10: 111 | K10: Net price discrepancy | M10: SGD | N10: =COUNTIF('HO data'!B:B,'SP Invoice Report'!C10) -> 1
A11: 25569 | C11: 29197289 | E11: 0 | F11: { } | G11: -94.6 | H11: SP_INVOICE_ENTRY_STATUS_DISCREPANCY | I11: 111 | K11: No successful reconciliation found against booking id | M11: SGD | N11: =COUNTIF('HO data'!B:B,'SP Invoice Report'!C11) -> 1
A12: 25569 | C12: 29213576 | E12: 0 | F12: { } | G12: -99.6 | H12: SP_INVOICE_ENTRY_STATUS_DISCREPANCY | I12: 111 | K12: Net price discrepancy | M12: SGD | N12: =COUNTIF('HO data'!B:B,'SP Invoice Report'!C12) -> 1
A13: 25569 | C13: 29238696 | E13: 0 | F13: { } | G13: -166 | H13: SP_INVOICE_ENTRY_STATUS_DISCREPANCY | I13: 111 | K13: No successful reconciliation found against booking id | M13: SGD | N13: =COUNTIF('HO data'!B:B,'SP Invoice Report'!C13) -> 1
... A6749: 25569 | C6749: 29767057 | E6749: 0 | F6749: { } | G6749: 68.95 | H6749: SP_INVOICE_ENTRY_STATUS_UNRESOLVED | I6749: 111 | K6749: No matching reconciliations found | M6749: SGD | N6749: =COUNTIF('HO data'!B:B,'SP Invoice Report'!C6749) -> 0
A6750: 25569 | C6750: (blank) | E6750: 0 | F6750: { } | G6750: 208.63 | H6750: SP_INVOICE_ENTRY_STATUS_UNRESOLVED | I6750: 111 | K6750: No matching reconciliations found | M6750: SGD | N6750: =COUNTIF('HO data'!B:B,'SP Invoice Report'!C6750) -> 0

Sheet HO data
A1: id | B1: bookingId | C1: fulfilmentId | D1: bookingCreationDate | E1: experienceDate | F1: fulfilmentStatus | G1: tgid | H1: tid | I1: experienceName | J1: tourName | K1: billingEntityName | L1: beId | M1: vendorName | N1: vid | O1: fulfilmentMethod | P1: paymentMethod | Q1: primaryGuestName | R1: persons | S1: paymentBasis | T1: spBookingRefNumber | U1: internalPaymentRefNumber | V1: status | W1: actor | X1: version | Y1: createdAt | Z1: updatedAt | AA1: currency | AB1: headoutSellingPrice | AC1: netPrice | AD1: extraCharges | AE1: partiallyFulfilled | AF1: bookingStatus | AG1: finalNetPrice | AH1: finalVendorId | AI1: chargedLoss | AJ1: errorTeamAttribution | AK1: errorBucket | AL1: comments | AM1: reconcileManually | AN1: reason | AO1: adult_count | AP1: adult_unit_price | AQ1: adult_price_net | AR1: adult_non_resident_count | AS1: adult_non_resident_unit_price | AT1: adult_non_resident_price_net | AU1: child_count | AV1: child_unit_price | AW1: child_price_net | AX1: concession_count | AY1: concession_unit_price | AZ1: concession_price_net | BA1: family_2_adult_2_children_count | BB1: family_2_adult_2_children_unit_price | BC1: family_2_adult_2_children_price_net | BD1: general_count | BE1: general_unit_price | BF1: general_price_net | BG1: malaysian_adult_count | BH1: malaysian_adult_unit_price | BI1: malaysian_adult_price_net | BJ1: non_malaysian_adult_count | BK1: non_malaysian_adult_unit_price | BL1: non_malaysian_adult_price_net | BM1: non_malaysian_child_count | BN1: non_malaysian_child_unit_price | BO1: non_malaysian_child_price_net | BP1: non_malaysian_senior_count | BQ1: non_malaysian_senior_unit_price | BR1: non_malaysian_senior_price_net | BS1: senior_count | BT1: senior_unit_price | BU1: senior_price_net | BV1: youth_count | BW1: youth_unit_price | BX1: youth_price_net
A2: reconciliation_2061782626271089 | B2: 27697547 | C2: 15908597 | D2: 46044.933 | E2: 46065 | F2: SUCCESS | G2: 31276 | H2: 65471 | I2: Universal Studios Hollywood - VIP Experience | K2: BeMyGuest | L2: 111 | M2: BeMyGuest_API | N2: 2992 | O2: MANUAL | P2: PORTAL_DEPOSIT | Q2: Mariano Luis Vignolo | R2: { "totalCount": 4, "personList": [{ "count": 4, "type": "GENERAL", "priceNet": 351.0 }] } | S2: DATE_OF_BOOKING | T2: UNHN9DB | U2: TODO | V2: RECONCILIATION_STATUS_MANUALLY_RECONCILED | W2: RECON | X2: 2 | Y2: 46044.933 | Z2: 46073.389 | AA2: USD | AB2: 1560 | AC2: 1508.4 | AD2: { "extraCharges": [{ "amountInTourCurrency": 78.0, "chargeType": "PERCENTAGE", "extraChargeCode": "CONVENIENCE_FEE", "chargeValue": 5.0 }] } | AE2: FALSE | AF2: COMPLETED | AI2: FALSE | AL2: Forex | AM2: FALSE | AN2: Net price discrepancy | BD2: 4 | BE2: 351 | BF2: 1404
A3: reconciliation_1456757280455269 | B3: 28028088 | C3: 15645127 | D3: 46024.357 | E3: 46028 | F3: SUCCESS | G3: 14274 | H3: 27070 | I3: Dolphin Encounter + S.E.A. Aquarium | K3: BeMyGuest | L3: 111 | M3: BeMyGuest_API | N3: 2992 | O3: MANUAL | P3: PORTAL_DEPOSIT | Q3: Simon Cross | R3: { "totalCount": 4, "personList": [{ "count": 2, "type": "ADULT", "priceNet": 127.3 }, { "count": 2, "type": "CHILD", "priceNet": 120.3 }] } | S3: DATE_OF_BOOKING | T3: V5UVERN | U3: TODO | V3: RECONCILIATION_STATUS_MANUALLY_RECONCILED | W3: RECON | X3: 3 | Y3: 46024.357 | Z3: 46073.389 | AA3: SGD | AB3: 578 | AC3: 565 | AD3: { } | AE3: FALSE | AF3: COMPLETED | AI3: FALSE | AJ3: Inventory | AK3: Pricing | AL3: Price Mismatch | AM3: FALSE | AN3: Reconciliation ALREADY manually reconciled | AO3: 2 | AP3: 127.3 | AQ3: 254.6 | AU3: 2 | AV3: 120.3 | AW3: 240.6
A4: reconciliation_2341521479663035 | B4: 28045518 | C4: 15787789 | D4: 46034.597 | E4: 46062 | F4: SUCCESS | G4: 1214 | H4: 61933 | I4: Warner Bros. Studio Tour Hollywood - Guided Tour in Spanish | K4: BeMyGuest | L4: 111 | M4: BeMyGuest_API | N4: 2992 | O4: MANUAL | P4: PORTAL_DEPOSIT | Q4: Mariano Luis Vignolo | R4: { "totalCount": 4, "personList": [{ "count": 4, "type": "GENERAL", "priceNet": 68.24 }] } | S4: DATE_OF_BOOKING | T4: UKJQ7ZP | U4: TODO | V4: RECONCILIATION_STATUS_MANUALLY_RECONCILED | W4: RECON | X4: 3 | Y4: 46034.597 | Z4: 46073.389 | AA4: USD | AB4: 304 | AC4: 250.02 | AD4: { } | AE4: FALSE | AF4: COMPLETED | AI4: FALSE | AJ4: Inventory | AK4: Pricing | AL4: Price Mismatch | AM4: FALSE | AN4: Net price discrepancy | BD4: 4 | BE4: 68.24 | BF4: 272.96
A5: reconciliation_758187959016748 | B5: 28584208 | C5: 15003347 | D5: 45980.976 | E5: 46010 | F5: CANCELLED | G5: 14126 | H5: 26842 | I5: Museum of the Future - Admission | K5: BeMyGuest | L5: 111 | M5: BeMyGuest_API | N5: 2992 | O5: VENDOR_API | P5: PORTAL_DEPOSIT | Q5: EVGENIIA Barashova | R5: { "totalCount": 3, "personList": [{ "count": 3, "type": "ADULT", "priceNet": 135.2 }] } | S5: DATE_OF_BOOKING | T5: 37707a31-72a8-4aed-a234-6f3cde17d72d | U5: TODO | V5: RECONCILIATION_STATUS_MANUALLY_RECONCILED | W5: RECON | X5: 10 | Y5: 45980.976 | Z5: 46073.389 | AA5: AED | AB5: 507 | AC5: 0 | AD5: { } | AE5: TRUE | AF5: CANCELLED | AI5: FALSE | AL5: Refunded | AM5: FALSE | AN5: No successful reconciliation found against booking id | AO5: 3 | AP5: 135.2 | AQ5: 405.6
A6: reconciliation_110204235101463 | B6: 28731825 | C6: 15120801 | D6: 45990.637 | E6: 46047 | F6: CANCELLED | G6: 31468 | H6: 63735 | I6: Central Park Zoo - Admission | K6: BeMyGuest | L6: 111 | M6: BeMyGuest_API | N6: 2992 | O6: VENDOR_API | P6: PORTAL_DEPOSIT | Q6: Elvin soto medina | R6: { "totalCount": 4, "personList": [{ "count": 2, "type": "ADULT", "priceNet": 18.06 }, { "count": 2, "type": "CHILD", "priceNet": 13.45 }] } | S6: DATE_OF_BOOKING | T6: cd014b5c-80b1-49bc-981b-388934017ac9 | U6: TODO | V6: RECONCILIATION_STATUS_MANUALLY_RECONCILED | W6: RECON | X6: 10 | Y6: 45990.637 | Z6: 46073.389 | AA6: USD | AB6: 64.4 | AC6: 0 | AD6: { "extraCharges": [{ "amountInTourCurrency": 12.0, "chargeType": "ABSOLUTE", "extraChargeCode": "CONVENIENCE_FEE", "chargeValue": 3.0 }] } | AE6: TRUE | AF6: CANCELLED | AI6: FALSE | AL6: Refunded | AM6: FALSE | AN6: No successful reconciliation found against booking id | AO6: 2 | AP6: 18.06 | AQ6: 36.12 | AU6: 2 | AV6: 13.45 | AW6: 26.9
A7: reconciliation_14969088203100 | B7: 28994240 | C7: 15332595 | D7: 46006.644 | E7: 46023 | F7: CANCELLED | G7: 7371 | H7: 55603 | I7: Marina Bay Sands SkyPark Observation Deck - Admission (Timeslot Entry from 5:00 PM) | K7: BeMyGuest | L7: 111 | M7: BeMyGuest_API | N7: 2992 | O7: VENDOR_API | P7: PORTAL_DEPOSIT | Q7: Andre Peter Lukoschat | R7: { "totalCount": 2, "personList": [{ "count": 2, "type": "ADULT", "priceNet": 37.2 }] } | S7: DATE_OF_BOOKING | T7: 3216880c-a285-4c55-8b03-89c61a624c19 | U7: TODO | V7: RECONCILIATION_STATUS_MANUALLY_RECONCILED | W7: RECON | X7: 11 | Y7: 46006.644 | Z7: 46073.389 | AA7: SGD | AB7: 78 | AC7: 0 | AD7: { "extraCharges": [{ "amountInTourCurrency": 7.8, "chargeType": "PERCENTAGE", "extraChargeCode": "CONVENIENCE_FEE", "chargeValue": 10.0 }] } | AE7: TRUE | AF7: CANCELLED | AI7: FALSE | AL7: Refunded | AM7: FALSE | AN7: No successful reconciliation found against booking id | AO7: 2 | AP7: 37.2 | AQ7: 74.4
A8: reconciliation_2502688021939251 | B8: 29003064 | C8: 15733734 | D8: 46030.477 | E8: 46032 | F8: SUCCESS | G8: 21554 | H8: 42293 | I8: Lunch at Eiffel Tower's Madame Brasserie - Madame Menu with Drinks | K8: BeMyGuest | L8: 111 | M8: BeMyGuest_API | N8: 2992 | O8: MANUAL | P8: HEADOUT_STANDARD_REPORTING | Q8: SOUCHON SEBASTIEN | R8: { "totalCount": 2, "personList": [{ "count": 2, "type": "ADULT", "priceNet": 91.27 }] } | S8: DATE_OF_BOOKING | T8: SU8X2E4 | U8: TODO | V8: RECONCILIATION_STATUS_MANUALLY_RECONCILED | W8: RECON | X8: 2 | Y8: 46030.477 | Z8: 46073.389 | AA8: EUR | AB8: 200.6 | AC8: 190.92 | AD8: { } | AE8: FALSE | AF8: COMPLETED | AI8: FALSE | AL8: Reconciled | AM8: FALSE | AN8: Net price discrepancy | AO8: 2 | AP8: 91.27 | AQ8: 182.54
A9: reconciliation_662306821688034 | B9: 29036584 | C9: 15364545 | D9: 46009.176 | E9: 46009 | F9: SUCCESS | G9: 11873 | H9: 22709 | I9: SkyPoint Observation Deck - Admission | K9: BeMyGuest | L9: 111 | M9: BeMyGuest_API | N9: 2992 | O9: VENDOR_API | P9: PORTAL_DEPOSIT | Q9: Sandhya Bhandari | R9: { "totalCount": 3, "personList": [{ "count": 3, "type": "ADULT", "priceNet": 22.58 }] } | S9: DATE_OF_BOOKING | T9: 65a6c659-08c5-46bb-b24b-4629760b9a85 | U9: TODO | V9: RECONCILIATION_STATUS_MANUALLY_RECONCILED | W9: RECON | X9: 9 | Y9: 46009.176 | Z9: 46073.389 | AA9: AUD | AB9: 96.78 | AC9: 0 | AD9: { } | AE9: TRUE | AF9: CANCELLED | AI9: FALSE | AL9: Refunded | AM9: FALSE | AN9: Net price discrepancy | AO9: 3 | AP9: 22.58 | AQ9: 67.74
A10: reconciliation_1230771134651821 | B10: 29170286 | C10: 15469696 | D10: 46015.756 | E10: 46024 | F10: SUCCESS | G10: 10055 | H10: 18487 | I10: Dubai Mega Yacht Dinner Cruise (Food and Soft Drinks Package) | K10: BeMyGuest | L10: 111 | M10: BeMyGuest_API | N10: 2992 | O10: VENDOR_API | P10: PORTAL_DEPOSIT | Q10: Awatif Rabbani | R10: { "totalCount": 2, "personList": [{ "count": 2, "type": "ADULT", "priceNet": 233.22 }] } | S10: DATE_OF_BOOKING | T10: 5222196a-6d89-45a9-b793-9a677fca5053 | U10: TODO | V10: RECONCILIATION_STATUS_AUTO_RECONCILED | W10: RECON | X10: 7 | Y10: 46015.756 | Z10: 46073.389 | AA10: AED | AB10: 598 | AC10: 0 | AD10: { } | AE10: TRUE | AF10: COMPLETED | AI10: FALSE | AL10: Refunded | AM10: FALSE | AN10: Net price discrepancy | AO10: 2 | AP10: 233.22 | AQ10: 466.44
A11: reconciliation_1345474853876359 | B11: 29197289 | C11: 15490331 | D11: 46017.083 | E11: 46017 | F11: CANCELLED | G11: 7371 | H11: 13460 | I11: Marina Bay Sands SkyPark Observation Deck - Admission (Entry until 4:00 PM) | K11: BeMyGuest | L11: 111 | M11: BeMyGuest_API | N11: 2992 | O11: VENDOR_API | P11: PORTAL_DEPOSIT | Q11: Marc Latournarie | R11: { "totalCount": 3, "personList": [{ "count": 2, "type": "ADULT", "priceNet": 33.2 }, { "count": 1, "type": "SENIOR", "priceNet": 28.2 }] } | S11: DATE_OF_BOOKING | T11: 844b492b-88ca-437c-b8a6-33c65f56fa2f | U11: TODO | V11: RECONCILIATION_STATUS_MANUALLY_RECONCILED | W11: RECON | X11: 11 | Y11: 46017.083 | Z11: 46073.389 | AA11: SGD | AB11: 101 | AC11: 0 | AD11: { "extraCharges": [{ "amountInTourCurrency": 10.1, "chargeType": "PERCENTAGE", "extraChargeCode": "CONVENIENCE_FEE", "chargeValue": 10.0 }] } | AE11: TRUE | AF11: CANCELLED | AI11: FALSE | AL11: Refunded | AM11: FALSE | AN11: No successful reconciliation found against booking id | AO11: 2 | AP11: 33.2 | AQ11: 66.4 | BS11: 1 | BT11: 28.2 | BU11: 28.2
A12: reconciliation_879136920198032 | B12: 29213576 | C12: 15503579 | D12: 46017.671 | E12: 46019 | F12: SUCCESS | G12: 17237 | H12: 13460 | I12: Marina Bay Sands SkyPark Observation Deck - Admission (Entry until 4:00 PM) | K12: BeMyGuest | L12: 111 | M12: BeMyGuest_API | N12: 2992 | O12: VENDOR_API | P12: PORTAL_DEPOSIT | Q12: Urte Venclovaite | R12: { "totalCount": 3, "personList": [{ "count": 3, "type": "ADULT", "priceNet": 33.2 }] } | S12: DATE_OF_BOOKING | T12: 7eee340d-48b7-4d6f-969a-c3a297f39025 | U12: TODO | V12: RECONCILIATION_STATUS_AUTO_RECONCILED | W12: RECON | X12: 7 | Y12: 46017.671 | Z12: 46073.389 | AA12: SGD | AB12: 91.95 | AC12: 0 | AD12: { "extraCharges": [{ "amountInTourCurrency": 9.194, "chargeType": "PERCENTAGE", "extraChargeCode": "CONVENIENCE_FEE", "chargeValue": 10.0 }] } | AE12: TRUE | AF12: COMPLETED | AI12: FALSE | AL12: Refunded | AM12: FALSE | AN12: Net price discrepancy | AO12: 3 | AP12: 33.2 | AQ12: 99.6
A13: reconciliation_1475726062034150 | B13: 29238696 | C13: 15523212 | D13: 46018.591 | E13: 46019 | F13: CANCELLED | G13: 7371 | H13: 13460 | I13: Marina Bay Sands SkyPark Observation Deck - Admission (Entry until 4:00 PM) | K13: BeMyGuest | L13: 111 | M13: BeMyGuest_API | N13: 2992 | O13: VENDOR_API | P13: PORTAL_DEPOSIT | Q13: FRANCISCO MANUEL GONZALVEZ ALBERO | R13: { "totalCount": 5, "personList": [{ "count": 5, "type": "ADULT", "priceNet": 33.2 }] } | S13: DATE_OF_BOOKING | T13: d048df6d-844b-45e8-9817-2da63d436f04 | U13: TODO | V13: RECONCILIATION_STATUS_MANUALLY_RECONCILED | W13: RECON | X13: 11 | Y13: 46018.591 | Z13: 46073.389 | AA13: SGD | AB13: 175 | AC13: 0 | AD13: { "extraCharges": [{ "amountInTourCurrency": 17.5, "chargeType": "PERCENTAGE", "extraChargeCode": "CONVENIENCE_FEE", "chargeValue": 10.0 }] } | AE13: TRUE | AF13: CANCELLED | AI13: FALSE | AL13: Refunded | AM13: FALSE | AN13: No successful reconciliation found against booking id | AO13: 5 | AP13: 33.2 | AQ13: 166
A14: reconciliation_1476562732919418 | B14: 29239028 | C14: 15523489 | D14: 46018.601 | E14: 46019 | F14: CANCELLED | G14: 17237 | H14: 13460 | I14: Marina Bay Sands SkyPark Observation Deck - Admission (Entry until 4:00 PM) | K14: BeMyGuest | L14: 111 | M14: BeMyGuest_API | N14: 2992 | O14: VENDOR_API | P14: PORTAL_DEPOSIT | Q14: Minseo Kim | R14: { "totalCount": 5, "personList": [{ "count": 5, "type": "ADULT", "priceNet": 33.2 }] } | S14: DATE_OF_BOOKING | T14: d7fe957e-6793-4754-ad73-535953c40a46 | U14: TODO | V14: RECONCILIATION_STATUS_MANUALLY_RECONCILED | W14: RECON | X14: 10 | Y14: 46018.601 | Z14: 46073.389 | AA14: SGD | AB14: 166.25 | AC14: 0 | AD14: { "extraCharges": [{ "amountInTourCurrency": 16.623, "chargeType": "PERCENTAGE", "extraChargeCode": "CONVENIENCE_FEE", "chargeValue": 10.0 }] } | AE14: TRUE | AF14: CANCELLED | AI14: FALSE | AL14: Refunded | AM14: FALSE | AN14: No successful reconciliation found against booking id | AO14: 5 | AP14: 33.2 | AQ14: 166
A15: reconciliation_1100671665552518 | B15: 29283815 | C15: 15559256 | D15: 46020.235 | E15: 46020 | F15: SUCCESS | G15: 17825 | H15: 62106 | I15: TWO-ATTRACTION COMBO: Genting SkyWorlds + Skytropolis Indoor Theme Park (Non-Malaysian) | K15: BeMyGuest | L15: 111 | M15: BeMyGuest_API | N15: 2992 | O15: VENDOR_API | P15: PORTAL_DEPOSIT | Q15: AISHWARYA VINEETH NAIR | R15: { "totalCount": 4, "personList": [{ "count": 4, "type": "NON_MALAYSIAN_ADULT", "priceNet": 178.0 }] } | S15: DATE_OF_BOOKING | T15: 9af3c978-eb7c-48eb-82eb-7b98310681fd | U15: TODO | V15: RECONCILIATION_STATUS_MANUALLY_RECONCILED | W15: RECON | X15: 7 | Y15: 46020.235 | Z15: 46073.389 | AA15: MYR | AB15: 812 | AC15: 0 | AD15: { } | AE15: TRUE | AF15: COMPLETED | AI15: FALSE | AL15: Refunded | AM15: FALSE | AN15: Net price discrepancy | BJ15: 4 | BK15: 178 | BL15: 712
A16: reconciliation_1191614916033869 | B16: 29315188 | C16: 15584507 | D16: 46021.288 | E16: 46022 | F16: FAILED | G16: 17825 | H16: 62106 | I16: TWO-ATTRACTION COMBO: Genting SkyWorlds + Skytropolis Indoor Theme Park (Non-Malaysian) | K16: BeMyGuest | L16: 111 | M16: BeMyGuest_API | N16: 2992 | O16: VENDOR_API | P16: PORTAL_DEPOSIT | Q16: Nengsih Nengsih | R16: { "totalCount": 1, "personList": [{ "count": 1, "type": "NON_MALAYSIAN_ADULT", "priceNet": 178.0 }] } | S16: DATE_OF_BOOKING | U16: TODO | V16: RECONCILIATION_STATUS_DISCREPANCY | W16: RECON | X16: 4 | Y16: 46021.288 | Z16: 46027.414 | AA16: MYR | AB16: 203 | AC16: 178 | AD16: { } | AE16: FALSE | AF16: CANCELLED | AI16: FALSE | AM16: FALSE | AN16: No successful reconciliation found against booking id | BJ16: 1 | BK16: 178 | BL16: 178
A17: reconciliation_1195440048336645 | B17: 29315188 | C17: 15585661 | D17: 46021.332 | E17: 46022 | F17: FAILED | G17: 17825 | H17: 62106 | I17: TWO-ATTRACTION COMBO: Genting SkyWorlds + Skytropolis Indoor Theme Park (Non-Malaysian) | K17: BeMyGuest | L17: 111 | M17: BeMyGuest_API | N17: 2992 | O17: VENDOR_API | P17: PORTAL_DEPOSIT | Q17: Nengsih Nengsih | R17: { "totalCount": 1, "personList": [{ "count": 1, "type": "NON_MALAYSIAN_ADULT", "priceNet": 178.0 }] } | S17: DATE_OF_BOOKING | U17: TODO | V17: RECONCILIATION_STATUS_DISCREPANCY | W17: RECON | X17: 4 | Y17: 46021.332 | Z17: 46027.414 | AA17: MYR | AB17: 203 | AC17: 178 | AD17: { } | AE17: FALSE | AF17: CANCELLED | AI17: FALSE | AM17: FALSE | AN17: No successful reconciliation found against booking id | BJ17: 1 | BK17: 178 | BL17: 178
A18: reconciliation_1208745624076272 | B18: 29315188 | C18: 15591266 | D18: 46021.486 | E18: 46022 | F18: FAILED | G18: 17825 | H18: 62106 | I18: TWO-ATTRACTION COMBO: Genting SkyWorlds + Skytropolis Indoor Theme Park (Non-Malaysian) | K18: BeMyGuest | L18: 111 | M18: BeMyGuest_API | N18: 2992 | O18: VENDOR_API | P18: PORTAL_DEPOSIT | Q18: Nengsih Nengsih | R18: { "totalCount": 1, "personList": [{ "count": 1, "type": "NON_MALAYSIAN_ADULT", "priceNet": 178.0 }] } | S18: DATE_OF_BOOKING | U18: TODO | V18: RECONCILIATION_STATUS_DISCREPANCY | W18: RECON | X18: 4 | Y18: 46021.486 | Z18: 46027.414 | AA18: MYR | AB18: 203 | AC18: 178 | AD18: { } | AE18: FALSE | AF18: CANCELLED | AI18: FALSE | AM18: FALSE | AN18: No successful reconciliation found against booking id | BJ18: 1 | BK18: 178 | BL18: 178
A19: reconciliation_1214769412849889 | B19: 29315188 | C19: 15593717 | D19: 46021.556 | E19: 46022 | F19: FAILED | G19: 17825 | H19: 62106 | I19: TWO-ATTRACTION COMBO: Genting SkyWorlds + Skytropolis Indoor Theme Park (Non-Malaysian) | K19: BeMyGuest | L19: 111 | M19: BeMyGuest_API | N19: 2992 | O19: VENDOR_API | P19: PORTAL_DEPOSIT | Q19: Nengsih Nengsih | R19: { "totalCount": 1, "personList": [{ "count": 1, "type": "NON_MALAYSIAN_ADULT", "priceNet": 178.0 }] } | S19: DATE_OF_BOOKING | U19: TODO | V19: RECONCILIATION_STATUS_DISCREPANCY | W19: RECON | X19: 4 | Y19: 46021.556 | Z19: 46027.414 | AA19: MYR | AB19: 203 | AC19: 178 | AD19: { } | AE19: FALSE | AF19: CANCELLED | AI19: FALSE | AM19: FALSE | AN19: No successful reconciliation found against booking id | BJ19: 1 | BK19: 178 | BL19: 178
A20: reconciliation_1712352006973451 | B20: 29315188 | C20: 15585582 | D20: 46021.33 | E20: 46022 | F20: FAILED | G20: 17825 | H20: 62106 | I20: TWO-ATTRACTION COMBO: Genting SkyWorlds + Skytropolis Indoor Theme Park (Non-Malaysian) | K20: BeMyGuest | L20: 111 | M20: BeMyGuest_API | N20: 2992 | O20: VENDOR_API | P20: PORTAL_DEPOSIT | Q20: Nengsih Nengsih | R20: { "totalCount": 1, "personList": [{ "count": 1, "type": "NON_MALAYSIAN_ADULT", "priceNet": 178.0 }] } | S20: DATE_OF_BOOKING | U20: TODO | V20: RECONCILIATION_STATUS_DISCREPANCY | W20: RECON | X20: 4 | Y20: 46021.33 | Z20: 46027.414 | AA20: MYR | AB20: 203 | AC20: 178 | AD20: { } | AE20: FALSE | AF20: CANCELLED | AI20: FALSE | AM20: FALSE | AN20: No successful reconciliation found against booking id | BJ20: 1 | BK20: 178 | BL20: 178
A21: reconciliation_1779130856406389 | B21: 29339921 | C21: 15604222 | D21: 46022.102 | E21: 46029 | F21: SUCCESS | G21: 24204 | H21: 26872 | I21: SEA LIFE Sydney Aquarium - Morning Admission | K21: BeMyGuest | L21: 111 | M21: BeMyGuest_Peak | N21: 2145 | O21: VENDOR_API | P21: PORTAL_DEPOSIT | Q21: Nigela Bagtang | R21: { "totalCount": 2, "personList": [{ "count": 1, "type": "ADULT", "priceNet": 32.53 }, { "count": 1, "type": "CHILD", "priceNet": 23.5 }] } | S21: DATE_OF_BOOKING | T21: bf3b5613-d61a-4d23-9f6c-2ebe026ebcda | U21: TODO | V21: RECONCILIATION_STATUS_MANUALLY_RECONCILED | W21: RECON | X21: 10 | Y21: 46022.102 | Z21: 46073.389 | AA21: AUD | AB21: 82.12 | AC21: 0 | AD21: { } | AE21: TRUE | AF21: CANCELLED | AI21: FALSE | AL21: Refunded | AM21: FALSE | AN21: Net price discrepancy | AO21: 1 | AP21: 32.53 | AQ21: 32.53 | AU21: 1 | AV21: 23.5 | AW21: 23.5
A22: reconciliation_1310270924605903 | B22: 29354020 | C22: 15615587 | D22: 46022.661 | E22: 46022 | F22: FAILED | G22: 11655 | H22: 22128 | I22: General Admission | K22: BeMyGuest | L22: 111 | M22: BeMyGuest_API | N22: 2992 | O22: VENDOR_API | P22: PORTAL_DEPOSIT | Q22: Claire Guilmette | R22: { "totalCount": 2, "personList": [{ "count": 2, "type": "ADULT", "priceNet": 31.19 }] } | S22: DATE_OF_BOOKING | U22: TODO | V22: RECONCILIATION_STATUS_PENDING | W22: RECON | X22: 3 | Y22: 46022.661 | Z22: 46022.683 | AA22: USD | AB22: 78 | AC22: 62.38 | AD22: { "extraCharges": [{ "amountInTourCurrency": 4.0, "chargeType": "ABSOLUTE", "extraChargeCode": "CONVENIENCE_FEE", "chargeValue": 2.0 }] } | AE22: FALSE | AF22: COMPLETED | AI22: FALSE | AM22: FALSE | AN22: Net price discrepancy | AO22: 2 | AP22: 31.19 | AQ22: 62.38
A23: reconciliation_1828658328199959 | B23: 29354020 | C23: 15615858 | D23: 46022.676 | E23: 46022 | F23: SUCCESS | G23: 11655 | H23: 22128 | I23: General Admission | K23: BeMyGuest | L23: 111 | M23: BeMyGuest_API | N23: 2992 | O23: VENDOR_API | P23: PORTAL_DEPOSIT | Q23: Claire Guilmette | R23: { "totalCount": 2, "personList": [{ "count": 2, "type": "ADULT", "priceNet": 31.19 }] } | S23: DATE_OF_BOOKING | T23: 69a699bd-29cd-4397-ad51-0c36b6efe2a5 | U23: TODO | V23: RECONCILIATION_STATUS_AUTO_RECONCILED | W23: RECON | X23: 7 | Y23: 46022.676 | Z23: 46073.389 | AA23: USD | AB23: 78 | AC23: 62.62 | AD23: { "extraCharges": [{ "amountInTourCurrency": 4.0, "chargeType": "ABSOLUTE", "extraChargeCode": "CONVENIENCE_FEE", "chargeValue": 2.0 }] } | AE23: TRUE | AF23: COMPLETED | AI23: FALSE | AL23: Reconciled | AM23: FALSE | AN23: Net price discrepancy | AO23: 2 | AP23: 31.19 | AQ23: 62.38
A24: reconciliation_1311120122806390 | B24: 29354284 | C24: 15615785 | D24: 46022.671 | E24: 46022 | F24: SUCCESS | G24: 31468 | H24: 63735 | I24: Central Park Zoo - Admission | K24: BeMyGuest | L24: 111 | M24: BeMyGuest_API | N24: 2992 | O24: VENDOR_API | P24: PORTAL_DEPOSIT | Q24: Viviana Palomino | R24: { "totalCount": 2, "personList": [{ "count": 1, "type": "ADULT", "priceNet": 18.06 }, { "count": 1, "type": "CHILD", "priceNet": 13.45 }] } | S24: DATE_OF_BOOKING | T24: ef6bc8d8-1f04-438f-b406-342b88aba616 | U24: TODO | V24: RECONCILIATION_STATUS_AUTO_RECONCILED | W24: RECON | X24: 7 | Y24: 46022.671 | Z24: 46073.389 | AA24: USD | AB24: 32.2 | AC24: 31.62 | AD24: { "extraCharges": [{ "amountInTourCurrency": 6.0, "chargeType": "ABSOLUTE", "extraChargeCode": "CONVENIENCE_FEE", "chargeValue": 3.0 }] } | AE24: TRUE | AF24: COMPLETED | AI24: FALSE | AL24: Reconciled | AM24: FALSE | AN24: Net price discrepancy | AO24: 1 | AP24: 18.06 | AQ24: 18.06 | AU24: 1 | AV24: 13.45 | AW24: 13.45
A25: reconciliation_1828556142791244 | B25: 29354343 | C25: 15615845 | D25: 46022.675 | E25: 46022 | F25: SUCCESS | G25: 30480 | H25: 63735 | I25: Central Park Zoo - Admission | K25: BeMyGuest | L25: 111 | M25: BeMyGuest_API | N25: 2992 | O25: VENDOR_API | P25: PORTAL_DEPOSIT | Q25: stacey mottram | R25: { "totalCount": 2, "personList": [{ "count": 2, "type": "ADULT", "priceNet": 18.06 }] } | S25: DATE_OF_BOOKING | T25: c81df581-fb15-4ff8-b7b5-7f4daa54f8a4 | U25: TODO | V25: RECONCILIATION_STATUS_AUTO_RECONCILED | W25: RECON | X25: 7 | Y25: 46022.675 | Z25: 46073.389 | AA25: USD | AB25: 39.9 | AC25: 36.25 | AD25: { "extraCharges": [{ "amountInTourCurrency": 6.0, "chargeType": "ABSOLUTE", "extraChargeCode": "CONVENIENCE_FEE", "chargeValue": 3.0 }] } | AE25: TRUE | AF25: COMPLETED | AI25: FALSE | AL25: Reconciled | AM25: FALSE | AN25: Net price discrepancy | AO25: 2 | AP25: 18.06 | AQ25: 36.12
A26: reconciliation_1828752017017451 | B26: 29354391 | C26: 15615875 | D26: 46022.677 | E26: 46023 | F26: SUCCESS | G26: 13224 | H26: 61763 | I26: The Habitat Penang Hill - Standard Entrance Pass | K26: BeMyGuest | L26: 111 | M26: BeMyGuest_API | N26: 2992 | O26: VENDOR_API | P26: PORTAL_DEPOSIT | Q26: Li Cui | R26: { "totalCount": 4, "personList": [{ "count": 3, "type": "ADULT", "priceNet": 43.0 }, { "count": 1, "type": "CHILD", "priceNet": 29.0 }] } | S26: DATE_OF_BOOKING | T26: d4be0068-502f-4609-9030-88f8ad4c8d31 | U26: TODO | V26: RECONCILIATION_STATUS_AUTO_RECONCILED | W26: RECON | X26: 7 | Y26: 46022.677 | Z26: 46073.389 | AA26: MYR | AB26: 187 | AC26: 157.51 | AD26: { } | AE26: TRUE | AF26: COMPLETED | AI26: FALSE | AL26: Reconciled | AM26: FALSE | AN26: Net price discrepancy | AO26: 3 | AP26: 43 | AQ26: 129 | AU26: 1 | AV26: 29 | AW26: 29
A27: reconciliation_1828866281877586 | B27: 29354428 | C27: 15615908 | D27: 46022.678 | E27: 46023 | F27: SUCCESS | G27: 17859 | H27: 52474 | I27: Dtac Happy Tourist 5G SIM Card - THB 349 Plan (Suvarnabumi Airport Pick-up) | K27: BeMyGuest | L27: 111 | M27: BeMyGuest_API | N27: 2992 | O27: VENDOR_API | P27: PORTAL_DEPOSIT | Q27: Sanjana Murali | R27: { "totalCount": 2, "personList": [{ "count": 2, "type": "ADULT", "priceNet": 202.0 }] } | S27: DATE_OF_BOOKING | T27: 372e012f-d2bf-469d-ae39-dbe2accc92dd | U27: TODO | V27: RECONCILIATION_STATUS_AUTO_RECONCILED | W27: RECON | X27: 7 | Y27: 46022.678 | Z27: 46073.389 | AA27: THB | AB27: 558 | AC27: 401.06 | AD27: { } | AE27: TRUE | AF27: COMPLETED | AI27: FALSE | AL27: Reconciled | AM27: FALSE | AN27: Net price discrepancy | AO27: 2 | AP27: 202 | AQ27: 404
A28: reconciliation_1828930377427998 | B28: 29354460 | C28: 15615928 | D28: 46022.679 | E28: 46022 | F28: SUCCESS | G28: 30480 | H28: 63735 | I28: Central Park Zoo - Admission | K28: BeMyGuest | L28: 111 | M28: BeMyGuest_API | N28: 2992 | O28: VENDOR_API | P28: PORTAL_DEPOSIT | Q28: Miroslav Stoch | R28: { "totalCount": 2, "personList": [{ "count": 1, "type": "ADULT", "priceNet": 18.06 }, { "count": 1, "type": "CHILD", "priceNet": 13.45 }] } | S28: DATE_OF_BOOKING | T28: de05235c-d23d-4c04-849e-cf9d5de17c75 | U28: TODO | V28: RECONCILIATION_STATUS_AUTO_RECONCILED | W28: RECON | X28: 7 | Y28: 46022.679 | Z28: 46073.389 | AA28: USD | AB28: 33.9 | AC28: 31.64 | AD28: { "extraCharges": [{ "amountInTourCurrency": 6.0, "chargeType": "ABSOLUTE", "extraChargeCode": "CONVENIENCE_FEE", "chargeValue": 3.0 }] } | AE28: TRUE | AF28: COMPLETED | AI28: FALSE | AL28: Reconciled | AM28: FALSE | AN28: Net price discrepancy | AO28: 1 | AP28: 18.06 | AQ28: 18.06 | AU28: 1 | AV28: 13.45 | AW28: 13.45
A29: reconciliation_1829166348975412 | B29: 29354523 | C29: 15615990 | D29: 46022.682 | E29: 46030 | F29: SUCCESS | G29: 7442 | H29: 43120 | I29: Universal Studios Singapore - One Day Ticket | K29: BeMyGuest | L29: 111 | M29: BeMyGuest_API | N29: 2992 | O29: VENDOR_API | P29: PORTAL_DEPOSIT | Q29: Shehani Dawundage | R29: { "totalCount": 1, "personList": [{ "count": 1, "type": "ADULT", "priceNet": 75.0 }] } | S29: DATE_OF_BOOKING | T29: 76730203-a652-4ffa-a2de-b44a21abe9a4 | U29: TODO | V29: RECONCILIATION_STATUS_AUTO_RECONCILED | W29: RECON | X29: 7 | Y29: 46022.682 | Z29: 46073.389 | AA29: SGD | AB29: 82.79 | AC29: 75 | AD29: { } | AE29: TRUE | AF29: COMPLETED | AI29: FALSE | AL29: Reconciled | AM29: FALSE | AN29: Reconciliation ALREADY auto reconciled | AO29: 1 | AP29: 75 | AQ29: 75
A30: reconciliation_1312170733490860 | B30: 29354594 | C30: 15616033 | D30: 46022.683 | E30: 46022 | F30: SUCCESS | G30: 30480 | H30: 63735 | I30: Central Park Zoo - Admission | K30: BeMyGuest | L30: 111 | M30: BeMyGuest_API | N30: 2992 | O30: VENDOR_API | P30: PORTAL_DEPOSIT | Q30: Katie arrington | R30: { "totalCount": 2, "personList": [{ "count": 2, "type": "ADULT", "priceNet": 18.06 }] } | S30: DATE_OF_BOOKING | T30: 6d591b9b-d047-4100-8b70-b4d74fc9ae58 | U30: TODO | V30: RECONCILIATION_STATUS_AUTO_RECONCILED | W30: RECON | X30: 7 | Y30: 46022.683 | Z30: 46073.389 | AA30: USD | AB30: 39.9 | AC30: 36.27 | AD30: { "extraCharges": [{ "amountInTourCurrency": 6.0, "chargeType": "ABSOLUTE", "extraChargeCode": "CONVENIENCE_FEE", "chargeValue": 3.0 }] } | AE30: TRUE | AF30: COMPLETED | AI30: FALSE | AL30: Reconciled | AM30: FALSE | AN30: Net price discrepancy | AO30: 2 | AP30: 18.06 | AQ30: 36.12
A31: reconciliation_2481328327825757 | B31: 29354885 | C31: 15730470 | D31: 46030.23 | E31: 46051 | F31: SUCCESS | G31: 7371 | H31: 55603 | I31: Marina Bay Sands SkyPark Observation Deck - Admission (Timeslot Entry from 5:00 PM) | K31: BeMyGuest | L31: 111 | M31: BeMyGuest_API | N31: 2992 | O31: MANUAL | P31: PORTAL_DEPOSIT | Q31: Jakub Kaczmarek | R31: { "totalCount": 6, "personList": [{ "count": 5, "type": "ADULT", "priceNet": 37.2 }, { "count": 1, "type": "CONCESSION", "priceNet": 32.2 }] } | S31: DATE_OF_BOOKING | T31: R6BX95Z | U31: TODO | V31: RECONCILIATION_STATUS_AUTO_RECONCILED | W31: RECON | X31: 3 | Y31: 46030.23 | Z31: 46073.389 | AA31: SGD | AB31: 230 | AC31: 218.2 | AD31: { "extraCharges": [{ "amountInTourCurrency": 23.0, "chargeType": "PERCENTAGE", "extraChargeCode": "CONVENIENCE_FEE", "chargeValue": 10.0 }] } | AE31: FALSE | AF31: COMPLETED | AI31: FALSE | AL31: Reconciled | AM31: FALSE | AN31: Reconciliation ALREADY auto reconciled | AO31: 5 | AP31: 37.2 | AQ31: 186 | AX31: 1 | AY31: 32.2 | AZ31: 32.2
A32: reconciliation_1313678225973341 | B32: 29355022 | C32: 15616358 | D32: 46022.701 | E32: 46022 | F32: SUCCESS | G32: 11655 | H32: 22128 | I32: General Admission | K32: BeMyGuest | L32: 111 | M32: BeMyGuest_API | N32: 2992 | O32: VENDOR_API | P32: PORTAL_DEPOSIT | Q32: Rebecca King | R32: { "totalCount": 3, "personList": [{ "count": 3, "type": "ADULT", "priceNet": 31.19 }] } | S32: DATE_OF_BOOKING | T32: 63f84127-fea2-4be4-80a7-bc1dbc94784b | U32: TODO | V32: RECONCILIATION_STATUS_AUTO_RECONCILED | W32: RECON | X32: 7 | Y32: 46022.701 | Z32: 46073.389 | AA32: USD | AB32: 117 | AC32: 93.98 | AD32: { "extraCharges": [{ "amountInTourCurrency": 6.0, "chargeType": "ABSOLUTE", "extraChargeCode": "CONVENIENCE_FEE", "chargeValue": 2.0 }] } | AE32: TRUE | AF32: COMPLETED | AI32: FALSE | AL32: Reconciled | AM32: FALSE | AN32: Net price discrepancy | AO32: 3 | AP32: 31.19 | AQ32: 93.57
A33: reconciliation_1831236476391228 | B33: 29355133 | C33: 15616450 | D33: 46022.706 | E33: 46022 | F33: SUCCESS | G33: 11655 | H33: 22128 | I33: General Admission | K33: BeMyGuest | L33: 111 | M33: BeMyGuest_API | N33: 2992 | O33: VENDOR_API | P33: PORTAL_DEPOSIT | Q33: Paul Metcalf | R33: { "totalCount": 4, "personList": [{ "count": 2, "type": "ADULT", "priceNet": 31.19 }, { "count": 2, "type": "CHILD", "priceNet": 20.79 }] } | S33: DATE_OF_BOOKING | T33: 7ef1a0d2-58dc-4a11-af4e-12e8e9c37ac4 | U33: TODO | V33: RECONCILIATION_STATUS_AUTO_RECONCILED | W33: RECON | X33: 7 | Y33: 46022.706 | Z33: 46073.389 | AA33: USD | AB33: 129.98 | AC33: 104.42 | AD33: { "extraCharges": [{ "amountInTourCurrency": 8.0, "chargeType": "ABSOLUTE", "extraChargeCode": "CONVENIENCE_FEE", "chargeValue": 2.0 }] } | AE33: TRUE | AF33: COMPLETED | AI33: FALSE | AL33: Reconciled | AM33: FALSE | AN33: Net price discrepancy | AO33: 2 | AP33: 31.19 | AQ33: 62.38 | AU33: 2 | AV33: 20.79 | AW33: 41.58
A34: reconciliation_1314181229560551 | B34: 29355136 | C34: 15616471 | D34: 46022.707 | E34: 46022 | F34: SUCCESS | G34: 30480 | H34: 63735 | I34: Central Park Zoo - Admission | K34: BeMyGuest | L34: 111 | M34: BeMyGuest_API | N34: 2992 | O34: VENDOR_API | P34: PORTAL_DEPOSIT | Q34: Andres Calderon zumbado | R34: { "totalCount": 2, "personList": [{ "count": 2, "type": "ADULT", "priceNet": 18.06 }] } | S34: DATE_OF_BOOKING | T34: 959092e2-0060-4c7e-a59b-8789c98b8888 | U34: TODO | V34: RECONCILIATION_STATUS_AUTO_RECONCILED | W34: RECON | X34: 7 | Y34: 46022.707 | Z34: 46073.389 | AA34: USD | AB34: 39.9 | AC34: 36.27 | AD34: { "extraCharges": [{ "amountInTourCurrency": 6.0, "chargeType": "ABSOLUTE", "extraChargeCode": "CONVENIENCE_FEE", "chargeValue": 3.0 }] } | AE34: TRUE | AF34: COMPLETED | AI34: FALSE | AL34: Reconciled | AM34: FALSE | AN34: Net price discrepancy | AO34: 2 | AP34: 18.06 | AQ34: 36.12
A35: reconciliation_1831695392391970 | B35: 29355265 | C35: 15616558 | D35: 46022.711 | E35: 46069 | F35: SUCCESS | G35: 37400 | H35: 27355 | I35: Universal Studios Singapore One-Time Express Pass (Individual) | K35: BeMyGuest | L35: 111 | M35: BeMyGuest_API | N35: 2992 | O35: VENDOR_API | P35: PORTAL_DEPOSIT | Q35: Malcolm James Workman | R35: { "totalCount": 3, "personList": [{ "count": 3, "type": "ADULT", "priceNet": 124.5 }] } | S35: DATE_OF_BOOKING | T35: 1.6888957e+15 | U35: TODO | V35: RECONCILIATION_STATUS_MANUALLY_RECONCILED | W35: RECON | X35: 5 | Y35: 46022.711 | Z35: 46073.389 | AA35: SGD | AB35: 705 | AC35: 225 | AD35: { } | AE35: FALSE | AF35: COMPLETED | AI35: FALSE | AL35: Combo on BMG | AM35: FALSE | AN35: Reconciliation ALREADY manually reconciled | AO35: 3 | AP35: 124.5 | AQ35: 373.5
A36: reconciliation_1315289446546391 | B36: 29355435 | C36: 15616705 | D36: 46022.719 | E36: 46026 | F36: SUCCESS | G36: 7442 | H36: 43120 | I36: Universal Studios Singapore - One Day Ticket | K36: BeMyGuest | L36: 111 | M36: BeMyGuest_API | N36: 2992 | O36: VENDOR_API | P36: PORTAL_DEPOSIT | Q36: rajesh bodasing | R36: { "totalCount": 5, "personList": [{ "count": 5, "type": "ADULT", "priceNet": 75.0 }] } | S36: DATE_OF_BOOKING | T36: f62f8414-3086-4485-9f63-b74452d4d9fe | U36: TODO | V36: RECONCILIATION_STATUS_AUTO_RECONCILED | W36: RECON | X36: 7 | Y36: 46022.719 | Z36: 46073.389 | AA36: SGD | AB36: 413.95 | AC36: 375 | AD36: { } | AE36: TRUE | AF36: COMPLETED | AI36: FALSE | AL36: Reconciled | AM36: FALSE | AN36: Reconciliation ALREADY auto reconciled | AO36: 5 | AP36: 75 | AQ36: 375
A37: reconciliation_1315451269596834 | B37: 29355529 | C37: 15616734 | D37: 46022.721 | E37: 46022 | F37: SUCCESS | G37: 30480 | H37: 63735 | I37: Central Park Zoo - Admission | K37: BeMyGuest | L37: 111 | M37: BeMyGuest_API | N37: 2992 | O37: VENDOR_API | P37: PORTAL_DEPOSIT | Q37: Israel Quiroz Plata | R37: { "totalCount": 3, "personList": [{ "count": 2, "type": "ADULT", "priceNet": 18.06 }, { "count": 1, "type": "CHILD", "priceNet": 13.45 }] } | S37: DATE_OF_BOOKING | T37: aee8c71b-7bc3-4da4-91ad-be2a6fb3a228 | U37: TODO | V37: RECONCILIATION_STATUS_AUTO_RECONCILED | W37: RECON | X37: 7 | Y37: 46022.721 | Z37: 46073.389 | AA37: USD | AB37: 53.85 | AC37: 49.77 | AD37: { "extraCharges": [{ "amountInTourCurrency": 9.0, "chargeType": "ABSOLUTE", "extraChargeCode": "CONVENIENCE_FEE", "chargeValue": 3.0 }] } | AE37: TRUE | AF37: COMPLETED | AI37: FALSE | AL37: Reconciled | AM37: FALSE | AN37: Net price discrepancy | AO37: 2 | AP37: 18.06 | AQ37: 36.12 | AU37: 1 | AV37: 13.45 | AW37: 13.45
A38: reconciliation_1832762525174658 | B38: 29355565 | C38: 15616772 | D38: 46022.723 | E38: 46022 | F38: SUCCESS | G38: 30480 | H38: 63735 | I38: Central Park Zoo - Admission | K38: BeMyGuest | L38: 111 | M38: BeMyGuest_API | N38: 2992 | O38: VENDOR_API | P38: PORTAL_DEPOSIT | Q38: Danny Fallas | R38: { "totalCount": 1, "personList": [{ "count": 1, "type": "ADULT", "priceNet": 18.06 }] } | S38: DATE_OF_BOOKING | T38: a8fff366-4eeb-4826-b261-42b2c3a3a773 | U38: TODO | V38: RECONCILIATION_STATUS_AUTO_RECONCILED | W38: RECON | X38: 7 | Y38: 46022.723 | Z38: 46073.389 | AA38: USD | AB38: 19.95 | AC38: 18.13 | AD38: { "extraCharges": [{ "amountInTourCurrency": 3.0, "chargeType": "ABSOLUTE", "extraChargeCode": "CONVENIENCE_FEE", "chargeValue": 3.0 }] } | AE38: TRUE | AF38: COMPLETED | AI38: FALSE | AL38: Reconciled | AM38: FALSE | AN38: Net price discrepancy | AO38: 1 | AP38: 18.06 | AQ38: 18.06
A39: reconciliation_1316373130292941 | B39: 29355765 | C39: 15616908 | D39: 46022.732 | E39: 46026 | F39: SUCCESS | G39: 7442 | H39: 43120 | I39: Universal Studios Singapore - One Day Ticket | K39: BeMyGuest | L39: 111 | M39: BeMyGuest_API | N39: 2992 | O39: VENDOR_API | P39: PORTAL_DEPOSIT | Q39: ISHARA BODASING | R39: { "totalCount": 2, "personList": [{ "count": 2, "type": "ADULT", "priceNet": 75.0 }] } | S39: DATE_OF_BOOKING | T39: 16abad2d-43a6-4433-bc39-e3af84284884 | U39: TODO | V39: RECONCILIATION_STATUS_AUTO_RECONCILED | W39: RECON | X39: 7 | Y39: 46022.732 | Z39: 46073.389 | AA39: SGD | AB39: 165.58 | AC39: 150 | AD39: { } | AE39: TRUE | AF39: COMPLETED | AI39: FALSE | AL39: Reconciled | AM39: FALSE | AN39: Reconciliation ALREADY auto reconciled | AO39: 2 | AP39: 75 | AQ39: 150
A40: reconciliation_1834436381610597 | B40: 29356009 | C40: 15617098 | D40: 46022.743 | E40: 46022 | F40: SUCCESS | G40: 11655 | H40: 22128 | I40: General Admission | K40: BeMyGuest | L40: 111 | M40: BeMyGuest_API | N40: 2992 | O40: VENDOR_API | P40: PORTAL_DEPOSIT | Q40: Carlos Maytorena | R40: { "totalCount": 2, "personList": [{ "count": 2, "type": "ADULT", "priceNet": 31.19 }] } | S40: DATE_OF_BOOKING | T40: 1d7692e5-33f9-4490-98dd-5602adee5130 | U40: TODO | V40: RECONCILIATION_STATUS_AUTO_RECONCILED | W40: RECON | X40: 7 | Y40: 46022.743 | Z40: 46073.389 | AA40: USD | AB40: 78 | AC40: 62.64 | AD40: { "extraCharges": [{ "amountInTourCurrency": 4.0, "chargeType": "ABSOLUTE", "extraChargeCode": "CONVENIENCE_FEE", "chargeValue": 2.0 }] } | AE40: TRUE | AF40: COMPLETED | AI40: FALSE | AL40: Reconciled | AM40: FALSE | AN40: Net price discrepancy | AO40: 2 | AP40: 31.19 | AQ40: 62.38
A41: reconciliation_1317445252768296 | B41: 29356052 | C41: 15617134 | D41: 46022.744 | E41: 46022 | F41: FAILED | G41: 30480 | H41: 63735 | I41: Central Park Zoo - Admission | K41: BeMyGuest | L41: 111 | M41: BeMyGuest_API | N41: 2992 | O41: VENDOR_API | P41: PORTAL_DEPOSIT | Q41: Louis Hoffman | R41: { "totalCount": 1, "personList": [{ "count": 1, "type": "ADULT", "priceNet": 18.06 }] } | S41: DATE_OF_BOOKING | U41: TODO | V41: RECONCILIATION_STATUS_PENDING | W41: RECON | X41: 3 | Y41: 46022.744 | Z41: 46022.757 | AA41: USD | AB41: 19.95 | AC41: 18.06 | AD41: { "extraCharges": [{ "amountInTourCurrency": 3.0, "chargeType": "ABSOLUTE", "extraChargeCode": "CONVENIENCE_FEE", "chargeValue": 3.0 }] } | AE41: FALSE | AF41: COMPLETED | AI41: FALSE | AM41: FALSE | AN41: Net price discrepancy | AO41: 1 | AP41: 18.06 | AQ41: 18.06
A42: reconciliation_1318327017170485 | B42: 29356052 | C42: 15617290 | D42: 46022.755 | E42: 46022 | F42: SUCCESS | G42: 30480 | H42: 63735 | I42: Central Park Zoo - Admission | K42: BeMyGuest | L42: 111 | M42: BeMyGuest_API | N42: 2992 | O42: VENDOR_API | P42: PORTAL_DEPOSIT | Q42: Louis Hoffman | R42: { "totalCount": 1, "personList": [{ "count": 1, "type": "ADULT", "priceNet": 18.06 }] } | S42: DATE_OF_BOOKING | T42: 686ff53d-477c-40f1-b98b-cf6ab86ee2b0 | U42: TODO | V42: RECONCILIATION_STATUS_AUTO_RECONCILED | W42: RECON | X42: 7 | Y42: 46022.755 | Z42: 46073.389 | AA42: USD | AB42: 19.95 | AC42: 18.13 | AD42: { "extraCharges": [{ "amountInTourCurrency": 3.0, "chargeType": "ABSOLUTE", "extraChargeCode": "CONVENIENCE_FEE", "chargeValue": 3.0 }] } | AE42: TRUE | AF42: COMPLETED | AI42: FALSE | AL42: Reconciled | AM42: FALSE | AN42: Net price discrepancy | AO42: 1 | AP42: 18.06 | AQ42: 18.06
A43: reconciliation_1317538942049424 | B43: 29356075 | C43: 15617152 | D43: 46022.746 | E43: 46024 | F43: SUCCESS | G43: 35785 | H43: 75803 | I43: Gallery Seating | K43: BeMyGuest | L43: 111 | M43: BeMyGuest_Off Peak | N43: 1858 | O43: VENDOR_API | P43: PORTAL_DEPOSIT | Q43: Jonathan Khonghun | R43: { "totalCount": 3, "personList": [{ "count": 3, "type": "GENERAL", "priceNet": 629.0 }] } | S43: DATE_OF_BOOKING | T43: 7c6ce618-b3ea-405c-9e5a-8aaa980bdad5 | U43: TODO | V43: RECONCILIATION_STATUS_MANUALLY_RECONCILED | W43: RECON | X43: 7 | Y43: 46022.746 | Z43: 46073.389 | AA43: MOP | AB43: 2451 | AC43: 1887 | AD43: { "extraCharges": [{ "amountInTourCurrency": 245.182, "chargeType": "PERCENTAGE", "extraChargeCode": "CONVENIENCE_FEE", "chargeValue": 10.0 }] } | AE43: TRUE | AF43: COMPLETED | AI43: FALSE | AL43: Forex | AM43: FALSE | AN43: Net price discrepancy | BD43: 3 | BE43: 629 | BF43: 1887
A44: reconciliation_1318026914258809 | B44: 29356196 | C44: 15617239 | D44: 46022.751 | E44: 46022 | F44: SUCCESS | G44: 31468 | H44: 63735 | I44: Central Park Zoo - Admission | K44: BeMyGuest | L44: 111 | M44: BeMyGuest_API | N44: 2992 | O44: VENDOR_API | P44: PORTAL_DEPOSIT | Q44: Juan camilo Alvarez munoz | R44: { "totalCount": 4, "personList": [{ "count": 4, "type": "ADULT", "priceNet": 18.06 }] } | S44: DATE_OF_BOOKING | T44: 08bdaaa7-b2c5-46f8-90a8-d926e92d8250 | U44: TODO | V44: RECONCILIATION_STATUS_AUTO_RECONCILED | W44: RECON | X44: 7 | Y44: 46022.751 | Z44: 46073.389 | AA44: USD | AB44: 75.8 | AC44: 72.54 | AD44: { "extraCharges": [{ "amountInTourCurrency": 12.0, "chargeType": "ABSOLUTE", "extraChargeCode": "CONVENIENCE_FEE", "chargeValue": 3.0 }] } | AE44: TRUE | AF44: COMPLETED | AI44: FALSE | AL44: Reconciled | AM44: FALSE | AN44: Net price discrepancy | AO44: 4 | AP44: 18.06 | AQ44: 72.24
A45: reconciliation_1318284436350817 | B45: 29356250 | C45: 15617282 | D45: 46022.754 | E45: 46022 | F45: SUCCESS | G45: 30480 | H45: 63735 | I45: Central Park Zoo - Admission | K45: BeMyGuest | L45: 111 | M45: BeMyGuest_API | N45: 2992 | O45: VENDOR_API | P45: PORTAL_DEPOSIT | Q45: Evgeny Eustace | R45: { "totalCount": 2, "personList": [{ "count": 2, "type": "ADULT", "priceNet": 18.06 }] } | S45: DATE_OF_BOOKING | T45: 525ee9b1-4ab5-4feb-8781-20b95d31d8b1 | U45: TODO | V45: RECONCILIATION_STATUS_AUTO_RECONCILED | W45: RECON | X45: 7 | Y45: 46022.754 | Z45: 46073.389 | AA45: USD | AB45: 39.9 | AC45: 36.27 | AD45: { "extraCharges": [{ "amountInTourCurrency": 6.0, "chargeType": "ABSOLUTE", "extraChargeCode": "CONVENIENCE_FEE", "chargeValue": 3.0 }] } | AE45: TRUE | AF45: COMPLETED | AI45: FALSE | AL45: Reconciled | AM45: FALSE | AN45: Net price discrepancy | AO45: 2 | AP45: 18.06 | AQ45: 36.12
A46: reconciliation_1836499502591912 | B46: 29356542 | C46: 15617510 | D46: 46022.766 | E46: 46022 | F46: SUCCESS | G46: 11655 | H46: 22128 | I46: General Admission | K46: BeMyGuest | L46: 111 | M46: BeMyGuest_API | N46: 2992 | O46: VENDOR_API | P46: PORTAL_DEPOSIT | Q46: Lobna Jbeniani | R46: { "totalCount": 2, "personList": [{ "count": 2, "type": "ADULT", "priceNet": 31.19 }] } | S46: DATE_OF_BOOKING | T46: 848b9e41-02c4-4ed0-a268-4d7eb5f701b9 | U46: TODO | V46: RECONCILIATION_STATUS_AUTO_RECONCILED | W46: RECON | X46: 7 | Y46: 46022.766 | Z46: 46073.389 | AA46: USD | AB46: 78 | AC46: 62.65 | AD46: { "extraCharges": [{ "amountInTourCurrency": 4.0, "chargeType": "ABSOLUTE", "extraChargeCode": "CONVENIENCE_FEE", "chargeValue": 2.0 }] } | AE46: TRUE | AF46: COMPLETED | AI46: FALSE | AL46: Reconciled | AM46: FALSE | AN46: Net price discrepancy | AO46: 2 | AP46: 31.19 | AQ46: 62.38
A47: reconciliation_1836586666988476 | B47: 29356567 | C47: 15617528 | D47: 46022.767 | E47: 46022 | F47: SUCCESS | G47: 11655 | H47: 22128 | I47: General Admission | K47: BeMyGuest | L47: 111 | M47: BeMyGuest_API | N47: 2992 | O47: VENDOR_API | P47: PORTAL_DEPOSIT | Q47: Tyson Hauschildt | R47: { "totalCount": 2, "personList": [{ "count": 2, "type": "ADULT", "priceNet": 31.19 }] } | S47: DATE_OF_BOOKING | T47: 9eff5cb1-bb53-4c58-b9cb-84b9bb69a16b | U47: TODO | V47: RECONCILIATION_STATUS_AUTO_RECONCILED | W47: RECON | X47: 7 | Y47: 46022.767 | Z47: 46073.389 | AA47: USD | AB47: 78 | AC47: 62.65 | AD47: { "extraCharges": [{ "amountInTourCurrency": 4.0, "chargeType": "ABSOLUTE", "extraChargeCode": "CONVENIENCE_FEE", "chargeValue": 2.0 }] } | AE47: TRUE | AF47: COMPLETED | AI47: FALSE | AL47: Reconciled | AM47: FALSE | AN47: Net price discrepancy | AO47: 2 | AP47: 31.19 | AQ47: 62.38
A48: reconciliation_1837321161655157 | B48: 29356701 | C48: 15617640 | D48: 46022.776 | E48: 46024 | F48: SUCCESS | G48: 30480 | H48: 63735 | I48: Central Park Zoo - Admission | K48: BeMyGuest | L48: 111 | M48: BeMyGuest_API | N48: 2992 | O48: VENDOR_API | P48: PORTAL_DEPOSIT | Q48: Yaritza Arreola | R48: { "totalCount": 2, "personList": [{ "count": 2, "type": "ADULT", "priceNet": 18.06 }] } | S48: DATE_OF_BOOKING | T48: bfa9efbf-afea-4a14-bb90-7f978b2ab4ac | U48: TODO | V48: RECONCILIATION_STATUS_AUTO_RECONCILED | W48: RECON | X48: 7 | Y48: 46022.776 | Z48: 46073.389 | AA48: USD | AB48: 39.9 | AC48: 36.28 | AD48: { "extraCharges": [{ "amountInTourCurrency": 6.0, "chargeType": "ABSOLUTE", "extraChargeCode": "CONVENIENCE_FEE", "chargeValue": 3.0 }] } | AE48: TRUE | AF48: COMPLETED | AI48: FALSE | AL48: Reconciled | AM48: FALSE | AN48: Net price discrepancy | AO48: 2 | AP48: 18.06 | AQ48: 36.12
A49: reconciliation_1320564016907445 | B49: 29356793 | C49: 15617713 | D49: 46022.781 | E49: 46022 | F49: SUCCESS | G49: 11655 | H49: 22128 | I49: General Admission | K49: BeMyGuest | L49: 111 | M49: BeMyGuest_API | N49: 2992 | O49: VENDOR_API | P49: PORTAL_DEPOSIT | Q49: Ellis Bieringer | R49: { "totalCount": 2, "personList": [{ "count": 2, "type": "ADULT", "priceNet": 31.19 }] } | S49: DATE_OF_BOOKING | T49: 9456d76e-a44e-4bc1-a040-f0336ee8e720 | U49: TODO | V49: RECONCILIATION_STATUS_AUTO_RECONCILED | W49: RECON | X49: 7 | Y49: 46022.781 | Z49: 46073.389 | AA49: USD | AB49: 78 | AC49: 62.65 | AD49: { "extraCharges": [{ "amountInTourCurrency": 4.0, "chargeType": "ABSOLUTE", "extraChargeCode": "CONVENIENCE_FEE", "chargeValue": 2.0 }] } | AE49: TRUE | AF49: COMPLETED | AI49: FALSE | AL49: Reconciled | AM49: FALSE | AN49: Net price discrepancy | AO49: 2 | AP49: 31.19 | AQ49: 62.38
A50: reconciliation_1321151687191326 | B50: 29356927 | C50: 15617818 | D50: 46022.787 | E50: 46022 | F50: FAILED | G50: 11655 | H50: 22128 | I50: General Admission | K50: BeMyGuest | L50: 111 | M50: BeMyGuest_API | N50: 2992 | O50: VENDOR_API | P50: PORTAL_DEPOSIT | Q50: Holden Kolodner | R50: { "totalCount": 1, "personList": [{ "count": 1, "type": "ADULT", "priceNet": 31.19 }] } | S50: DATE_OF_BOOKING | U50: TODO | V50: RECONCILIATION_STATUS_PENDING | W50: RECON | X50: 3 | Y50: 46022.787 | Z50: 46022.808 | AA50: USD | AB50: 39 | AC50: 31.19 | AD50: { "extraCharges": [{ "amountInTourCurrency": 2.0, "chargeType": "ABSOLUTE", "extraChargeCode": "CONVENIENCE_FEE", "chargeValue": 2.0 }] } | AE50: FALSE | AF50: COMPLETED | AI50: FALSE | AM50: FALSE | AN50: Net price discrepancy | AO50: 1 | AP50: 31.19 | AQ50: 31.19
A51: reconciliation_1322954787634516 | B51: 29356927 | C51: 15618095 | D51: 46022.808 | E51: 46022 | F51: SUCCESS | G51: 11655 | H51: 22128 | I51: General Admission | K51: BeMyGuest | L51: 111 | M51: BeMyGuest_API | N51: 2992 | O51: MANUAL | P51: PORTAL_DEPOSIT | Q51: Holden Kolodner | R51: { "totalCount": 1, "personList": [{ "count": 1, "type": "ADULT", "priceNet": 31.19 }] } | S51: DATE_OF_BOOKING | T51: #LLC7QR7 | U51: TODO | V51: RECONCILIATION_STATUS_AUTO_RECONCILED | W51: RECON | X51: 4 | Y51: 46022.808 | Z51: 46073.389 | AA51: USD | AB51: 39 | AC51: 31.33 | AD51: { "extraCharges": [{ "amountInTourCurrency": 2.0, "chargeType": "ABSOLUTE", "extraChargeCode": "CONVENIENCE_FEE", "chargeValue": 2.0 }] } | AE51: FALSE | AF51: COMPLETED | AI51: FALSE | AL51: Reconciled | AM51: FALSE | AN51: Net price discrepancy | AO51: 1 | AP51: 31.19 | AQ51: 31.19
A52: reconciliation_1322339060471533 | B52: 29357157 | C52: 15618012 | D52: 46022.801 | E52: 46027 | F52: CANCELLED | G52: 38409 | H52: 82215 | I52: 1-Day "Any Day" Ticket with Direct Entry | K52: BeMyGuest | L52: 111 | M52: BeMyGuest_API | N52: 2992 | O52: VENDOR_API | P52: PORTAL_DEPOSIT | Q52: Johnson Aniketh Nagamallah | R52: { "totalCount": 2, "personList": [{ "count": 2, "type": "GENERAL", "priceNet": 68.21 }] } | S52: DATE_OF_BOOKING | T52: 20402e7e-9484-40ae-af88-29be0a608d5c | U52: TODO | V52: RECONCILIATION_STATUS_MANUALLY_RECONCILED | W52: RECON | X52: 11 | Y52: 46022.801 | Z52: 46073.389 | AA52: USD | AB52: 181.9 | AC52: 0 | AD52: { } | AE52: TRUE | AF52: CANCELLED | AI52: FALSE | AL52: Refunded | AM52: FALSE | AN52: No successful reconciliation found against booking id | BD52: 2 | BE52: 68.21 | BF52: 136.42
A53: reconciliation_1324211297441889 | B53: 29357281 | C53: 15618259 | D53: 46022.823 | E53: 46033 | F53: SUCCESS | G53: 10120 | H53: 50549 | I53: Hong Kong Disneyland 1 Day Ticket (Tier 3) with Disney Premier Access (3 Attractions) | K53: BeMyGuest | L53: 111 | M53: BeMyGuest_API | N53: 2992 | O53: VENDOR_API | P53: PORTAL_DEPOSIT | Q53: Atif Shafi | R53: { "totalCount": 4, "personList": [{ "count": 2, "type": "ADULT", "priceNet": 877.36 }, { "count": 2, "type": "CHILD", "priceNet": 704.5 }] } | S53: DATE_OF_BOOKING | T53: 5ebf3bc5-b67a-4bdc-bf7a-92f241cd4795 | U53: TODO | V53: RECONCILIATION_STATUS_MANUALLY_RECONCILED | W53: RECON | X53: 7 | Y53: 46022.823 | Z53: 46073.389 | AA53: HKD | AB53: 3397.88 | AC53: 3178.34 | AD53: { "extraCharges": [{ "amountInTourCurrency": 339.787, "chargeType": "PERCENTAGE", "extraChargeCode": "CONVENIENCE_FEE", "chargeValue": 10.0 }] } | AE53: TRUE | AF53: COMPLETED | AI53: FALSE | AL53: Reconciled | AM53: FALSE | AN53: Net price discrepancy | AO53: 2 | AP53: 877.36 | AQ53: 1754.72 | AU53: 2 | AV53: 704.5 | AW53: 1409
A54: reconciliation_1840799610656272 | B54: 29357341 | C54: 15618185 | D54: 46022.816 | E54: 46024 | F54: SUCCESS | G54: 13205 | H54: 25404 | I54: Lost World of Tambun Amusement and Water Park - Admission (MALAYSIAN CITIZENS) | K54: BeMyGuest | L54: 111 | M54: BeMyGuest_API | N54: 2992 | O54: VENDOR_API | P54: PORTAL_DEPOSIT | Q54: NUR HIDAYAH BINTI ALI | R54: { "totalCount": 1, "personList": [{ "count": 1, "type": "ADULT", "priceNet": 82.0 }] } | S54: DATE_OF_BOOKING | T54: b35ef7c6-f423-4eec-bfaa-eaaa3652fc6e | U54: TODO | V54: RECONCILIATION_STATUS_AUTO_RECONCILED | W54: RECON | X54: 7 | Y54: 46022.816 | Z54: 46073.389 | AA54: MYR | AB54: 95 | AC54: 81.78 | AD54: { } | AE54: TRUE | AF54: COMPLETED | AI54: FALSE | AL54: Reconciled | AM54: FALSE | AN54: Net price discrepancy | AO54: 1 | AP54: 82 | AQ54: 82
A55: reconciliation_1840829168444896 | B55: 29357357 | C55: 15618187 | D55: 46022.817 | E55: 46023 | F55: SUCCESS | G55: 30482 | H55: 63737 | I55: New York Historical Society - Admission | K55: BeMyGuest | L55: 111 | M55: BeMyGuest_API | N55: 2992 | O55: VENDOR_API | P55: PORTAL_DEPOSIT | Q55: Laura Hobby | R55: { "totalCount": 2, "personList": [{ "count": 2, "type": "ADULT", "priceNet": 18.01 }] } | S55: DATE_OF_BOOKING | T55: 7daa93b8-13c4-42f8-a52b-3a50af13fbd6 | U55: TODO | V55: RECONCILIATION_STATUS_AUTO_RECONCILED | W55: RECON | X55: 7 | Y55: 46022.817 | Z55: 46073.389 | AA55: USD | AB55: 48.02 | AC55: 36.17 | AD55: { } | AE55: TRUE | AF55: COMPLETED | AI55: FALSE | AL55: Reconciled | AM55: FALSE | AN55: Net price discrepancy | AO55: 2 | AP55: 18.01 | AQ55: 36.02
A56: reconciliation_1842319646984810 | B56: 29357621 | C56: 15618377 | D56: 46022.834 | E56: 46022 | F56: SUCCESS | G56: 11655 | H56: 22128 | I56: General Admission | K56: BeMyGuest | L56: 111 | M56: BeMyGuest_API | N56: 2992 | O56: VENDOR_API | P56: PORTAL_DEPOSIT | Q56: Meri Andrasyan | R56: { "totalCount": 2, "personList": [{ "count": 2, "type": "ADULT", "priceNet": 31.19 }] } | S56: DATE_OF_BOOKING | T56: 9242bfcd-8863-4460-aa83-f619539e48f7 | U56: TODO | V56: RECONCILIATION_STATUS_AUTO_RECONCILED | W56: RECON | X56: 7 | Y56: 46022.834 | Z56: 46073.389 | AA56: USD | AB56: 78 | AC56: 62.65 | AD56: { "extraCharges": [{ "amountInTourCurrency": 4.0, "chargeType": "ABSOLUTE", "extraChargeCode": "CONVENIENCE_FEE", "chargeValue": 2.0 }] } | AE56: TRUE | AF56: COMPLETED | AI56: FALSE | AL56: Reconciled | AM56: FALSE | AN56: Net price discrepancy | AO56: 2 | AP56: 31.19 | AQ56: 62.38
A57: reconciliation_1325996364583421 | B57: 29357753 | C57: 15618497 | D57: 46022.843 | E57: 46022 | F57: SUCCESS | G57: 11655 | H57: 22128 | I57: General Admission | K57: BeMyGuest | L57: 111 | M57: BeMyGuest_API | N57: 2992 | O57: VENDOR_API | P57: PORTAL_DEPOSIT | Q57: Yuhua Nie | R57: { "totalCount": 2, "personList": [{ "count": 2, "type": "ADULT", "priceNet": 31.19 }] } | S57: DATE_OF_BOOKING | T57: 32bc10ef-d395-4714-a65a-544c7d034f3d | U57: TODO | V57: RECONCILIATION_STATUS_AUTO_RECONCILED | W57: RECON | X57: 7 | Y57: 46022.843 | Z57: 46073.389 | AA57: USD | AB57: 78 | AC57: 62.65 | AD57: { "extraCharges": [{ "amountInTourCurrency": 4.0, "chargeType": "ABSOLUTE", "extraChargeCode": "CONVENIENCE_FEE", "chargeValue": 2.0 }] } | AE57: TRUE | AF57: COMPLETED | AI57: FALSE | AL57: Reconciled | AM57: FALSE | AN57: Net price discrepancy | AO57: 2 | AP57: 31.19 | AQ57: 62.38
A58: reconciliation_1329477835979218 | B58: 29358240 | C58: 15618905 | D58: 46022.884 | E58: 46022 | F58: SUCCESS | G58: 11655 | H58: 22128 | I58: General Admission | K58: BeMyGuest | L58: 111 | M58: BeMyGuest_API | N58: 2992 | O58: VENDOR_API | P58: PORTAL_DEPOSIT | Q58: Camila alejandra ruiz ascencio | R58: { "totalCount": 5, "personList": [{ "count": 5, "type": "ADULT", "priceNet": 31.19 }] } | S58: DATE_OF_BOOKING | T58: 1a25952a-1731-41da-8952-e40f7b53b83c | U58: TODO | V58: RECONCILIATION_STATUS_AUTO_RECONCILED | W58: RECON | X58: 7 | Y58: 46022.884 | Z58: 46073.389 | AA58: USD | AB58: 195 | AC58: 156.63 | AD58: { "extraCharges": [{ "amountInTourCurrency": 10.0, "chargeType": "ABSOLUTE", "extraChargeCode": "CONVENIENCE_FEE", "chargeValue": 2.0 }] } | AE58: TRUE | AF58: COMPLETED | AI58: FALSE | AL58: Reconciled | AM58: FALSE | AN58: Net price discrepancy | AO58: 5 | AP58: 31.19 | AQ58: 155.95
A59: reconciliation_1848554132624057 | B59: 29358514 | C59: 15619130 | D59: 46022.906 | E59: 46025 | F59: SUCCESS | G59: 35805 | H59: 67661 | I59: Scienceworks Melbourne - Admission | K59: BeMyGuest | L59: 111 | M59: BeMyGuest_Off Peak | N59: 1858 | O59: VENDOR_API | P59: PORTAL_DEPOSIT | Q59: Wendy Wei Wang | R59: { "totalCount": 1, "personList": [{ "count": 1, "type": "ADULT", "priceNet": 12.92 }] } | S59: DATE_OF_BOOKING | T59: 3e7a30a6-ea8e-4787-bbc8-5d8d26e1550c | U59: TODO | V59: RECONCILIATION_STATUS_AUTO_RECONCILED | W59: RECON | X59: 7 | Y59: 46022.906 | Z59: 46073.389 | AA59: AUD | AB59: 14.16 | AC59: 12.92 | AD59: { } | AE59: TRUE | AF59: COMPLETED | AI59: FALSE | AL59: Forex | AM59: FALSE | AN59: Net price discrepancy | AO59: 1 | AP59: 12.92 | AQ59: 12.92
A60: reconciliation_1855185413017139 | B60: 29359245 | C60: 15619731 | D60: 46022.983 | E60: 46091 | F60: SUCCESS | G60: 7442 | H60: 43120 | I60: Universal Studios Singapore - One Day Ticket | K60: BeMyGuest | L60: 111 | M60: BeMyGuest_API | N60: 2992 | O60: VENDOR_API | P60: PORTAL_DEPOSIT | Q60: Michael joseph Bowen | R60: { "totalCount": 2, "personList": [{ "count": 2, "type": "ADULT", "priceNet": 68.0 }] } | S60: DATE_OF_BOOKING | T60: ee7d8dfa-59a6-4fbf-b8a9-d3eddf172f8a | U60: TODO | V60: RECONCILIATION_STATUS_AUTO_RECONCILED | W60: RECON | X60: 7 | Y60: 46022.983 | Z60: 46073.389 | AA60: SGD | AB60: 150.12 | AC60: 136 | AD60: { } | AE60: TRUE | AF60: COMPLETED | AI60: FALSE | AL60: Reconciled | AM60: FALSE | AN60: Reconciliation ALREADY auto reconciled | AO60: 2 | AP60: 68 | AQ60: 136
A61: reconciliation_1338282447829662 | B61: 29359268 | C61: 15619747 | D61: 46022.986 | E61: 46022 | F61: SUCCESS | G61: 11655 | H61: 22128 | I61: General Admission | K61: BeMyGuest | L61: 111 | M61: BeMyGuest_API | N61: 2992 | O61: VENDOR_API | P61: PORTAL_DEPOSIT | Q61: Frank Finch | R61: { "totalCount": 8, "personList": [{ "count": 7, "type": "ADULT", "priceNet": 31.19 }, { "count": 1, "type": "CHILD", "priceNet": 20.79 }] } | S61: DATE_OF_BOOKING | T61: ea9102b5-3aa0-4b52-aa8b-00e5133f9905 | U61: TODO | V61: RECONCILIATION_STATUS_MANUALLY_RECONCILED | W61: RECON | X61: 7 | Y61: 46022.986 | Z61: 46073.389 | AA61: USD | AB61: 298.99 | AC61: 240.17 | AD61: { "extraCharges": [{ "amountInTourCurrency": 16.0, "chargeType": "ABSOLUTE", "extraChargeCode": "CONVENIENCE_FEE", "chargeValue": 2.0 }] } | AE61: TRUE | AF61: COMPLETED | AI61: FALSE | AL61: Reconciled | AM61: FALSE | AN61: Net price discrepancy | AO61: 7 | AP61: 31.19 | AQ61: 218.33 | AU61: 1 | AV61: 20.79 | AW61: 20.79
A62: reconciliation_1342878133915796 | B62: 29359730 | C62: 15620110 | D62: 46023.039 | E62: 46025 | F62: SUCCESS | G62: 35785 | H62: 83215 | I62: Grand Seating (Splash Area) | K62: BeMyGuest | L62: 111 | M62: BeMyGuest_API | N62: 2992 | O62: VENDOR_API | P62: PORTAL_DEPOSIT | Q62: Leath Nicholson | R62: { "totalCount": 4, "personList": [{ "count": 4, "type": "GENERAL", "priceNet": 988.0 }] } | S62: DATE_OF_BOOKING | T62: 4865072f-c38e-442e-a99a-5934ebcf1129 | U62: TODO | V62: RECONCILIATION_STATUS_MANUALLY_RECONCILED | W62: RECON | X62: 5 | Y62: 46023.039 | Z62: 46073.389 | AA62: MOP | AB62: 4528 | AC62: 3952 | AD62: { } | AE62: FALSE | AF62: COMPLETED | AI62: FALSE | AL62: Forex | AM62: FALSE | AN62: Net price discrepancy | BD62: 4 | BE62: 988 | BF62: 3952
A63: reconciliation_1343092563561097 | B63: 29359748 | C63: 15620131 | D63: 46023.041 | E63: 46023 | F63: SUCCESS | G63: 7442 | H63: 43120 | I63: Universal Studios Singapore - One Day Ticket | K63: BeMyGuest | L63: 111 | M63: BeMyGuest_API | N63: 2992 | O63: VENDOR_API | P63: PORTAL_DEPOSIT | Q63: YORIKO OTAKA | R63: { "totalCount": 3, "personList": [{ "count": 1, "type": "ADULT", "priceNet": 75.0 }, { "count": 2, "type": "CHILD", "priceNet": 66.0 }] } | S63: DATE_OF_BOOKING | T63: 7d0dc870-1dca-41c6-baa5-e9a24fd6a4c9 | U63: TODO | V63: RECONCILIATION_STATUS_AUTO_RECONCILED | W63: RECON | X63: 6 | Y63: 46023.041 | Z63: 46073.389 | AA63: SGD | AB63: 221.29 | AC63: 207 | AD63: { } | AE63: TRUE | AF63: COMPLETED | AI63: FALSE | AL63: Reconciled | AM63: FALSE | AN63: Reconciliation ALREADY auto reconciled | AO63: 1 | AP63: 75 | AQ63: 75 | AU63: 2 | AV63: 66 | AW63: 132
A64: reconciliation_1860411332647098 | B64: 29359779 | C64: 15620150 | D64: 46023.043 | E64: 46023 | F64: SUCCESS | G64: 10283 | H64: 26872 | I64: SEA LIFE Sydney Aquarium - Morning Admission | K64: BeMyGuest | L64: 111 | M64: BeMyGuest_Peak | N64: 2145 | O64: VENDOR_API | P64: PORTAL_DEPOSIT | Q64: Cameron Cross | R64: { "totalCount": 2, "personList": [{ "count": 2, "type": "ADULT", "priceNet": 32.53 }] } | S64: DATE_OF_BOOKING | T64: 9dcb55c4-8c3a-4442-beec-24eab0d606c3 | U64: TODO | V64: RECONCILIATION_STATUS_MANUALLY_RECONCILED | W64: RECON | X64: 6 | Y64: 46023.043 | Z64: 46073.389 | AA64: AUD | AB64: 113.06 | AC64: 65.06 | AD64: { } | AE64: TRUE | AF64: COMPLETED | AI64: FALSE | AL64: Forex | AM64: FALSE | AN64: Net price discrepancy | AO64: 2 | AP64: 32.53 | AQ64: 65.06
A65: reconciliation_1861638284709386 | B65: 29359933 | C65: 15620273 | D65: 46023.057 | E65: 46023 | F65: FAILED | G65: 13613 | H65: 39989 | I65: Mastercard® Canopy Bridge with Complimentary Canopy Park Admission | K65: BeMyGuest | L65: 111 | M65: BeMyGuest_API | N65: 2992 | O65: VENDOR_API | P65: PORTAL_DEPOSIT | Q65: Lim Pei Shi | R65: { "totalCount": 7, "personList": [{ "count": 7, "type": "ADULT", "priceNet": 8.3 }] } | S65: DATE_OF_BOOKING | U65: TODO | V65: RECONCILIATION_STATUS_PENDING | W65: RECON | X65: 3 | Y65: 46023.057 | Z65: 46023.066 | AA65: SGD | AB65: 81.34 | AC65: 58.1 | AD65: { } | AE65: FALSE | AF65: COMPLETED | AI65: FALSE | AM65: FALSE | AN65: Reconciliation ALREADY auto reconciled | AO65: 7 | AP65: 8.3 | AQ65: 58.1
A66: reconciliation_1862326161093863 | B66: 29359933 | C66: 15620335 | D66: 46023.065 | E66: 46023 | F66: SUCCESS | G66: 13613 | H66: 39989 | I66: Mastercard® Canopy Bridge with Complimentary Canopy Park Admission | K66: BeMyGuest | L66: 111 | M66: BeMyGuest_API | N66: 2992 | O66: VENDOR_API | P66: PORTAL_DEPOSIT | Q66: Lim Pei Shi | R66: { "totalCount": 7, "personList": [{ "count": 7, "type": "ADULT", "priceNet": 8.3 }] } | S66: DATE_OF_BOOKING | T66: a9235c1c-4557-4ae1-9892-5e6a65753500 | U66: TODO | V66: RECONCILIATION_STATUS_AUTO_RECONCILED | W66: RECON | X66: 6 | Y66: 46023.065 | Z66: 46073.389 | AA66: SGD | AB66: 81.34 | AC66: 58.1 | AD66: { } | AE66: TRUE | AF66: COMPLETED | AI66: FALSE | AL66: Reconciled | AM66: FALSE | AN66: Reconciliation ALREADY auto reconciled | AO66: 7 | AP66: 8.3 | AQ66: 58.1
A67: reconciliation_1861727963919118 | B67: 29359946 | C67: 15620281 | D67: 46023.058 | E67: 46023 | F67: SUCCESS | G67: 13613 | H67: 39989 | I67: Mastercard® Canopy Bridge with Complimentary Canopy Park Admission | K67: BeMyGuest | L67: 111 | M67: BeMyGuest_API | N67: 2992 | O67: VENDOR_API | P67: PORTAL_DEPOSIT | Q67: Tan Bee Keng | R67: { "totalCount": 7, "personList": [{ "count": 7, "type": "ADULT", "priceNet": 8.3 }] } | S67: DATE_OF_BOOKING | T67: df8df17f-4258-4427-bd1c-4fdc09493b73 | U67: TODO | V67: RECONCILIATION_STATUS_AUTO_RECONCILED | W67: RECON | X67: 6 | Y67: 46023.058 | Z67: 46073.389 | AA67: SGD | AB67: 81.34 | AC67: 58.1 | AD67: { } | AE67: TRUE | AF67: COMPLETED | AI67: FALSE | AL67: Reconciled | AM67: FALSE | AN67: Reconciliation ALREADY auto reconciled | AO67: 7 | AP67: 8.3 | AQ67: 58.1
A68: reconciliation_1861901812923454 | B68: 29359962 | C68: 15620294 | D68: 46023.06 | E68: 46023 | F68: SUCCESS | G68: 13613 | H68: 39989 | I68: Mastercard® Canopy Bridge with Complimentary Canopy Park Admission | K68: BeMyGuest | L68: 111 | M68: BeMyGuest_API | N68: 2992 | O68: VENDOR_API | P68: PORTAL_DEPOSIT | Q68: Wong Qiao Yi | R68: { "totalCount": 7, "personList": [{ "count": 7, "type": "ADULT", "priceNet": 8.3 }] } | S68: DATE_OF_BOOKING | T68: ff9bf88b-d400-459b-bea5-dccff233978a | U68: TODO | V68: RECONCILIATION_STATUS_AUTO_RECONCILED | W68: RECON | X68: 6 | Y68: 46023.06 | Z68: 46073.389 | AA68: SGD | AB68: 81.34 | AC68: 58.1 | AD68: { } | AE68: TRUE | AF68: COMPLETED | AI68: FALSE | AL68: Reconciled | AM68: FALSE | AN68: Reconciliation ALREADY auto reconciled | AO68: 7 | AP68: 8.3 | AQ68: 58.1
A69: reconciliation_1862031570844696 | B69: 29359976 | C69: 15620308 | D69: 46023.062 | E69: 46023 | F69: SUCCESS | G69: 7442 | H69: 43120 | I69: Universal Studios Singapore - One Day Ticket | K69: BeMyGuest | L69: 111 | M69: BeMyGuest_API | N69: 2992 | O69: VENDOR_API | P69: PORTAL_DEPOSIT | Q69: VICNESH NADARAJAH | R69: { "totalCount": 2, "personList": [{ "count": 1, "type": "ADULT", "priceNet": 75.0 }, { "count": 1, "type": "CHILD", "priceNet": 66.0 }] } | S69: DATE_OF_BOOKING | T69: cf0f2116-c839-4a7b-b919-53fe0e8f0e69 | U69: TODO | V69: RECONCILIATION_STATUS_AUTO_RECONCILED | W69: RECON | X69: 6 | Y69: 46023.062 | Z69: 46073.389 | AA69: SGD | AB69: 152.04 | AC69: 141 | AD69: { } | AE69: TRUE | AF69: COMPLETED | AI69: FALSE | AL69: Reconciled | AM69: FALSE | AN69: Reconciliation ALREADY auto reconciled | AO69: 1 | AP69: 75 | AQ69: 75 | AU69: 1 | AV69: 66 | AW69: 66
A70: reconciliation_1862064146057918 | B70: 29359984 | C70: 15620312 | D70: 46023.062 | E70: 46023 | F70: SUCCESS | G70: 31203 | H70: 65275 | I70: Singapore River Cruise by WaterB | K70: BeMyGuest | L70: 111 | M70: BeMyGuest_API | N70: 2992 | O70: VENDOR_API | P70: PORTAL_DEPOSIT | Q70: Rubben Muniandy | R70: { "totalCount": 5, "personList": [{ "count": 3, "type": "ADULT", "priceNet": 23.2 }, { "count": 2, "type": "CHILD", "priceNet": 15.0 }] } | S70: DATE_OF_BOOKING | T70: 0c092e1b-19a9-44f1-93c3-ed2edc029285 | U70: TODO | V70: RECONCILIATION_STATUS_AUTO_RECONCILED | W70: RECON | X70: 6 | Y70: 46023.062 | Z70: 46073.389 | AA70: SGD | AB70: 107 | AC70: 99.6 | AD70: { "extraCharges": [{ "amountInTourCurrency": 5.35, "chargeType": "PERCENTAGE", "extraChargeCode": "CONVENIENCE_FEE", "chargeValue": 5.0 }] } | AE70: TRUE | AF70: COMPLETED | AI70: FALSE | AL70: Reconciled | AM70: FALSE | AN70: Reconciliation ALREADY auto reconciled | AO70: 3 | AP70: 23.2 | AQ70: 69.6 | AU70: 2 | AV70: 15 | AW70: 30
A71: reconciliation_1345194766973067 | B71: 29360017 | C71: 15620340 | D71: 46023.066 | E71: 46023 | F71: SUCCESS | G71: 7371 | H71: 13460 | I71: Marina Bay Sands SkyPark Observation Deck - Admission (Entry until 4:00 PM) | K71: BeMyGuest | L71: 111 | M71: BeMyGuest_API | N71: 2992 | O71: VENDOR_API | P71: PORTAL_DEPOSIT | Q71: Manikandan selamuthu Krishnamurthy | R71: { "totalCount": 4, "personList": [{ "count": 3, "type": "ADULT", "priceNet": 33.2 }, { "count": 1, "type": "CHILD", "priceNet": 28.2 }] } | S71: DATE_OF_BOOKING | T71: f9645c90-4a62-480f-892a-54e335aad220 | U71: TODO | V71: RECONCILIATION_STATUS_AUTO_RECONCILED | W71: RECON | X71: 6 | Y71: 46023.066 | Z71: 46073.389 | AA71: SGD | AB71: 136 | AC71: 127.8 | AD71: { "extraCharges": [{ "amountInTourCurrency": 13.6, "chargeType": "PERCENTAGE", "extraChargeCode": "CONVENIENCE_FEE", "chargeValue": 10.0 }] } | AE71: TRUE | AF71: COMPLETED | AI71: FALSE | AL71: Reconciled | AM71: FALSE | AN71: Reconciliation ALREADY auto reconciled | AO71: 3 | AP71: 33.2 | AQ71: 99.6 | AU71: 1 | AV71: 28.2 | AW71: 28.2
A72: reconciliation_1863045597084216 | B72: 29360096 | C72: 15620402 | D72: 46023.074 | E72: 46023 | F72: SUCCESS | G72: 7442 | H72: 43120 | I72: Universal Studios Singapore - One Day Ticket | K72: BeMyGuest | L72: 111 | M72: BeMyGuest_API | N72: 2992 | O72: VENDOR_API | P72: PORTAL_DEPOSIT | Q72: Juliana Lalli | R72: { "totalCount": 3, "personList": [{ "count": 2, "type": "ADULT", "priceNet": 75.0 }, { "count": 1, "type": "CHILD", "priceNet": 66.0 }] } | S72: DATE_OF_BOOKING | T72: a170f4fb-982a-484f-9190-4760f5803d55 | U72: TODO | V72: RECONCILIATION_STATUS_AUTO_RECONCILED | W72: RECON | X72: 6 | Y72: 46023.074 | Z72: 46073.389 | AA72: SGD | AB72: 234.83 | AC72: 216 | AD72: { } | AE72: TRUE | AF72: COMPLETED | AI72: FALSE | AL72: Reconciled | AM72: FALSE | AN72: Reconciliation ALREADY auto reconciled | AO72: 2 | AP72: 75 | AQ72: 150 | AU72: 1 | AV72: 66 | AW72: 66
A73: reconciliation_1346482338350960 | B73: 29360161 | C73: 15620454 | D73: 46023.081 | E73: 46023 | F73: SUCCESS | G73: 7371 | H73: 13460 | I73: Marina Bay Sands SkyPark Observation Deck - Admission (Entry until 4:00 PM) | K73: BeMyGuest | L73: 111 | M73: BeMyGuest_API | N73: 2992 | O73: VENDOR_API | P73: PORTAL_DEPOSIT | Q73: Cindy Vachutta | R73: { "totalCount": 2, "personList": [{ "count": 2, "type": "ADULT", "priceNet": 33.2 }] } | S73: DATE_OF_BOOKING | T73: 5755fce9-512e-489c-9b26-26ae7feba915 | U73: TODO | V73: RECONCILIATION_STATUS_AUTO_RECONCILED | W73: RECON | X73: 6 | Y73: 46023.08 | Z73: 46073.389 | AA73: SGD | AB73: 70 | AC73: 66.4 | AD73: { "extraCharges": [{ "amountInTourCurrency": 7.0, "chargeType": "PERCENTAGE", "extraChargeCode": "CONVENIENCE_FEE", "chargeValue": 10.0 }] } | AE73: TRUE | AF73: COMPLETED | AI73: FALSE | AL73: Reconciled | AM73: FALSE | AN73: Reconciliation ALREADY auto reconciled | AO73: 2 | AP73: 33.2 | AQ73: 66.4
A74: reconciliation_1346466306194863 | B74: 29360172 | C74: 15620450 | D74: 46023.08 | E74: 46023 | F74: SUCCESS | G74: 23404 | H74: 76805 | I74: SEA LIFE Bangkok - Admission with Digiphoto (Peak) + Glass Bottom Boat | K74: BeMyGuest | L74: 111 | M74: BeMyGuest_Off Peak | N74: 1858 | O74: VENDOR_API | P74: PORTAL_DEPOSIT | Q74: Rusyaifiza Ramli | R74: { "totalCount": 4, "personList": [{ "count": 2, "type": "ADULT", "priceNet": 1040.0 }, { "count": 2, "type": "CHILD", "priceNet": 900.0 }] } | S74: DATE_OF_BOOKING | T74: 322d841a-d8a1-4f82-a5b7-317966489818 | U74: TODO | V74: RECONCILIATION_STATUS_MANUALLY_RECONCILED | W74: RECON | X74: 6 | Y74: 46023.08 | Z74: 46073.389 | AA74: THB | AB74: 4485.92 | AC74: 3858.79 | AD74: { } | AE74: TRUE | AF74: COMPLETED | AI74: FALSE | AL74: Reconciled | AM74: FALSE | AN74: Net price discrepancy | AO74: 2 | AP74: 1040 | AQ74: 2080 | AU74: 2 | AV74: 900 | AW74: 1800
A75: reconciliation_1864216941315344 | B75: 29360234 | C75: 15620506 | D75: 46023.087 | E75: 46024 | F75: SUCCESS | G75: 24823 | H75: 30850 | I75: Singapore Night Safari - Open Dated Admission with Tram Ride (Singapore Residents) | K75: BeMyGuest | L75: 111 | M75: BeMyGuest_Off Peak | N75: 1858 | O75: VENDOR_API | P75: PORTAL_DEPOSIT | Q75: Ryo Konishi | R75: { "totalCount": 4, "personList": [{ "count": 2, "type": "ADULT", "priceNet": 51.6 }, { "count": 2, "type": "CHILD", "priceNet": 36.3 }] } | S75: DATE_OF_BOOKING | T75: b82b5eb6-b18a-43d2-a79b-a4c4574c0ace | U75: TODO | V75: RECONCILIATION_STATUS_AUTO_RECONCILED | W75: RECON | X75: 6 | Y75: 46023.087 | Z75: 46073.389 | AA75: SGD | AB75: 198 | AC75: 175.8 | AD75: { } | AE75: TRUE | AF75: COMPLETED | AI75: FALSE | AL75: Reconciled | AM75: FALSE | AN75: Reconciliation ALREADY auto reconciled | AO75: 2 | AP75: 51.6 | AQ75: 103.2 | AU75: 2 | AV75: 36.3 | AW75: 72.6
A76: reconciliation_1864324677823581 | B76: 29360242 | C76: 15620518 | D76: 46023.089 | E76: 46023 | F76: SUCCESS | G76: 17237 | H76: 13460 | I76: Marina Bay Sands SkyPark Observation Deck - Admission (Entry until 4:00 PM) | K76: BeMyGuest | L76: 111 | M76: BeMyGuest_API | N76: 2992 | O76: VENDOR_API | P76: PORTAL_DEPOSIT | Q76: Rachel Porteous | R76: { "totalCount": 5, "personList": [{ "count": 5, "type": "ADULT", "priceNet": 33.2 }] } | S76: DATE_OF_BOOKING | T76: e371fc6a-ba54-4bed-a6c3-18c0b78e3afb | U76: TODO | V76: RECONCILIATION_STATUS_AUTO_RECONCILED | W76: RECON | X76: 6 | Y76: 46023.089 | Z76: 46073.389 | AA76: SGD | AB76: 153.25 | AC76: 166 | AD76: { "extraCharges": [{ "amountInTourCurrency": 15.323, "chargeType": "PERCENTAGE", "extraChargeCode": "CONVENIENCE_FEE", "chargeValue": 10.0 }] } | AE76: TRUE | AF76: COMPLETED | AI76: FALSE | AL76: Reconciled | AM76: FALSE | AN76: Reconciliation ALREADY auto reconciled | AO76: 5 | AP76: 33.2 | AQ76: 166
A77: reconciliation_1347257392501767 | B77: 29360254 | C77: 15620526 | D77: 46023.089 | E77: 46023 | F77: SUCCESS | G77: 17237 | H77: 13460 | I77: Marina Bay Sands SkyPark Observation Deck - Admission (Entry until 4:00 PM) | K77: BeMyGuest | L77: 111 | M77: BeMyGuest_API | N77: 2992 | O77: VENDOR_API | P77: PORTAL_DEPOSIT | Q77: BIGFELLA TE AHO | R77: { "totalCount": 3, "personList": [{ "count": 3, "type": "ADULT", "priceNet": 33.2 }] } | S77: DATE_OF_BOOKING | T77: 1035f268-5e67-4ab3-94f9-9ead2527a4f2 | U77: TODO | V77: RECONCILIATION_STATUS_AUTO_RECONCILED | W77: RECON | X77: 6 | Y77: 46023.089 | Z77: 46073.389 | AA77: SGD | AB77: 91.95 | AC77: 99.6 | AD77: { "extraCharges": [{ "amountInTourCurrency": 9.194, "chargeType": "PERCENTAGE", "extraChargeCode": "CONVENIENCE_FEE", "chargeValue": 10.0 }] } | AE77: TRUE | AF77: COMPLETED | AI77: FALSE | AL77: Reconciled | AM77: FALSE | AN77: Reconciliation ALREADY auto reconciled | AO77: 3 | AP77: 33.2 | AQ77: 99.6
A78: reconciliation_1864706438373555 | B78: 29360288 | C78: 15620548 | D78: 46023.093 | E78: 46023 | F78: SUCCESS | G78: 18972 | H78: 36816 | I78: Devdan Show - Category C Seating without Transfers | K78: BeMyGuest | L78: 111 | M78: BeMyGuest_API | N78: 2992 | O78: VENDOR_API | P78: PORTAL_DEPOSIT | Q78: Abbas Alibhai | R78: { "totalCount": 4, "personList": [{ "count": 2, "type": "ADULT", "priceNet": 315912.0 }, { "count": 2, "type": "CHILD", "priceNet": 157956.0 }] } | S78: DATE_OF_BOOKING | T78: f4b435ea-09c1-46d8-9bb2-45cb0e4f4a95 | U78: TODO | V78: RECONCILIATION_STATUS_AUTO_RECONCILED | W78: RECON | X78: 6 | Y78: 46023.093 | Z78: 46073.389 | AA78: IDR | AB78: 1079982 | AC78: 947736 | AD78: { } | AE78: TRUE | AF78: COMPLETED | AI78: FALSE | AL78: Forex | AM78: FALSE | AN78: Net price discrepancy | AO78: 2 | AP78: 315912 | AQ78: 631824 | AU78: 2 | AV78: 157956 | AW78: 315912
A79: reconciliation_1864957962767333 | B79: 29360328 | C79: 15620585 | D79: 46023.096 | E79: 46023 | F79: SUCCESS | G79: 17237 | H79: 13460 | I79: Marina Bay Sands SkyPark Observation Deck - Admission (Entry until 4:00 PM) | K79: BeMyGuest | L79: 111 | M79: BeMyGuest_API | N79: 2992 | O79: VENDOR_API | P79: PORTAL_DEPOSIT | Q79: Vladislav Kan | R79: { "totalCount": 4, "personList": [{ "count": 4, "type": "ADULT", "priceNet": 33.2 }] } | S79: DATE_OF_BOOKING | T79: f7dd9fc5-9cf3-41c6-89e4-7c35f02c8b5e | U79: TODO | V79: RECONCILIATION_STATUS_AUTO_RECONCILED | W79: RECON | X79: 6 | Y79: 46023.096 | Z79: 46073.389 | AA79: SGD | AB79: 122.6 | AC79: 132.8 | AD79: { "extraCharges": [{ "amountInTourCurrency": 12.258, "chargeType": "PERCENTAGE", "extraChargeCode": "CONVENIENCE_FEE", "chargeValue": 10.0 }] } | AE79: TRUE | AF79: COMPLETED | AI79: FALSE | AL79: Reconciled | AM79: FALSE | AN79: Reconciliation ALREADY auto reconciled | AO79: 4 | AP79: 33.2 | AQ79: 132.8
A80: reconciliation_1865350725073519 | B80: 29360382 | C80: 15620629 | D80: 46023.1 | E80: 46104 | F80: SUCCESS | G80: 7442 | H80: 43120 | I80: Universal Studios Singapore - One Day Ticket | K80: BeMyGuest | L80: 111 | M80: BeMyGuest_API | N80: 2992 | O80: VENDOR_API | P80: PORTAL_DEPOSIT | Q80: Elycia Tamara Morgan | R80: { "totalCount": 2, "personList": [{ "count": 2, "type": "ADULT", "priceNet": 68.0 }] } | S80: DATE_OF_BOOKING | T80: 3e646848-28fd-48dd-a348-0595a663c349 | U80: TODO | V80: RECONCILIATION_STATUS_AUTO_RECONCILED | W80: RECON | X80: 6 | Y80: 46023.1 | Z80: 46073.389 | AA80: SGD | AB80: 150.12 | AC80: 136 | AD80: { } | AE80: TRUE | AF80: COMPLETED | AI80: FALSE | AL80: Reconciled | AM80: FALSE | AN80: Reconciliation ALREADY auto reconciled | AO80: 2 | AP80: 68 | AQ80: 136
A81: reconciliation_1865366758433691 | B81: 29360389 | C81: 15620630 | D81: 46023.101 | E81: 46023 | F81: SUCCESS | G81: 7443 | H81: 13581 | I81: S.E.A. Aquarium - Admission | K81: BeMyGuest | L81: 111 | M81: BeMyGuest_API | N81: 2992 | O81: VENDOR_API | P81: PORTAL_DEPOSIT | Q81: Yolanda Maria Teresa MacDonald | R81: { "totalCount": 4, "personList": [{ "count": 3, "type": "ADULT", "priceNet": 47.0 }, { "count": 1, "type": "CHILD", "priceNet": 39.0 }] } | S81: DATE_OF_BOOKING | T81: 87ddbc8f-db36-46ff-bd84-0c1ca43a6a28 | U81: TODO | V81: RECONCILIATION_STATUS_AUTO_RECONCILED | W81: RECON | X81: 6 | Y81: 46023.101 | Z81: 46073.389 | AA81: SGD | AB81: 208 | AC81: 180 | AD81: { "extraCharges": [{ "amountInTourCurrency": 20.8, "chargeType": "PERCENTAGE", "extraChargeCode": "CONVENIENCE_FEE", "chargeValue": 10.0 }] } | AE81: TRUE | AF81: COMPLETED | AI81: FALSE | AL81: Reconciled | AM81: FALSE | AN81: Reconciliation ALREADY auto reconciled | AO81: 3 | AP81: 47 | AQ81: 141 | AU81: 1 | AV81: 39 | AW81: 39
A82: reconciliation_1348245403243477 | B82: 29360393 | C82: 15620637 | D82: 46023.101 | E82: 46023 | F82: SUCCESS | G82: 17237 | H82: 13460 | I82: Marina Bay Sands SkyPark Observation Deck - Admission (Entry until 4:00 PM) | K82: BeMyGuest | L82: 111 | M82: BeMyGuest_API | N82: 2992 | O82: VENDOR_API | P82: PORTAL_DEPOSIT | Q82: Carsten Dreissig | R82: { "totalCount": 2, "personList": [{ "count": 2, "type": "ADULT", "priceNet": 33.2 }] } | S82: DATE_OF_BOOKING | T82: 9a27a54c-e66c-41db-ab6c-c52f44063127 | U82: TODO | V82: RECONCILIATION_STATUS_AUTO_RECONCILED | W82: RECON | X82: 6 | Y82: 46023.101 | Z82: 46073.389 | AA82: SGD | AB82: 61.3 | AC82: 66.4 | AD82: { "extraCharges": [{ "amountInTourCurrency": 6.129, "chargeType": "PERCENTAGE", "extraChargeCode": "CONVENIENCE_FEE", "chargeValue": 10.0 }] } | AE82: TRUE | AF82: COMPLETED | AI82: FALSE | AL82: Reconciled | AM82: FALSE | AN82: Reconciliation ALREADY auto reconciled | AO82: 2 | AP82: 33.2 | AQ82: 66.4
A83: reconciliation_1865629294371892 | B83: 29360417 | C83: 15620654 | D83: 46023.104 | E83: 46023 | F83: SUCCESS | G83: 13613 | H83: 26013 | I83: Jewel Changi Airport - Canopy Park | K83: BeMyGuest | L83: 111 | M83: BeMyGuest_API | N83: 2992 | O83: VENDOR_API | P83: PORTAL_DEPOSIT | Q83: Tan Ngah Sze Bevelyn | R83: { "totalCount": 2, "personList": [{ "count": 2, "type": "ADULT", "priceNet": 4.8 }] } | S83: DATE_OF_BOOKING | T83: 66aff15f-ffe9-4518-954e-c14bf4f58750 | U83: TODO | V83: RECONCILIATION_STATUS_AUTO_RECONCILED | W83: RECON | X83: 6 | Y83: 46023.104 | Z83: 46073.389 | AA83: SGD | AB83: 14.6 | AC83: 9.6 | AD83: { } | AE83: TRUE | AF83: COMPLETED | AI83: FALSE | AL83: Reconciled | AM83: FALSE | AN83: Reconciliation ALREADY auto reconciled | AO83: 2 | AP83: 4.8 | AQ83: 9.6
A84: reconciliation_1866926876820010 | B84: 29360421 | C84: 15620787 | D84: 46023.119 | E84: 46023 | F84: SUCCESS | G84: 10339 | H84: 19178 | I84: Taronga Zoo - Admission | K84: BeMyGuest | L84: 111 | M84: BeMyGuest_API | N84: 2992 | O84: VENDOR_API | P84: PORTAL_DEPOSIT | Q84: Antara Martins | R84: { "totalCount": 2, "personList": [{ "count": 2, "type": "ADULT", "priceNet": 39.65 }] } | S84: DATE_OF_BOOKING | T84: 0cc416c3-afa5-4a72-899d-298b3a85fa9d | U84: TODO | V84: RECONCILIATION_STATUS_MANUALLY_RECONCILED | W84: RECON | X84: 6 | Y84: 46023.119 | Z84: 46073.389 | AA84: AUD | AB84: 102 | AC84: 79.3 | AD84: { "extraCharges": [{ "amountInTourCurrency": 10.2, "chargeType": "PERCENTAGE", "extraChargeCode": "CONVENIENCE_FEE", "chargeValue": 10.0 }] } | AE84: TRUE | AF84: COMPLETED | AI84: FALSE | AL84: Forex | AM84: FALSE | AN84: Net price discrepancy | AO84: 2 | AP84: 39.65 | AQ84: 79.3
A85: reconciliation_1865997018540032 | B85: 29360442 | C85: 15620692 | D85: 46023.108 | E85: 46023 | F85: SUCCESS | G85: 7443 | H85: 13581 | I85: S.E.A. Aquarium - Admission | K85: BeMyGuest | L85: 111 | M85: BeMyGuest_API | N85: 2992 | O85: VENDOR_API | P85: PORTAL_DEPOSIT | Q85: Michelle Hadley | R85: { "totalCount": 3, "personList": [{ "count": 2, "type": "ADULT", "priceNet": 47.0 }, { "count": 1, "type": "CHILD", "priceNet": 39.0 }] } | S85: DATE_OF_BOOKING | T85: 1b9f96f4-e2dd-4044-b4cd-0ac8658d0cb9 | U85: TODO | V85: RECONCILIATION_STATUS_AUTO_RECONCILED | W85: RECON | X85: 6 | Y85: 46023.108 | Z85: 46073.389 | AA85: SGD | AB85: 153 | AC85: 133 | AD85: { "extraCharges": [{ "amountInTourCurrency": 15.3, "chargeType": "PERCENTAGE", "extraChargeCode": "CONVENIENCE_FEE", "chargeValue": 10.0 }] } | AE85: TRUE | AF85: COMPLETED | AI85: FALSE | AL85: Reconciled | AM85: FALSE | AN85: Reconciliation ALREADY auto reconciled | AO85: 2 | AP85: 47 | AQ85: 94 | AU85: 1 | AV85: 39 | AW85: 39
A86: reconciliation_1348750894143217 | B86: 29360445 | C86: 15620682 | D86: 46023.107 | E86: 46023 | F86: SUCCESS | G86: 7371 | H86: 13460 | I86: Marina Bay Sands SkyPark Observation Deck - Admission (Entry until 4:00 PM) | K86: BeMyGuest | L86: 111 | M86: BeMyGuest_API | N86: 2992 | O86: VENDOR_API | P86: PORTAL_DEPOSIT | Q86: Lia Di Taranto | R86: { "totalCount": 2, "personList": [{ "count": 2, "type": "ADULT", "priceNet": 33.2 }] } | S86: DATE_OF_BOOKING | T86: a4b49272-8341-4bbe-a405-6de143f6f494 | U86: TODO | V86: RECONCILIATION_STATUS_AUTO_RECONCILED | W86: RECON | X86: 6 | Y86: 46023.107 | Z86: 46073.389 | AA86: SGD | AB86: 70 | AC86: 66.4 | AD86: { "extraCharges": [{ "amountInTourCurrency": 7.0, "chargeType": "PERCENTAGE", "extraChargeCode": "CONVENIENCE_FEE", "chargeValue": 10.0 }] } | AE86: TRUE | AF86: COMPLETED | AI86: FALSE | AL86: Reconciled | AM86: FALSE | AN86: Reconciliation ALREADY auto reconciled | AO86: 2 | AP86: 33.2 | AQ86: 66.4
A87: reconciliation_1348780989548248 | B87: 29360451 | C87: 15620686 | D87: 46023.107 | E87: 46023 | F87: SUCCESS | G87: 24587 | H87: 43120 | I87: Universal Studios Singapore - One Day Ticket | K87: BeMyGuest | L87: 111 | M87: BeMyGuest_API | N87: 2992 | O87: VENDOR_API | P87: PORTAL_DEPOSIT | Q87: Daniella D DeRosa | R87: { "totalCount": 2, "personList": [{ "count": 2, "type": "ADULT", "priceNet": 75.0 }] } | S87: DATE_OF_BOOKING | T87: a0c5eca3-9834-4adc-a5b2-5f85ddd6c848 | U87: TODO | V87: RECONCILIATION_STATUS_AUTO_RECONCILED | W87: RECON | X87: 6 | Y87: 46023.107 | Z87: 46073.389 | AA87: SGD | AB87: 157.3 | AC87: 150 | AD87: { } | AE87: TRUE | AF87: COMPLETED | AI87: FALSE | AL87: Reconciled | AM87: FALSE | AN87: Reconciliation ALREADY auto reconciled | AO87: 2 | AP87: 75 | AQ87: 150
A88: reconciliation_1348912718663498 | B88: 29360456 | C88: 15620699 | D88: 46023.109 | E88: 46023 | F88: SUCCESS | G88: 19403 | H88: 37805 | I88: SuperPark Malaysia - Admission (Three Hours) | K88: BeMyGuest | L88: 111 | M88: BeMyGuest_Peak | N88: 2145 | O88: VENDOR_API | P88: PORTAL_DEPOSIT | Q88: Nabilah binti Ahmad Nasruddin | R88: { "totalCount": 5, "personList": [{ "count": 5, "type": "GENERAL", "priceNet": 41.3 }] } | S88: DATE_OF_BOOKING | T88: 25f9f252-ff78-488f-805a-b876e3a19da1 | U88: TODO | V88: RECONCILIATION_STATUS_AUTO_RECONCILED | W88: RECON | X88: 6 | Y88: 46023.109 | Z88: 46073.389 | AA88: MYR | AB88: 295 | AC88: 205.86 | AD88: { } | AE88: TRUE | AF88: COMPLETED | AI88: FALSE | AL88: Reconciled | AM88: FALSE | AN88: Net price discrepancy | BD88: 5 | BE88: 41.3 | BF88: 206.5
A89: reconciliation_1866212948753743 | B89: 29360487 | C89: 15620714 | D89: 46023.11 | E89: 46024 | F89: SUCCESS | G89: 7371 | H89: 13460 | I89: Marina Bay Sands SkyPark Observation Deck - Admission (Entry until 4:00 PM) | K89: BeMyGuest | L89: 111 | M89: BeMyGuest_API | N89: 2992 | O89: VENDOR_API | P89: PORTAL_DEPOSIT | Q89: Thomas Michael Mummert | R89: { "totalCount": 2, "personList": [{ "count": 1, "type": "ADULT", "priceNet": 33.2 }, { "count": 1, "type": "SENIOR", "priceNet": 28.2 }] } | S89: DATE_OF_BOOKING | T89: 3a69de2a-daa5-46f5-8764-8ba27b440e22 | U89: TODO | V89: RECONCILIATION_STATUS_AUTO_RECONCILED | W89: RECON | X89: 6 | Y89: 46023.11 | Z89: 46073.389 | AA89: SGD | AB89: 66 | AC89: 61.4 | AD89: { "extraCharges": [{ "amountInTourCurrency": 6.6, "chargeType": "PERCENTAGE", "extraChargeCode": "CONVENIENCE_FEE", "chargeValue": 10.0 }] } | AE89: TRUE | AF89: COMPLETED | AI89: FALSE | AL89: Reconciled | AM89: FALSE | AN89: Reconciliation ALREADY auto reconciled | AO89: 1 | AP89: 33.2 | AQ89: 33.2 | BS89: 1 | BT89: 28.2 | BU89: 28.2
A90: reconciliation_1866857740162579 | B90: 29360578 | C90: 15620781 | D90: 46023.118 | E90: 46037 | F90: SUCCESS | G90: 28844 | H90: 43120 | I90: Universal Studios Singapore - One Day Ticket | K90: BeMyGuest | L90: 111 | M90: BeMyGuest_API | N90: 2992 | O90: VENDOR_API | P90: PORTAL_DEPOSIT | Q90: Dmitri Mitchell | R90: { "totalCount": 5, "personList": [{ "count": 3, "type": "ADULT", "priceNet": 75.0 }, { "count": 2, "type": "CHILD", "priceNet": 66.0 }] } | S90: DATE_OF_BOOKING | T90: 6ffe79a3-cef2-4842-934c-d0d6f890bfdd | U90: TODO | V90: RECONCILIATION_STATUS_AUTO_RECONCILED | W90: RECON | X90: 6 | Y90: 46023.118 | Z90: 46073.389 | AA90: SGD | AB90: 367.53 | AC90: 357 | AD90: { } | AE90: TRUE | AF90: COMPLETED | AI90: FALSE | AL90: Reconciled | AM90: FALSE | AN90: Reconciliation ALREADY auto reconciled | AO90: 3 | AP90: 75 | AQ90: 225 | AU90: 2 | AV90: 66 | AW90: 132
A91: reconciliation_1866879784213533 | B91: 29360579 | C91: 15620786 | D91: 46023.118 | E91: 46023 | F91: SUCCESS | G91: 7443 | H91: 13581 | I91: S.E.A. Aquarium - Admission | K91: BeMyGuest | L91: 111 | M91: BeMyGuest_API | N91: 2992 | O91: VENDOR_API | P91: PORTAL_DEPOSIT | Q91: Boreth Vathana | R91: { "totalCount": 3, "personList": [{ "count": 2, "type": "ADULT", "priceNet": 47.0 }, { "count": 1, "type": "CHILD", "priceNet": 39.0 }] } | S91: DATE_OF_BOOKING | T91: 68a0edf2-8b37-400b-9915-e16f4307d93e | U91: TODO | V91: RECONCILIATION_STATUS_AUTO_RECONCILED | W91: RECON | X91: 6 | Y91: 46023.118 | Z91: 46073.389 | AA91: SGD | AB91: 153 | AC91: 133 | AD91: { "extraCharges": [{ "amountInTourCurrency": 15.3, "chargeType": "PERCENTAGE", "extraChargeCode": "CONVENIENCE_FEE", "chargeValue": 10.0 }] } | AE91: TRUE | AF91: COMPLETED | AI91: FALSE | AL91: Reconciled | AM91: FALSE | AN91: Reconciliation ALREADY auto reconciled | AO91: 2 | AP91: 47 | AQ91: 94 | AU91: 1 | AV91: 39 | AW91: 39
A92: reconciliation_1349784469968331 | B92: 29360580 | C92: 15620789 | D92: 46023.119 | E92: 46023 | F92: SUCCESS | G92: 7442 | H92: 43120 | I92: Universal Studios Singapore - One Day Ticket | K92: BeMyGuest | L92: 111 | M92: BeMyGuest_API | N92: 2992 | O92: VENDOR_API | P92: PORTAL_DEPOSIT | Q92: Matthew Philip west | R92: { "totalCount": 2, "personList": [{ "count": 2, "type": "ADULT", "priceNet": 75.0 }] } | S92: DATE_OF_BOOKING | T92: f7326a31-3aed-4c7a-a3c0-d0acbd56c7ab | U92: TODO | V92: RECONCILIATION_STATUS_AUTO_RECONCILED | W92: RECON | X92: 6 | Y92: 46023.119 | Z92: 46073.389 | AA92: SGD | AB92: 165.58 | AC92: 150 | AD92: { } | AE92: TRUE | AF92: COMPLETED | AI92: FALSE | AL92: Reconciled | AM92: FALSE | AN92: Reconciliation ALREADY auto reconciled | AO92: 2 | AP92: 75 | AQ92: 150
A93: reconciliation_1866939903590626 | B93: 29360581 | C93: 15620790 | D93: 46023.119 | E93: 46023 | F93: SUCCESS | G93: 7371 | H93: 13460 | I93: Marina Bay Sands SkyPark Observation Deck - Admission (Entry until 4:00 PM) | K93: BeMyGuest | L93: 111 | M93: BeMyGuest_API | N93: 2992 | O93: VENDOR_API | P93: PORTAL_DEPOSIT | Q93: Stephen Tracey | R93: { "totalCount": 4, "personList": [{ "count": 4, "type": "ADULT", "priceNet": 33.2 }] } | S93: DATE_OF_BOOKING | T93: c852962d-6bb5-405a-86e2-5cf518e6e32d | U93: TODO | V93: RECONCILIATION_STATUS_AUTO_RECONCILED | W93: RECON | X93: 6 | Y93: 46023.119 | Z93: 46073.389 | AA93: SGD | AB93: 140 | AC93: 132.8 | AD93: { "extraCharges": [{ "amountInTourCurrency": 14.0, "chargeType": "PERCENTAGE", "extraChargeCode": "CONVENIENCE_FEE", "chargeValue": 10.0 }] } | AE93: TRUE | AF93: COMPLETED | AI93: FALSE | AL93: Reconciled | AM93: FALSE | AN93: Reconciliation ALREADY auto reconciled | AO93: 4 | AP93: 33.2 | AQ93: 132.8
A94: reconciliation_1867045113817089 | B94: 29360594 | C94: 15620803 | D94: 46023.12 | E94: 46025 | F94: SUCCESS | G94: 7371 | H94: 55603 | I94: Marina Bay Sands SkyPark Observation Deck - Admission (Timeslot Entry from 5:00 PM) | K94: BeMyGuest | L94: 111 | M94: BeMyGuest_API | N94: 2992 | O94: VENDOR_API | P94: PORTAL_DEPOSIT | Q94: Melissa Mattei | R94: { "totalCount": 2, "personList": [{ "count": 2, "type": "ADULT", "priceNet": 37.2 }] } | S94: DATE_OF_BOOKING | T94: 0e38bb42-9797-40d1-b1ff-a875523a0b83 | U94: TODO | V94: RECONCILIATION_STATUS_AUTO_RECONCILED | W94: RECON | X94: 6 | Y94: 46023.12 | Z94: 46073.389 | AA94: SGD | AB94: 78 | AC94: 74.4 | AD94: { "extraCharges": [{ "amountInTourCurrency": 7.8, "chargeType": "PERCENTAGE", "extraChargeCode": "CONVENIENCE_FEE", "chargeValue": 10.0 }] } | AE94: TRUE | AF94: COMPLETED | AI94: FALSE | AL94: Reconciled | AM94: FALSE | AN94: Reconciliation ALREADY auto reconciled | AO94: 2 | AP94: 37.2 | AQ94: 74.4
A95: reconciliation_1349918228455952 | B95: 29360599 | C95: 15620806 | D95: 46023.12 | E95: 46023 | F95: SUCCESS | G95: 7442 | H95: 43120 | I95: Universal Studios Singapore - One Day Ticket | K95: BeMyGuest | L95: 111 | M95: BeMyGuest_API | N95: 2992 | O95: VENDOR_API | P95: PORTAL_DEPOSIT | Q95: Mykola Tolkachov | R95: { "totalCount": 2, "personList": [{ "count": 2, "type": "ADULT", "priceNet": 75.0 }] } | S95: DATE_OF_BOOKING | T95: c9047571-8e1c-4ef7-82ae-1f3807232528 | U95: TODO | V95: RECONCILIATION_STATUS_AUTO_RECONCILED | W95: RECON | X95: 6 | Y95: 46023.12 | Z95: 46073.389 | AA95: SGD | AB95: 165.58 | AC95: 150 | AD95: { } | AE95: TRUE | AF95: COMPLETED | AI95: FALSE | AL95: Reconciled | AM95: FALSE | AN95: Reconciliation ALREADY auto reconciled | AO95: 2 | AP95: 75 | AQ95: 150
A96: reconciliation_1350189273564608 | B96: 29360631 | C96: 15620834 | D96: 46023.123 | E96: 46023 | F96: SUCCESS | G96: 7443 | H96: 13581 | I96: S.E.A. Aquarium - Admission | K96: BeMyGuest | L96: 111 | M96: BeMyGuest_API | N96: 2992 | O96: VENDOR_API | P96: PORTAL_DEPOSIT | Q96: MAO RUI | R96: { "totalCount": 2, "personList": [{ "count": 2, "type": "ADULT", "priceNet": 47.0 }] } | S96: DATE_OF_BOOKING | T96: 5a9231d5-c290-4af8-a5c2-e82c52ad7fa1 | U96: TODO | V96: RECONCILIATION_STATUS_AUTO_RECONCILED | W96: RECON | X96: 6 | Y96: 46023.123 | Z96: 46073.389 | AA96: SGD | AB96: 110 | AC96: 94 | AD96: { "extraCharges": [{ "amountInTourCurrency": 11.0, "chargeType": "PERCENTAGE", "extraChargeCode": "CONVENIENCE_FEE", "chargeValue": 10.0 }] } | AE96: TRUE | AF96: COMPLETED | AI96: FALSE | AL96: Reconciled | AM96: FALSE | AN96: Reconciliation ALREADY auto reconciled | AO96: 2 | AP96: 47 | AQ96: 94
A97: reconciliation_1350230855751633 | B97: 29360646 | C97: 15620837 | D97: 46023.124 | E97: 46023 | F97: SUCCESS | G97: 12433 | H97: 23852 | I97: Entopia by Penang Butterfly Farm - Admission (Malaysian Citizen) | K97: BeMyGuest | L97: 111 | M97: BeMyGuest_API | N97: 2992 | O97: VENDOR_API | P97: PORTAL_DEPOSIT | Q97: Hazel Soh | R97: { "totalCount": 5, "personList": [{ "count": 3, "type": "ADULT", "priceNet": 46.3 }, { "count": 1, "type": "SENIOR", "priceNet": 32.3 }, { "count": 1, "type": "CHILD", "priceNet": 32.3 }] } | S97: DATE_OF_BOOKING | T97: 2ea9e9f5-a95b-411a-a6da-7576e9060529 | U97: TODO | V97: RECONCILIATION_STATUS_AUTO_RECONCILED | W97: RECON | X97: 6 | Y97: 46023.124 | Z97: 46073.389 | AA97: MYR | AB97: 256.5 | AC97: 202.93 | AD97: { } | AE97: TRUE | AF97: COMPLETED | AI97: FALSE | AL97: Reconciled | AM97: FALSE | AN97: Net price discrepancy | AO97: 3 | AP97: 46.3 | AQ97: 138.9 | AU97: 1 | AV97: 32.3 | AW97: 32.3 | BS97: 1 | BT97: 32.3 | BU97: 32.3
A98: reconciliation_1350316527395730 | B98: 29360651 | C98: 15620846 | D98: 46023.125 | E98: 46023 | F98: SUCCESS | G98: 7444 | H98: 13582 | I98: Adventure Cove Waterpark - One-Day Ticket | K98: BeMyGuest | L98: 111 | M98: BeMyGuest_API | N98: 2992 | O98: VENDOR_API | P98: PORTAL_DEPOSIT | Q98: Lau Kwee Ein | R98: { "totalCount": 3, "personList": [{ "count": 2, "type": "ADULT", "priceNet": 29.0 }, { "count": 1, "type": "CHILD", "priceNet": 25.0 }] } | S98: DATE_OF_BOOKING | T98: 98668a4c-ec8d-4e51-85e1-43857e01db1c | U98: TODO | V98: RECONCILIATION_STATUS_AUTO_RECONCILED | W98: RECON | X98: 6 | Y98: 46023.125 | Z98: 46073.389 | AA98: SGD | AB98: 112 | AC98: 83 | AD98: { "extraCharges": [{ "amountInTourCurrency": 5.6, "chargeType": "PERCENTAGE", "extraChargeCode": "CONVENIENCE_FEE", "chargeValue": 5.0 }] } | AE98: TRUE | AF98: COMPLETED | AI98: FALSE | AL98: Reconciled | AM98: FALSE | AN98: Reconciliation ALREADY auto reconciled | AO98: 2 | AP98: 29 | AQ98: 58 | AU98: 1 | AV98: 25 | AW98: 25
A99: reconciliation_1350483862984637 | B99: 29360678 | C99: 15620864 | D99: 46023.127 | E99: 46023 | F99: SUCCESS | G99: 23404 | H99: 76806 | I99: SEA LIFE Bangkok - Admission with Digiphoto (Peak) + 4D Movie | K99: BeMyGuest | L99: 111 | M99: BeMyGuest_Off Peak | N99: 1858 | O99: VENDOR_API | P99: PORTAL_DEPOSIT | Q99: Zaw Thet | R99: { "totalCount": 5, "personList": [{ "count": 3, "type": "ADULT", "priceNet": 1020.0 }, { "count": 2, "type": "CHILD", "priceNet": 900.0 }] } | S99: DATE_OF_BOOKING | T99: 0ffd90f4-cf0f-4512-93a6-a2d3ba923862 | U99: TODO | V99: RECONCILIATION_STATUS_MANUALLY_RECONCILED | W99: RECON | X99: 6 | Y99: 46023.127 | Z99: 46073.389 | AA99: THB | AB99: 6368.67 | AC99: 4833.22 | AD99: { } | AE99: TRUE | AF99: COMPLETED | AI99: FALSE | AL99: Reconciled | AM99: FALSE | AN99: Net price discrepancy | AO99: 3 | AP99: 1020 | AQ99: 3060 | AU99: 2 | AV99: 900 | AW99: 1800
A100: reconciliation_1905036533615610 | B100: 29360689 | C100: 15630276 | D100: 46023.56 | E100: 46024 | F100: SUCCESS | G100: 17825 | H100: 62106 | I100: TWO-ATTRACTION COMBO: Genting SkyWorlds + Skytropolis Indoor Theme Park (Non-Malaysian) | K100: BeMyGuest | L100: 111 | M100: BeMyGuest_API | N100: 2992 | O100: MANUAL | P100: PORTAL_DEPOSIT | Q100: Yuspa Muleya | R100: { "totalCount": 4, "personList": [{ "count": 2, "type": "NON_MALAYSIAN_ADULT", "priceNet": 178.0 }, { "count": 2, "type": "NON_MALAYSIAN_CHILD", "priceNet": 143.0 }] } | S100: DATE_OF_BOOKING | T100: LXS59Q7 | U100: TODO | V100: RECONCILIATION_STATUS_MANUALLY_RECONCILED | W100: RECON | X100: 3 | Y100: 46023.56 | Z100: 46073.389 | AA100: MYR | AB100: 730 | AC100: 702.08 | AD100: { } | AE100: FALSE | AF100: COMPLETED | AI100: FALSE | AL100: Reconciled | AM100: FALSE | AN100: Net price discrepancy | BJ100: 2 | BK100: 178 | BL100: 356 | BM100: 2 | BN100: 143 | BO100: 286
...
